Workbook

Sheet README
A1: PK Residential Master Material Database - v1.0
A2: Purpose | B2: Knowledge base for automatic MTO/BOQ generation of 5-10 marla houses (Islamabad/Rawalpindi). It stores HOW to calculate quantities (work items, measurement rules, coefficients, mixes, wastage) - not fixed quantities.
A3: Built from | B3: 31-sheet drawing set (5 Marla, Mr. Sameer Shah, IBN-E-ASGHAR & Associates, 17-11-2025), the existing CostLens v0.4.0 app, Pakistani estimating practice and codes (see Sources).
A4: Data model | B4: Drawings -> ELEMENTS (Element_Library) -> WORK ITEMS (Work_Items: measured BOQ items with measurement rules) -> RECIPES (coefficients per unit work) -> MATERIALS (Material_Master). Material qty = Σ(WI qty × coefficient) × (1 + wastage).
A5: Colour legend | B5: Blue text = editable input/assumption. Black = formula. Green = cross-sheet lookup. Yellow fill = to be filled by user (rates, counts). Light-blue headers in Material_Master = the 9 required columns.
A6: Material_Master | B6: One row per procurable material. Mat_ID is the permanent key (never reuse). Formula_Key = RECIPE means quantities come from Recipes; otherwise see Calc_Methods grammar.
A7: Work_Items | B7: Measured BOQ items with measurement rule, engine formula expression, required inputs, default spec and mapping to legacy app codes.
A8: Recipes | B8: Work item -> material coefficients (live formulas linked to Coefficients and Mix_Design). Changing a coefficient updates all recipes.
A9: Coefficients | B9: All engineering constants/allowances with units, basis and source. Derived coefficients are formulas.
A10: Mix_Design | B10: Nominal mixes (PCC 1:4:8, RCC 1:2:4, 1:1.5:3, mortars) -> cement bags, sand, crush per cft/m3 using dry volume factors.
A11: Wastage_Factors | B11: Default / min / max wastage per material class.
A12: Input_Dictionary | B12: Every parameter the AI extraction must produce or the user must confirm, with defaults, validation ranges and sample values.
A13: Element_Library | B13: Drawing elements the AI must detect, which attributes to extract and which work items they drive.
... A24: Key rules | B24: 1) Never invent quantities - missing inputs are flagged. 2) AI extracts, deterministic engine calculates. 3) Every quantity traceable to a drawing element + rule + coefficient. 4) User verifies low-confidence items before BOQ export.
A25: Counts | B25: ="Materials: "&(COUNTA(Material_Master!A:A)-1)&" | Work items: "&(COUNTA(Work_Items!A:A)-1)&" | Recipe lines: "&(COUNTA(Recipes!A:A)-1)&" | Coefficients: "&(COUNTA(Coefficients!A:A)-1) -> Materials: 309 | Work items: 101 | Recipe lines: 308 | Coefficients: 238
A26: Disclaimer | B26: Coefficients marked 'Allowance' are estimating defaults and must be calibrated; structural quantities require an engineer's design/BBS. Not a substitute for professional design.

Sheet Material_Master
A1: Mat_ID | B1: Category | C1: Subcategory | D1: Material Description | E1: Specification/Grade | F1: Unit | G1: Typical Application | H1: Calculation Basis/Formula | I1: Required Inputs | J1: Notes | K1: Scope | L1: Standard/Reference | M1: Takeoff Unit | N1: Formula_Key | O1: Linked Work Items | P1: Wastage_Key | Q1: Wastage % | R1: Construction Stage | S1: Tier/Option | T1: In Sample Drawings? | U1: Drawing Source | V1: Legacy App Code
A2: PRE-001 | B2: Preliminaries & Site | C2: Temporary works | D2: Site hoarding / temporary enclosure | E2: GI corrugated sheet 26-28 SWG on timber/pipe posts, or tarpaulin | F2: rft | G2: Open plot sides, safety & material security | H2: Q = open boundary length (plot perimeter - shared walls - existing walls) | I2: SITE_W, SITE_D, BOUNDARY_LEN | J2: Often omitted in estimates; reusable - consider hire. | K2: Complete | L2: - | M2: rft | N2: LEN(site.open_boundary) | P2: W_NIL | Q2: =IFERROR(INDEX(Wastage_Factors!$B$2:$B$60,MATCH(P2,Wastage_Factors!$A$2:$A$60,0)),0) -> 0 | R2: S0 | S2: Optional | T2: Not shown | U2: Site plan (sh.1)
A3: PRE-002 | B3: Preliminaries & Site | C3: Temporary services | D3: Temporary electricity connection & site DB | E3: IESCO temporary connection; site DB with RCCB | F3: LS | G3: Construction power (mixer, vibrator, lighting) | H3: 1 per project | I3: - | J3: Utility fees are statutory - verify with IESCO. | K3: Complete | L3: PETSAC-2014 | M3: LS | N3: LS | P3: W_NIL | Q3: =IFERROR(INDEX(Wastage_Factors!$B$2:$B$60,MATCH(P3,Wastage_Factors!$A$2:$A$60,0)),0) -> 0 | R3: S0 | S3: Standard | T3: Not shown | U3: -
A4: PRE-003 | B4: Preliminaries & Site | C4: Temporary services | D4: Site store, watchman shed & toilet | E4: Brick/steel temporary shed | F4: LS | G4: Material storage (cement must be kept dry) | H4: 1 per project | I4: - | K4: Complete | L4: - | M4: LS | N4: LS | P4: W_NIL | Q4: =IFERROR(INDEX(Wastage_Factors!$B$2:$B$60,MATCH(P4,Wastage_Factors!$A$2:$A$60,0)),0) -> 0 | R4: S0 | S4: Standard | T4: Not shown | U4: -
A5: PRE-004 | B5: Preliminaries & Site | C5: Setting out | D5: Setting-out consumables | E5: Lime powder, pegs, string line, profile boards | F5: LS | G5: Layout of foundations & walls | H5: 1 per project | I5: - | K5: Complete | L5: - | M5: LS | N5: LS | P5: W_NIL | Q5: =IFERROR(INDEX(Wastage_Factors!$B$2:$B$60,MATCH(P5,Wastage_Factors!$A$2:$A$60,0)),0) -> 0 | R5: S0 | S5: Standard | T5: Implied | U5: Foundation plan
A6: PRE-005 | B6: Preliminaries & Site | C6: Investigations | D6: Soil investigation (SBC test) | E6: 2 boreholes / test pits, SBC & soil classification | F6: Nos | G6: Confirms footing sizes & founding depth | H6: Min 1-2 per plot | I6: PLOT_MARLA | J6: Foundation drawings assume SBC; none stated. Strongly recommended in Islamabad (variable clay/shale). | K6: Complete | L6: BCP-2021 Ch.18 | M6: Nos | N6: COUNT(1..2) | P6: W_NIL | Q6: =IFERROR(INDEX(Wastage_Factors!$B$2:$B$60,MATCH(P6,Wastage_Factors!$A$2:$A$60,0)),0) -> 0 | R6: S0 | S6: Recommended | T6: Not shown | U6: -
A7: PRE-006 | B7: Preliminaries & Site | C7: Quality testing | D7: Material testing (concrete cubes, rebar tensile, bricks) | E7: Cubes 3 per pour (7/28 day); rebar tensile/bend per lot | F7: Nos | G7: QA/QC | H7: Cubes = 3 x number of pours; rebar tests = 1 per lot/diameter | I7: SLAB_AREA, N_FLOORS | K7: Complete | L7: ASTM C39 / A615 | M7: Nos | N7: COUNT(pours)*3 | P7: W_NIL | Q7: =IFERROR(INDEX(Wastage_Factors!$B$2:$B$60,MATCH(P7,Wastage_Factors!$A$2:$A$60,0)),0) -> 0 | R7: S1 | S7: Recommended | T7: Not shown | U7: -
A8: PRE-007 | B8: Preliminaries & Site | C8: Safety | D8: PPE, safety nets, barricading | E8: Helmets, shoes, harness for roof works, edge protection | F8: LS | G8: Site safety | H8: 1 per project | I8: - | K8: Complete | L8: - | M8: LS | N8: LS | P8: W_NIL | Q8: =IFERROR(INDEX(Wastage_Factors!$B$2:$B$60,MATCH(P8,Wastage_Factors!$A$2:$A$60,0)),0) -> 0 | R8: S0 | S8: Standard | T8: Not shown | U8: -
A9: EW-001 | B9: Earthwork & Site Prep | C9: Excavation | D9: Surplus excavated earth - disposal (tractor trolley loads) | E9: Carted to approved dump | F9: cft | G9: Excavated material not reused | H9: Q = Σ [WI qty × Recipe coefficient] × (1 + Wastage %) — driven by WI-EW-09 (see Recipes) | I9: FDN_STRIP_LEN, FDN_SECTION, FTG_ISO, TANK_* | J9: Loose volume = bank volume x bulking (~1.25). | K9: Structure | L9: - | M9: cft | N9: RECIPE | O9: WI-EW-09 | P9: W_NIL | Q9: =IFERROR(INDEX(Wastage_Factors!$B$2:$B$60,MATCH(P9,Wastage_Factors!$A$2:$A$60,0)),0) -> 0 | R9: S1 | S9: Standard | T9: Implied | U9: Foundation details (sh.14-15)
A10: EW-002 | B10: Earthwork & Site Prep | C10: Filling | D10: Imported earth for plinth filling | E10: Good earth, free of organics, compacted in 6in layers at OMC | F10: cft | G10: Plinth fill between foundation walls up to floor base level | H10: Q = Σ [WI qty × Recipe coefficient] × (1 + Wastage %) — driven by WI-EW-05 (see Recipes) | I10: H_PLINTH, ROOM(GF), T_FLOOR_BUILDUP | J10: Drawing plinth 1'-6" above road; porch level differs. | K10: Structure | L10: - | M10: cft | N10: RECIPE | O10: WI-EW-05 | P10: W_EARTH | Q10: =IFERROR(INDEX(Wastage_Factors!$B$2:$B$60,MATCH(P10,Wastage_Factors!$A$2:$A$60,0)),0) -> 0 | R10: S1 | S10: Standard | T10: Implied | U10: Elevations: plinth 1'-6" (sh.5-7) | V10: PLINTH-FILL-01
A11: EW-003 | B11: Earthwork & Site Prep | C11: Filling | D11: Sand filling under floors (local 'bhal' / kassi sand) | E11: Clean fine sand, watered & compacted | F11: cft | G11: Levelling layer under soling/PCC | H11: Q = Σ [WI qty × Recipe coefficient] × (1 + Wastage %) — driven by WI-EW-06 (see Recipes) | I11: ROOM(GF) | K11: Structure | L11: - | M11: cft | N11: RECIPE | O11: WI-EW-06 | P11: W_SAND | Q11: =IFERROR(INDEX(Wastage_Factors!$B$2:$B$60,MATCH(P11,Wastage_Factors!$A$2:$A$60,0)),0) -> 0.1 | R11: S1 | S11: Standard | T11: Not shown | U11: -
A12: EW-004 | B12: Earthwork & Site Prep | C12: Treatment | D12: Anti-termite chemical | E12: Chlorpyrifos 20% EC or imidacloprid, diluted per label | F12: L | G12: Trench bottoms & sides, plinth fill, under floors | H12: Q = Σ [WI qty × Recipe coefficient] × (1 + Wastage %) — driven by WI-EW-07 (see Recipes) | I12: FDN_STRIP_LEN, ROOM(GF) | J12: Not in drawing set; standard in PK specs. | K12: Structure | L12: Manufacturer label | M12: sft | N12: RECIPE | O12: WI-EW-07 | P12: W_MISC | Q12: =IFERROR(INDEX(Wastage_Factors!$B$2:$B$60,MATCH(P12,Wastage_Factors!$A$2:$A$60,0)),0) -> 0.05 | R12: S1 | S12: Recommended | T12: Not shown | U12: - | V12: AT-01
A13: EW-005 | B13: Earthwork & Site Prep | C13: Dewatering | D13: Dewatering (if water table encountered) | E13: Pump hire | F13: LS | G13: Excavation below water table | H13: Contingent on soil report | I13: Soil report | K13: Structure | L13: - | M13: LS | N13: LS | P13: W_NIL | Q13: =IFERROR(INDEX(Wastage_Factors!$B$2:$B$60,MATCH(P13,Wastage_Factors!$A$2:$A$60,0)),0) -> 0 | R13: S1 | S13: Contingent | T13: Not shown | U13: -
A14: EW-006 | B14: Earthwork & Site Prep | C14: Filling | D14: Brick ballast / khangar for sub-base | E14: Over-burnt brick bats 1.5-2in | F14: cft | G14: Sub-base under porch/driveway where specified | H14: Q = area x thickness x 1.15 × (1 + Wastage %) | I14: PAVING_AREA | K14: Structure | L14: - | M14: cft | N14: AREA(paving)*T | P14: W_AGG | Q14: =IFERROR(INDEX(Wastage_Factors!$B$2:$B$60,MATCH(P14,Wastage_Factors!$A$2:$A$60,0)),0) -> 0.075 | R14: S8 | S14: Optional | T14: Not shown | U14: -
A15: EW-007 | B15: Earthwork & Site Prep | C15: Membranes | D15: Polythene vapour barrier under GF floor | E15: 500-1000 gauge LDPE | F15: sft | G15: Below GF floor PCC | H15: Q = Σ [WI qty × Recipe coefficient] × (1 + Wastage %) — driven by WI-EW-08 (see Recipes) | I15: ROOM(GF) | K15: Structure | L15: - | M15: sft | N15: RECIPE | O15: WI-EW-08 | P15: W_POLY | Q15: =IFERROR(INDEX(Wastage_Factors!$B$2:$B$60,MATCH(P15,Wastage_Factors!$A$2:$A$60,0)),0) -> 0.05 | R15: S1 | S15: Recommended | T15: Not shown | U15: -
A16: CON-001 | B16: Concrete & Aggregates | C16: Binders | D16: Ordinary Portland Cement (OPC) - 50 kg bag | E16: Type I, 42.5 grade; fresh stock (<60 days) | F16: bag | G16: All concrete, mortar, plaster, screeds, DPC, bedding | H16: Q = Σ [WI qty × Recipe coefficient] × (1 + Wastage %) — driven by WI-CN-01, WI-CN-02, WI-CN-03, WI-CN-04, WI-CN-05, WI-CN-06, WI-CN-07, WI-CN-08, WI-CN-09, WI-CN-10, WI-CN-11, WI-CN-12, WI-CN-13, WI-MS-01, WI-MS-02, WI-MS-03, WI-MS-04, WI-MS-06, WI-PL-01, WI-PL-02, WI-PL-03, WI-PL-04, WI-WP-01, WI-WP-02, WI-WP-04, WI-FL-01, WI-FL-02, WI-FL-04, WI-PB-12, WI-PB-13, WI-EX-01 (see Recipes) | I16: All concrete/mortar work items | J16: North-region brands: Bestway, Fauji, DG Khan, Askari, Kohat, Cherat, Maple Leaf, Lucky. Cement is ordered in phases - see Construction Stage. | K16: Structure | L16: PS 232 / ASTM C150 | M16: bag | N16: RECIPE | O16: WI-CN-01, WI-CN-02, WI-CN-03, WI-CN-04, WI-CN-05, WI-CN-06, WI-CN-07, WI-CN-08, WI-CN-09, WI-CN-10, WI-CN-11, WI-CN-12, WI-CN-13, WI-MS-01, WI-MS-02, WI-MS-03, WI-MS-04, WI-MS-06, WI-PL-01, WI-PL-02, WI-PL-03, WI-PL-04, WI-WP-01, WI-WP-02, WI-WP-04, WI-FL-01, WI-FL-02, WI-FL-04, WI-PB-12, WI-PB-13, WI-EX-01 | P16: W_CEM | Q16: =IFERROR(INDEX(Wastage_Factors!$B$2:$B$60,MATCH(P16,Wastage_Factors!$A$2:$A$60,0)),0) -> 0.02 | R16: S1-S6 | S16: Standard | T16: Specified | U16: sh.14-16, 24 | V16: BEAM-CONC-01, COL-CONC-01, DPC-01, FDN-MAS-01, FLR-01, FTG-CONC-01, GF-PCC-01, LINTEL-CONC-01, MAS-01, PCC-01, PLAS-01, PLAS-02, PLAS-03, ROOF-01, SLAB-CONC-01, STAIR-CONC-01, WP-01, WSD-01
A17: CON-002 | B17: Concrete & Aggregates | C17: Binders | D17: Sulphate Resisting Cement (SRC) | E17: ASTM C150 Type V | F17: bag | G17: Foundations, septic tank, UG tank where sulphate/saline soil | H17: Replace CON-001 in substructure items if soil report indicates sulphates × (1 + Wastage %) | I17: Soil report | K17: Structure | L17: ASTM C150 | M17: bag | N17: RECIPE(substitute) | P17: W_CEM | Q17: =IFERROR(INDEX(Wastage_Factors!$B$2:$B$60,MATCH(P17,Wastage_Factors!$A$2:$A$60,0)),0) -> 0.02 | R17: S1 | S17: Contingent | T17: Not shown | U17: -
A18: CON-003 | B18: Concrete & Aggregates | C18: Binders | D18: White cement | E18: White Portland cement | F18: kg | G18: Marble joints, tile grout (economy), pointing | H18: Q = Σ [WI qty × Recipe coefficient] × (1 + Wastage %) — driven by WI-FL-04 (see Recipes) | I18: ROOM | K18: Architecture | L18: - | M18: kg | N18: RECIPE | O18: WI-FL-04 | P18: W_CEM | Q18: =IFERROR(INDEX(Wastage_Factors!$B$2:$B$60,MATCH(P18,Wastage_Factors!$A$2:$A$60,0)),0) -> 0.02 | R18: S6 | S18: Standard | T18: Not shown | U18: - | V18: FLR-01
A19: CON-004 | B19: Concrete & Aggregates | C19: Fine aggregate | D19: Coarse sand for concrete (Lawrencepur) | E19: FM >= 2.5, silt < 3% | F19: cft | G19: RCC, PCC, DPC | H19: Q = Σ [WI qty × Recipe coefficient] × (1 + Wastage %) — driven by WI-CN-01, WI-CN-02, WI-CN-03, WI-CN-04, WI-CN-05, WI-CN-06, WI-CN-07, WI-CN-08, WI-CN-09, WI-CN-10, WI-CN-11, WI-CN-12, WI-CN-13, WI-EX-01 (see Recipes) | I19: Concrete work items | J19: Lawrencepur is the default concrete sand in Islamabad/Rawalpindi. Trucks/trolleys vary in cft - verify load size. | K19: Structure | L19: ASTM C33 | M19: cft | N19: RECIPE | O19: WI-CN-01, WI-CN-02, WI-CN-03, WI-CN-04, WI-CN-05, WI-CN-06, WI-CN-07, WI-CN-08, WI-CN-09, WI-CN-10, WI-CN-11, WI-CN-12, WI-CN-13, WI-EX-01 | P19: W_SAND | Q19: =IFERROR(INDEX(Wastage_Factors!$B$2:$B$60,MATCH(P19,Wastage_Factors!$A$2:$A$60,0)),0) -> 0.1 | R19: S1-S3 | S19: Standard | T19: Implied | U19: - | V19: BEAM-CONC-01, COL-CONC-01, DPC-01, FTG-CONC-01, GF-PCC-01, LINTEL-CONC-01, PCC-01, SLAB-CONC-01, STAIR-CONC-01
A20: CON-005 | B20: Concrete & Aggregates | C20: Fine aggregate | D20: Sand for masonry & plaster | E20: Screened, FM 1.8-2.5, clean | F20: cft | G20: Brick mortar, plaster, tile bedding, screeds | H20: Q = Σ [WI qty × Recipe coefficient] × (1 + Wastage %) — driven by WI-MS-01, WI-MS-02, WI-MS-03, WI-MS-04, WI-MS-05, WI-MS-06, WI-PL-01, WI-PL-02, WI-PL-03, WI-PL-04, WI-WP-01, WI-WP-02, WI-WP-04, WI-FL-01, WI-FL-02, WI-FL-04, WI-PB-12, WI-PB-13, WI-EX-01 (see Recipes) | I20: Masonry/plaster work items | J20: Can be same source as CON-004; separate line allows different pricing (e.g. fine plaster sand). | K20: Structure | L20: ASTM C144 | M20: cft | N20: RECIPE | O20: WI-MS-01, WI-MS-02, WI-MS-03, WI-MS-04, WI-MS-05, WI-MS-06, WI-PL-01, WI-PL-02, WI-PL-03, WI-PL-04, WI-WP-01, WI-WP-02, WI-WP-04, WI-FL-01, WI-FL-02, WI-FL-04, WI-PB-12, WI-PB-13, WI-EX-01 | P20: W_SAND | Q20: =IFERROR(INDEX(Wastage_Factors!$B$2:$B$60,MATCH(P20,Wastage_Factors!$A$2:$A$60,0)),0) -> 0.1 | R20: S1-S6 | S20: Standard | T20: Implied | U20: - | V20: FDN-MAS-01, FLR-01, GF-SOL-01, MAS-01, PLAS-01, PLAS-02, PLAS-03, ROOF-01, WP-01, WSD-01
A21: CON-006 | B21: Concrete & Aggregates | C21: Coarse aggregate | D21: Crushed stone 3/4in down (Margalla crush) | E21: Graded 3/4in-#4, clean, angular | F21: cft | G21: RCC footings, columns, beams, slabs, tanks | H21: Q = Σ [WI qty × Recipe coefficient] × (1 + Wastage %) — driven by WI-CN-03, WI-CN-04, WI-CN-05, WI-CN-06, WI-CN-07, WI-CN-08, WI-CN-11 (see Recipes) | I21: Concrete work items | J21: Margalla crush is local to Islamabad; Sargodha crush alternative. | K21: Structure | L21: ASTM C33 | M21: cft | N21: RECIPE | O21: WI-CN-03, WI-CN-04, WI-CN-05, WI-CN-06, WI-CN-07, WI-CN-08, WI-CN-11 | P21: W_AGG | Q21: =IFERROR(INDEX(Wastage_Factors!$B$2:$B$60,MATCH(P21,Wastage_Factors!$A$2:$A$60,0)),0) -> 0.075 | R21: S1-S3 | S21: Standard | T21: Implied | U21: - | V21: BEAM-CONC-01, COL-CONC-01, FTG-CONC-01, SLAB-CONC-01, STAIR-CONC-01
A22: CON-007 | B22: Concrete & Aggregates | C22: Coarse aggregate | D22: Crushed stone 1/2in / 3/8in down | E22: Graded | F22: cft | G22: DPC, lintels, chajjas, apron, thin sections | H22: Q = Σ [WI qty × Recipe coefficient] × (1 + Wastage %) — driven by WI-CN-09, WI-CN-10, WI-CN-12, WI-CN-13 (see Recipes) | I22: DPC, lintels | K22: Structure | L22: ASTM C33 | M22: cft | N22: RECIPE | O22: WI-CN-09, WI-CN-10, WI-CN-12, WI-CN-13 | P22: W_AGG | Q22: =IFERROR(INDEX(Wastage_Factors!$B$2:$B$60,MATCH(P22,Wastage_Factors!$A$2:$A$60,0)),0) -> 0.075 | R22: S1-S2 | S22: Standard | T22: Implied | U22: sh.14 | V22: DPC-01, LINTEL-CONC-01
A23: CON-008 | B23: Concrete & Aggregates | C23: Coarse aggregate | D23: Crushed stone 1.5in down (or brick ballast) | E23: For lean concrete | F23: cft | G23: PCC 1:4:8 foundation base, floor base, manholes | H23: Q = Σ [WI qty × Recipe coefficient] × (1 + Wastage %) — driven by WI-CN-01, WI-CN-02, WI-PB-12, WI-PB-13, WI-EX-01 (see Recipes) | I23: PCC work items | K23: Structure | L23: - | M23: cft | N23: RECIPE | O23: WI-CN-01, WI-CN-02, WI-PB-12, WI-PB-13, WI-EX-01 | P23: W_AGG | Q23: =IFERROR(INDEX(Wastage_Factors!$B$2:$B$60,MATCH(P23,Wastage_Factors!$A$2:$A$60,0)),0) -> 0.075 | R23: S1 | S23: Standard | T23: Specified | U23: sh.14-16, 24 | V23: GF-PCC-01, PCC-01, WSD-01
A24: CON-009 | B24: Concrete & Aggregates | C24: Ready-mix | D24: Ready-mix concrete (alternative to site mix) | E24: 3000-4000 psi, slump per element | F24: cft | G24: Roof/floor slabs where access allows | H24: Q = RCC volume of selected elements x (1 + wastage); replaces CON-001/004/006 for those elements | I24: SLAB_AREA, T_SLAB | J24: Pump charges extra; streets in 5-marla sectors may limit truck access. | K24: Structure | L24: ASTM C94 | M24: m3 | N24: VOL(slab)*(1+w) | P24: W_CONC_RMC | Q24: =IFERROR(INDEX(Wastage_Factors!$B$2:$B$60,MATCH(P24,Wastage_Factors!$A$2:$A$60,0)),0) -> 0.03 | R24: S2 | S24: Optional | T24: Not shown | U24: -
A25: CON-010 | B25: Concrete & Aggregates | C25: Admixtures | D25: Plasticizer / superplasticizer | E25: ASTM C494 Type A/F | F25: L | G25: Slabs/columns for workability at low w/c | H25: Q = cement bags in RCC x dosage (typ. 0.25-0.5 L/bag) × (1 + Wastage %) | I25: Cement qty (RCC) | K25: Structure | L25: ASTM C494 | M25: L | N25: RECIPE(cement_RCC)*dose | P25: W_MISC | Q25: =IFERROR(INDEX(Wastage_Factors!$B$2:$B$60,MATCH(P25,Wastage_Factors!$A$2:$A$60,0)),0) -> 0.05 | R25: S2 | S25: Optional | T25: Not shown | U25: -
A26: CON-011 | B26: Concrete & Aggregates | C26: Admixtures | D26: Bonding agent (SBR latex) | E26: SBR emulsion | F26: L | G26: Plaster on RCC surfaces, repairs, cold joints | H26: Q = RCC exposed area to be plastered x 0.01 L/sft × (1 + Wastage %) | I26: SLAB_AREA | K26: Structure | L26: - | M26: sft | N26: AREA(rcc_soffit)*0.01 | P26: W_MISC | Q26: =IFERROR(INDEX(Wastage_Factors!$B$2:$B$60,MATCH(P26,Wastage_Factors!$A$2:$A$60,0)),0) -> 0.05 | R26: S5 | S26: Optional | T26: Not shown | U26: -
A27: CON-012 | B27: Concrete & Aggregates | C27: Curing | D27: Curing hessian / curing compound | E27: Jute hessian or wax-based compound | F27: sft | G27: Slabs, columns curing (7-14 days) | H27: Q = slab area x 1.1 (reused) × (1 + Wastage %) | I27: SLAB_AREA | K27: Structure | L27: ASTM C309 | M27: sft | N27: AREA(slab)*1.1/reuse | P27: W_MISC | Q27: =IFERROR(INDEX(Wastage_Factors!$B$2:$B$60,MATCH(P27,Wastage_Factors!$A$2:$A$60,0)),0) -> 0.05 | R27: S2 | S27: Standard | T27: Not shown | U27: -
A28: CON-013 | B28: Concrete & Aggregates | C28: Accessories | D28: Cover blocks / rebar spacers | E28: Concrete or PVC, 3/4in slabs, 1.5in beams/cols, 3in footings | F28: Nos | G28: Maintain concrete cover | H28: Q = Σ [WI qty × Recipe coefficient] × (1 + Wastage %) — driven by WI-CN-03, WI-CN-04, WI-CN-05, WI-CN-06, WI-CN-07, WI-CN-08, WI-CN-09 (see Recipes) | I28: RCC work items | K28: Structure | L28: ACI 318 cover | M28: Nos | N28: RECIPE | O28: WI-CN-03, WI-CN-04, WI-CN-05, WI-CN-06, WI-CN-07, WI-CN-08, WI-CN-09 | P28: W_MISC | Q28: =IFERROR(INDEX(Wastage_Factors!$B$2:$B$60,MATCH(P28,Wastage_Factors!$A$2:$A$60,0)),0) -> 0.05 | R28: S1-S2 | S28: Standard | T28: Not shown | U28: - | V28: BEAM-CONC-01, COL-CONC-01, FTG-CONC-01, LINTEL-CONC-01, SLAB-CONC-01, STAIR-CONC-01
A29: CON-014 | B29: Concrete & Aggregates | C29: Aggregate | D29: Stone/marble chips 1/8-3/8in | E29: Topping (drawing: 1.5in chips) | F29: cft | G29: Tank base topping, terrazzo/chips flooring | H29: Q = area x thickness x dry factor 1.3 × (1 + Wastage %) | I29: TANK_UG | J29: Drawing notes '1.5in thick chips' in UG/septic tank details. | K29: Structure | L29: - | M29: sft | N29: AREA*T*1.3 | P29: W_AGG | Q29: =IFERROR(INDEX(Wastage_Factors!$B$2:$B$60,MATCH(P29,Wastage_Factors!$A$2:$A$60,0)),0) -> 0.075 | R29: S1 | S29: Standard | T29: Specified | U29: Tanks detail (sh.16)
A30: RBR-001 | B30: Reinforcement & Steel | C30: Rebar | D30: Deformed bar #3 (10 mm / 3/8in) | E30: ASTM A615 Grade 60 (fy 60,000 psi / 420 MPa); 0.56 kg/m | F30: kg | G30: Ties/stirrups, slab distribution, tank walls (3/8in @6in c/c per drawing) | H30: Q = Σ [WI qty × Recipe coefficient] × (1 + Wastage %) — driven by WI-RF-01, WI-RF-02, WI-RF-03, WI-RF-04, WI-RF-05, WI-RF-06, WI-RF-07 (see Recipes) | I30: BBS or member volumes + K_ST ratios | J30: Mills: Amreli, Mughal, Ittehad, Naveena, Agha, AFCO. Standard length 12 m (40 ft). Purchase in tons. | K30: Structure | L30: ASTM A615 Gr60 | M30: kg | N30: RECIPE | O30: WI-RF-01, WI-RF-02, WI-RF-03, WI-RF-04, WI-RF-05, WI-RF-06, WI-RF-07 | P30: W_STEEL | Q30: =IFERROR(INDEX(Wastage_Factors!$B$2:$B$60,MATCH(P30,Wastage_Factors!$A$2:$A$60,0)),0) -> 0.03 | R30: S1-S2 | S30: Standard | T30: Specified | U30: sh.14, 16 | V30: BEAM-STEEL-01, COL-STEEL-01, FTG-STEEL-01, LINTEL-STEEL-01, SLAB-STEEL-01, STAIR-STEEL-01
A31: RBR-002 | B31: Reinforcement & Steel | C31: Rebar | D31: Deformed bar #4 (12 mm / 1/2in) | E31: ASTM A615 Gr60; 0.99 kg/m | F31: kg | G31: Slab main bars, column/beam bars, footing mats | H31: Q = Σ [WI qty × Recipe coefficient] × (1 + Wastage %) — driven by WI-RF-01, WI-RF-02, WI-RF-03, WI-RF-04, WI-RF-05, WI-RF-06, WI-PB-12 (see Recipes) | I31: BBS | K31: Structure | L31: ASTM A615 Gr60 | M31: kg | N31: RECIPE | O31: WI-RF-01, WI-RF-02, WI-RF-03, WI-RF-04, WI-RF-05, WI-RF-06, WI-PB-12 | P31: W_STEEL | Q31: =IFERROR(INDEX(Wastage_Factors!$B$2:$B$60,MATCH(P31,Wastage_Factors!$A$2:$A$60,0)),0) -> 0.03 | R31: S1-S2 | S31: Standard | T31: Specified | U31: sh.14 (sec AA #4) | V31: BEAM-STEEL-01, COL-STEEL-01, FTG-STEEL-01, LINTEL-STEEL-01, SLAB-STEEL-01, STAIR-STEEL-01, WSD-01
A32: RBR-003 | B32: Reinforcement & Steel | C32: Rebar | D32: Deformed bar #5 (16 mm / 5/8in) | E32: ASTM A615 Gr60; 1.58 kg/m | F32: kg | G32: Beam & column main bars | H32: Q = Σ [WI qty × Recipe coefficient] × (1 + Wastage %) — driven by WI-RF-02, WI-RF-03 (see Recipes) | I32: BBS | J32: No beam/column schedule in drawing set - quantity from ratio only until structural drawings are issued. | K32: Structure | L32: ASTM A615 Gr60 | M32: kg | N32: RECIPE | O32: WI-RF-02, WI-RF-03 | P32: W_STEEL | Q32: =IFERROR(INDEX(Wastage_Factors!$B$2:$B$60,MATCH(P32,Wastage_Factors!$A$2:$A$60,0)),0) -> 0.03 | R32: S2 | S32: Standard | T32: Not shown | U32: Not detailed | V32: BEAM-STEEL-01, COL-STEEL-01
A33: RBR-004 | B33: Reinforcement & Steel | C33: Rebar | D33: Deformed bar #6 (19/20 mm / 3/4in) | E33: ASTM A615 Gr60; 2.24 kg/m | F33: kg | G33: Longer-span beams, 10-marla columns, cantilevers | H33: Q = BBS kg for #6 bars x (1 + w) | I33: BBS | K33: Structure | L33: ASTM A615 Gr60 | M33: kg | N33: BBS(#6) | P33: W_STEEL | Q33: =IFERROR(INDEX(Wastage_Factors!$B$2:$B$60,MATCH(P33,Wastage_Factors!$A$2:$A$60,0)),0) -> 0.03 | R33: S2 | S33: Contingent | T33: Not shown | U33: Not detailed
A34: RBR-006 | B34: Reinforcement & Steel | C34: Accessories | D34: Binding wire (black annealed) | E34: 18/20 SWG | F34: kg | G34: Tying all reinforcement | H34: Q = Σ [WI qty × Recipe coefficient] × (1 + Wastage %) — driven by WI-RF-01, WI-RF-02, WI-RF-03, WI-RF-04, WI-RF-05, WI-RF-06, WI-RF-07 (see Recipes) | I34: Total rebar kg | J34: ~10 kg per tonne of steel. | K34: Structure | L34: - | M34: kg | N34: RECIPE | O34: WI-RF-01, WI-RF-02, WI-RF-03, WI-RF-04, WI-RF-05, WI-RF-06, WI-RF-07 | P34: W_NIL | Q34: =IFERROR(INDEX(Wastage_Factors!$B$2:$B$60,MATCH(P34,Wastage_Factors!$A$2:$A$60,0)),0) -> 0 | R34: S1-S2 | S34: Standard | T34: Implied | U34: - | V34: BEAM-STEEL-01, COL-STEEL-01, FTG-STEEL-01, LINTEL-STEEL-01, SLAB-STEEL-01, STAIR-STEEL-01
A35: RBR-007 | B35: Reinforcement & Steel | C35: Accessories | D35: Chairs / bar supports | E35: Fabricated from #3/#4 bars | F35: kg | G35: Top-mat support in slabs/footings | H35: Q = 1-1.5% of slab + footing steel (if not in BBS) × (1 + Wastage %) | I35: BBS | J35: Usually included in BBS/ratio - avoid double counting. | K35: Structure | L35: - | M35: kg | N35: (WI-RF-01+WI-RF-04)*0.015 | P35: W_STEEL | Q35: =IFERROR(INDEX(Wastage_Factors!$B$2:$B$60,MATCH(P35,Wastage_Factors!$A$2:$A$60,0)),0) -> 0.03 | R35: S2 | S35: Standard | T35: Not shown | U35: -
A36: RBR-008 | B36: Reinforcement & Steel | C36: Mesh | D36: Welded wire mesh | E36: e.g. 6mm @ 6in | F36: sft | G36: Porch/driveway slabs, screed crack control | H36: Q = area x 1.1 (laps) × (1 + Wastage %) | I36: PAVING_AREA | K36: Structure | L36: ASTM A1064 | M36: sft | N36: AREA*1.1 | P36: W_STEEL | Q36: =IFERROR(INDEX(Wastage_Factors!$B$2:$B$60,MATCH(P36,Wastage_Factors!$A$2:$A$60,0)),0) -> 0.03 | R36: S8 | S36: Optional | T36: Not shown | U36: -
A37: RBR-009 | B37: Reinforcement & Steel | C37: Structural steel | D37: MS sections (angles, channels, pipes, flats) | E37: ASTM A36 / local MS | F37: kg | G37: Tank stand, canopy frames, gate frame, manhole frames | H37: Q = sum(member length x unit weight) from details × (1 + Wastage %) | I37: Details | J37: Manhole cover frames specified as 2x2x1/4in angle; 2.5x2.5x1/2in CI angle frame. | K37: Structure | L37: ASTM A36 | M37: kg | N37: SUM(len*kg_m) | P37: W_STEEL_SECT | Q37: =IFERROR(INDEX(Wastage_Factors!$B$2:$B$60,MATCH(P37,Wastage_Factors!$A$2:$A$60,0)),0) -> 0.05 | R37: S2-S8 | S37: Standard | T37: Specified | U37: sh.24 (2x2x1/4 angle frames)
A38: RBR-010 | B38: Reinforcement & Steel | C38: Seismic | D38: Wall ties / dowels at column-wall & wall-wall junctions | E38: #3 bar 2ft long every 4th course, or GI hoop iron | F38: kg | G38: Tie masonry to RCC columns; seismic zone 2B | H38: Q = junction count x (wall height / 1ft) / 4 x 0.61 m x 0.56 kg/m × (1 + Wastage %) | I38: WALL_CL_LEN, COL | J38: Islamabad/Rawalpindi are seismic zone 2B (BCP SP-2007 Table 2.2). | K38: Structure | L38: BCP-2021 masonry provisions | M38: kg | N38: COUNT(junctions)*H/1*0.25*0.34 | P38: W_STEEL | Q38: =IFERROR(INDEX(Wastage_Factors!$B$2:$B$60,MATCH(P38,Wastage_Factors!$A$2:$A$60,0)),0) -> 0.03 | R38: S2 | S38: Recommended | T38: Not shown | U38: Not shown
A39: FRM-001 | B39: Formwork & Temporary Works | C39: Shuttering | D39: Steel shuttering plates (hire) | E39: Steel plates on props | F39: sft | G39: Slab & beam soffits | H39: Q = Σ [WI qty × Recipe coefficient] × (1 + Wastage %) — driven by WI-FW-01 (see Recipes) | I39: SLAB_AREA, BEAM | J39: Commonly hired per sft per cast in PK. | K39: Structure | L39: - | M39: sft | N39: RECIPE | O39: WI-FW-01 | P39: W_NIL | Q39: =IFERROR(INDEX(Wastage_Factors!$B$2:$B$60,MATCH(P39,Wastage_Factors!$A$2:$A$60,0)),0) -> 0 | R39: S2 | S39: Standard | T39: Not shown | U39: - | V39: FORM-SLAB-01
A40: FRM-002 | B40: Formwork & Temporary Works | C40: Shuttering | D40: Plywood (shuttering grade 12-18mm) / timber planks | E40: Film-faced or commercial ply | F40: sft | G40: Columns, footings, lintels, stairs, tanks | H40: Q = Σ [WI qty × Recipe coefficient] × (1 + Wastage %) — driven by WI-FW-02 (see Recipes) | I40: Contact areas | K40: Structure | L40: - | M40: sft | N40: RECIPE | O40: WI-FW-02 | P40: W_WOOD_BOARD | Q40: =IFERROR(INDEX(Wastage_Factors!$B$2:$B$60,MATCH(P40,Wastage_Factors!$A$2:$A$60,0)),0) -> 0.1 | R40: S1-S2 | S40: Standard | T40: Not shown | U40: - | V40: FORM-COL-01
A41: FRM-003 | B41: Formwork & Temporary Works | C41: Props | D41: Steel props / bamboo ballies (hire) | E41: Adjustable telescopic props | F41: Nos | G41: Supporting slab formwork | H41: Q = Σ [WI qty × Recipe coefficient] × (1 + Wastage %) — driven by WI-FW-01 (see Recipes) | I41: SLAB_AREA | K41: Structure | L41: - | M41: Nos | N41: RECIPE | O41: WI-FW-01 | P41: W_NIL | Q41: =IFERROR(INDEX(Wastage_Factors!$B$2:$B$60,MATCH(P41,Wastage_Factors!$A$2:$A$60,0)),0) -> 0 | R41: S2 | S41: Standard | T41: Not shown | U41: - | V41: FORM-SLAB-01
A42: FRM-004 | B42: Formwork & Temporary Works | C42: Timber | D42: Timber battens / scantlings | E42: Kail/Partal 2x3in, 3x4in | F42: cft | G42: Formwork framing | H42: Q = Σ [WI qty × Recipe coefficient] × (1 + Wastage %) — driven by WI-FW-02 (see Recipes) | I42: Contact areas | K42: Structure | L42: - | M42: cft | N42: RECIPE | O42: WI-FW-02 | P42: W_TIMBER | Q42: =IFERROR(INDEX(Wastage_Factors!$B$2:$B$60,MATCH(P42,Wastage_Factors!$A$2:$A$60,0)),0) -> 0.15 | R42: S2 | S42: Standard | T42: Not shown | U42: - | V42: FORM-COL-01
A43: FRM-005 | B43: Formwork & Temporary Works | C43: Consumables | D43: Nails (assorted) | E43: 2-4in wire nails | F43: kg | G43: Formwork | H43: Q = Σ [WI qty × Recipe coefficient] × (1 + Wastage %) — driven by WI-FW-02 (see Recipes) | I43: Contact areas | K43: Structure | L43: - | M43: kg | N43: RECIPE | O43: WI-FW-02 | P43: W_MISC | Q43: =IFERROR(INDEX(Wastage_Factors!$B$2:$B$60,MATCH(P43,Wastage_Factors!$A$2:$A$60,0)),0) -> 0.05 | R43: S2 | S43: Standard | T43: Not shown | U43: - | V43: FORM-COL-01
A44: FRM-006 | B44: Formwork & Temporary Works | C44: Consumables | D44: Shuttering release oil | E44: Mould oil / used mobil oil | F44: L | G44: Formwork faces | H44: Q = Σ [WI qty × Recipe coefficient] × (1 + Wastage %) — driven by WI-FW-01, WI-FW-02 (see Recipes) | I44: Formwork area | K44: Structure | L44: - | M44: L | N44: RECIPE | O44: WI-FW-01, WI-FW-02 | P44: W_MISC | Q44: =IFERROR(INDEX(Wastage_Factors!$B$2:$B$60,MATCH(P44,Wastage_Factors!$A$2:$A$60,0)),0) -> 0.05 | R44: S2 | S44: Standard | T44: Not shown | U44: - | V44: FORM-COL-01, FORM-SLAB-01
A45: FRM-007 | B45: Formwork & Temporary Works | C45: Access | D45: Scaffolding (hire) | E45: Steel pipe/cup-lock or bamboo | F45: sft | G45: External plaster, paint, facade works | H45: Q = sum of elevation areas (sft-month of hire) | I45: FACADE_AREA | K45: Structure | L45: - | M45: sft | N45: AREA(facade) | P45: W_NIL | Q45: =IFERROR(INDEX(Wastage_Factors!$B$2:$B$60,MATCH(P45,Wastage_Factors!$A$2:$A$60,0)),0) -> 0 | R45: S5 | S45: Standard | T45: Not shown | U45: Elevations (sh.5-7, 11-13)
A46: FRM-008 | B46: Formwork & Temporary Works | C46: Membranes | D46: Polythene sheet over shuttering | E46: 200-300 gauge | F46: sft | G46: Prevent slurry loss through plate joints | H46: Q = Σ [WI qty × Recipe coefficient] × (1 + Wastage %) — driven by WI-FW-01 (see Recipes) | I46: SLAB_AREA | K46: Structure | L46: - | M46: sft | N46: RECIPE | O46: WI-FW-01 | P46: W_POLY | Q46: =IFERROR(INDEX(Wastage_Factors!$B$2:$B$60,MATCH(P46,Wastage_Factors!$A$2:$A$60,0)),0) -> 0.05 | R46: S2 | S46: Optional | T46: Not shown | U46: - | V46: FORM-SLAB-01
A47: MAS-001 | B47: Masonry | C47: Clay bricks | D47: Burnt clay brick Class A ('Awwal') 9x4.5x3in nominal | E47: Well-burnt, metallic ring, absorption <= 20%, strength per spec | F47: Nos | G47: Foundation brickwork, 9in & 4.5in walls, parapets, manholes, boundary wall | H47: Q = Σ [WI qty × Recipe coefficient] × (1 + Wastage %) — driven by WI-MS-01, WI-MS-02, WI-MS-03, WI-MS-04, WI-PB-12, WI-PB-13, WI-EX-01 (see Recipes) | I47: WALL_CL_LEN, WALL_H, OPENINGS, FDN_SECTION | J47: Order per 1000. Measure actual brick size - it changes bricks/cft by ~5%. | K47: Structure | L47: PS / ASTM C62 (ref) | M47: Nos | N47: RECIPE | O47: WI-MS-01, WI-MS-02, WI-MS-03, WI-MS-04, WI-PB-12, WI-PB-13, WI-EX-01 | P47: W_BRICK | Q47: =IFERROR(INDEX(Wastage_Factors!$B$2:$B$60,MATCH(P47,Wastage_Factors!$A$2:$A$60,0)),0) -> 0.05 | R47: S1-S2 | S47: Standard | T47: Specified | U47: sh.8-10, 14-15, 24 | V47: FDN-MAS-01, MAS-01, WSD-01
A48: MAS-002 | B48: Masonry | C48: Clay bricks | D48: Burnt clay brick Class B ('Doem') / over-burnt | E48: For soling & non-structural fill | F48: Nos | G48: Brick soling under floors | H48: Q = Σ [WI qty × Recipe coefficient] × (1 + Wastage %) — driven by WI-MS-05 (see Recipes) | I48: ROOM(GF) | J48: Do not use for load-bearing walls. | K48: Structure | L48: - | M48: Nos | N48: RECIPE | O48: WI-MS-05 | P48: W_BRICK | Q48: =IFERROR(INDEX(Wastage_Factors!$B$2:$B$60,MATCH(P48,Wastage_Factors!$A$2:$A$60,0)),0) -> 0.05 | R48: S1 | S48: Standard | T48: Not shown | U48: - | V48: GF-SOL-01
A49: MAS-003 | B49: Masonry | C49: Clay tiles | D49: Burnt clay roof tiles 9x4.5x1.5in | E49: Machine-made, uniform | F49: Nos | G49: Roof finishing over mud insulation | H49: Q = Σ [WI qty × Recipe coefficient] × (1 + Wastage %) — driven by WI-WP-01 (see Recipes) | I49: ROOF_AREA | K49: Architecture | L49: - | M49: Nos | N49: RECIPE | O49: WI-WP-01 | P49: W_TILE_FLR | Q49: =IFERROR(INDEX(Wastage_Factors!$B$2:$B$60,MATCH(P49,Wastage_Factors!$A$2:$A$60,0)),0) -> 0.07 | R49: S3 | S49: Standard | T49: Not shown | U49: - | V49: ROOF-01
A50: MAS-004 | B50: Masonry | C50: Blocks | D50: Hollow concrete block 8x8x16in (and 6in/4in) | E50: ASTM C90 load-bearing | F50: Nos | G50: Alternative walling / boundary wall | H50: Q = Σ [WI qty × Recipe coefficient] × (1 + Wastage %) — driven by WI-MS-06 (see Recipes) | I50: WALL_CL_LEN | K50: Architecture | L50: ASTM C90 | M50: sft | N50: RECIPE | O50: WI-MS-06 | P50: W_BLOCK | Q50: =IFERROR(INDEX(Wastage_Factors!$B$2:$B$60,MATCH(P50,Wastage_Factors!$A$2:$A$60,0)),0) -> 0.03 | R50: S2 | S50: Alternative | T50: Not shown | U50: -
A51: MAS-005 | B51: Masonry | C51: Blocks | D51: AAC lightweight blocks | E51: 600x200x100-200mm | F51: cft | G51: Partitions / upper-floor infill (reduces dead load) | H51: Q = wall area x thickness - openings, x (1 + w) | I51: WALL_CL_LEN | J51: Requires thin-bed adhesive (MAS-006). | K51: Architecture | L51: ASTM C1693 | M51: sft | N51: AREA(wall)*t | P51: W_BLOCK | Q51: =IFERROR(INDEX(Wastage_Factors!$B$2:$B$60,MATCH(P51,Wastage_Factors!$A$2:$A$60,0)),0) -> 0.03 | R51: S2 | S51: Alternative | T51: Not shown | U51: -
A52: MAS-006 | B52: Masonry | C52: Mortar | D52: Thin-bed block adhesive | E52: Polymer-modified | F52: bag | G52: AAC block laying | H52: Q = AAC wall area x manufacturer coverage rate (bags per sft for block thickness) × (1 + Wastage %) | I52: WALL_CL_LEN | J52: Coverage per manufacturer - verify. | K52: Architecture | L52: - | M52: sft | N52: AREA(aac)/coverage | P52: W_ADHESIVE | Q52: =IFERROR(INDEX(Wastage_Factors!$B$2:$B$60,MATCH(P52,Wastage_Factors!$A$2:$A$60,0)),0) -> 0.05 | R52: S2 | S52: Alternative | T52: Not shown | U52: -
A53: MAS-009 | B53: Masonry | C53: Reinforcement | D53: Hoop iron / GI strip bond | E53: 22-24 SWG GI strip | F53: kg | G53: 4.5in partitions tied every 4th course | H53: Q = 4.5in wall length x (height / 1ft x 1/4) courses x 0.03 kg/rft × (1 + Wastage %) | I53: WALL_CL_LEN | K53: Structure | L53: - | M53: rft | N53: LEN(wall45)*H*0.25*0.03 | P53: W_STEEL | Q53: =IFERROR(INDEX(Wastage_Factors!$B$2:$B$60,MATCH(P53,Wastage_Factors!$A$2:$A$60,0)),0) -> 0.03 | R53: S2 | S53: Recommended | T53: Not shown | U53: -
A54: MAS-010 | B54: Masonry | C54: Decorative | D54: Brick jali / ventilation blocks | E54: Terracotta/concrete | F54: Nos | G54: Planter, boundary, stair ventilation | H54: Q = count from elevations × (1 + Wastage %) | I54: ELEVATIONS | K54: External | L54: - | M54: Nos | N54: COUNT(jali) | P54: W_BRICK | Q54: =IFERROR(INDEX(Wastage_Factors!$B$2:$B$60,MATCH(P54,Wastage_Factors!$A$2:$A$60,0)),0) -> 0.05 | R54: S8 | S54: Optional | T54: Not shown | U54: -
A55: MAS-011 | B55: Masonry | C55: Cladding | D55: Facing bricks / brick cladding tiles | E55: Split tiles 9x3x0.5in | F55: sft | G55: Front elevation feature cladding | H55: Q = cladding area from elevation x (1 + w) | I55: FACADE_AREA | J55: Elevation finishes not annotated in set - confirm. | K55: Architecture | L55: - | M55: sft | N55: AREA(facade, finish=brick) | P55: W_TILE_WALL | Q55: =IFERROR(INDEX(Wastage_Factors!$B$2:$B$60,MATCH(P55,Wastage_Factors!$A$2:$A$60,0)),0) -> 0.08 | R55: S6 | S55: Optional | T55: Implied | U55: Elevations (sh.5, 11)
A56: MAS-012 | B56: Masonry | C56: Cladding | D56: Natural stone cladding | E56: Stone 3/4in on adhesive/anchors | F56: sft | G56: Front elevation feature | H56: Q = cladding area from elevation x (1 + w) | I56: FACADE_AREA | K56: Architecture | L56: - | M56: sft | N56: AREA(facade, finish=stone) | P56: W_MARBLE | Q56: =IFERROR(INDEX(Wastage_Factors!$B$2:$B$60,MATCH(P56,Wastage_Factors!$A$2:$A$60,0)),0) -> 0.1 | R56: S6 | S56: Optional | T56: Implied | U56: Elevations
A57: MAS-013 | B57: Masonry | C57: Accessories | D57: Galvanised chicken wire mesh strip (6-9in) | E57: GI hexagonal 1in | F57: rft | G57: Across RCC/brick junctions and conduit chases before plaster | H57: Q = Σ [WI qty × Recipe coefficient] × (1 + Wastage %) — driven by WI-MS-02, WI-PL-02 (see Recipes) | I57: WALL_CL_LEN | J57: Prevents the most common plaster crack in PK houses. | K57: Architecture | L57: - | M57: rft | N57: RECIPE | O57: WI-MS-02, WI-PL-02 | P57: W_MISC | Q57: =IFERROR(INDEX(Wastage_Factors!$B$2:$B$60,MATCH(P57,Wastage_Factors!$A$2:$A$60,0)),0) -> 0.05 | R57: S5 | S57: Recommended | T57: Not shown | U57: - | V57: MAS-01, PLAS-02
A58: MAS-014 | B58: Masonry | C58: Coping | D58: Parapet/boundary coping (precast or in-situ) | E58: RCC/marble/stone, with drip groove | F58: rft | G58: Top of parapets & boundary walls | H58: Q = parapet length + boundary wall length × (1 + Wastage %) | I58: ROOF_AREA, BOUNDARY_LEN | K58: External | L58: - | M58: rft | N58: LEN(parapet)+LEN(boundary) | P58: W_MISC | Q58: =IFERROR(INDEX(Wastage_Factors!$B$2:$B$60,MATCH(P58,Wastage_Factors!$A$2:$A$60,0)),0) -> 0.05 | R58: S3 | S58: Recommended | T58: Not shown | U58: Elevations
A59: WPF-001 | B59: Waterproofing, DPC & Insulation | C59: Bituminous | D59: Bitumen (hot applied) | E59: Penetration grade 60/70 or blown 85/25 | F59: kg | G59: DPC 2 coats (drawing), roof 2 coats | H59: Q = Σ [WI qty × Recipe coefficient] × (1 + Wastage %) — driven by WI-CN-12, WI-WP-01 (see Recipes) | I59: WALL_CL_LEN(GF), ROOF_AREA | J59: Drums ~ 150-200 kg; fuel for heating. | K59: Architecture | L59: ASTM D946 / D312 | M59: sft | N59: RECIPE | O59: WI-CN-12, WI-WP-01 | P59: W_BITUMEN | Q59: =IFERROR(INDEX(Wastage_Factors!$B$2:$B$60,MATCH(P59,Wastage_Factors!$A$2:$A$60,0)),0) -> 0.05 | R59: S1,S3 | S59: Standard | T59: Specified | U59: sh.14-15 DPC note | V59: DPC-01, ROOF-01
A60: WPF-002 | B60: Waterproofing, DPC & Insulation | C60: Bituminous | D60: Bitumen primer (cut-back) | E60: Solvent-based primer | F60: gal | G60: Prime slab before bitumen/membrane | H60: Q = Σ [WI qty × Recipe coefficient] × (1 + Wastage %) — driven by WI-WP-01 (see Recipes) | I60: ROOF_AREA | K60: Architecture | L60: ASTM D41 | M60: sft | N60: RECIPE | O60: WI-WP-01 | P60: W_PAINT | Q60: =IFERROR(INDEX(Wastage_Factors!$B$2:$B$60,MATCH(P60,Wastage_Factors!$A$2:$A$60,0)),0) -> 0.05 | R60: S3 | S60: Standard | T60: Not shown | U60: - | V60: ROOF-01
A61: WPF-003 | B61: Waterproofing, DPC & Insulation | C61: Membranes | D61: Polythene sheet (high-density) | E61: 500-1000 gauge | F61: sft | G61: DPC double layer (drawing), roof, under floors | H61: Q = Σ [WI qty × Recipe coefficient] × (1 + Wastage %) — driven by WI-CN-12, WI-WP-01 (see Recipes) | I61: WALL_CL_LEN(GF), ROOF_AREA | J61: Sold by kg/roll - convert with gauge (1000 gauge ~ 0.25 mm). | K61: Architecture | L61: - | M61: sft | N61: RECIPE | O61: WI-CN-12, WI-WP-01 | P61: W_POLY | Q61: =IFERROR(INDEX(Wastage_Factors!$B$2:$B$60,MATCH(P61,Wastage_Factors!$A$2:$A$60,0)),0) -> 0.05 | R61: S1,S3 | S61: Standard | T61: Specified | U61: sh.14-15 | V61: DPC-01, ROOF-01
A62: WPF-004 | B62: Waterproofing, DPC & Insulation | C62: Cementitious | D62: Two-component cementitious waterproof coating | E62: Polymer-modified, flexible | F62: kg | G62: Bath/kitchen floors + 1ft upturn, shower walls, terraces, planters, tank interiors | H62: Q = Σ [WI qty × Recipe coefficient] × (1 + Wastage %) — driven by WI-WP-03 (see Recipes) | I62: ROOM(wet), TERRACE_AREA | J62: Drawing set has no wet-area waterproofing spec - add. | K62: Architecture | L62: EN 14891 | M62: sft | N62: RECIPE | O62: WI-WP-03 | P62: W_MISC | Q62: =IFERROR(INDEX(Wastage_Factors!$B$2:$B$60,MATCH(P62,Wastage_Factors!$A$2:$A$60,0)),0) -> 0.05 | R62: S5 | S62: Standard | T62: Not shown | U62: Plumbing plans (sh.21-22) | V62: WP-01
A63: WPF-005 | B63: Waterproofing, DPC & Insulation | C63: Membranes | D63: APP/SBS modified bitumen membrane 3-4 mm (torch-on) | E63: Polyester reinforced | F63: sft | G63: Premium roof waterproofing alternative | H63: Q = Σ [WI qty × Recipe coefficient] × (1 + Wastage %) — driven by WI-WP-02 (see Recipes) | I63: ROOF_AREA | J63: Roll ~10 m2 (107.6 sft). | K63: Architecture | L63: ASTM D6222/6223 | M63: sft | N63: RECIPE | O63: WI-WP-02 | P63: W_POLY | Q63: =IFERROR(INDEX(Wastage_Factors!$B$2:$B$60,MATCH(P63,Wastage_Factors!$A$2:$A$60,0)),0) -> 0.05 | R63: S3 | S63: Alternative | T63: Not shown | U63: - | V63: WP-01
A64: WPF-006 | B64: Waterproofing, DPC & Insulation | C64: Liquid | D64: Liquid PU / acrylic elastomeric roof coating | E64: UV-stable | F64: L | G64: Over-coating roof/terraces | H64: Q = area x coverage (L/sft per coat) x coats × (1 + Wastage %) | I64: ROOF_AREA | K64: Architecture | L64: - | M64: sft | N64: AREA(roof)*cov*coats | P64: W_PAINT | Q64: =IFERROR(INDEX(Wastage_Factors!$B$2:$B$60,MATCH(P64,Wastage_Factors!$A$2:$A$60,0)),0) -> 0.05 | R64: S3 | S64: Alternative | T64: Not shown | U64: -
A65: WPF-007 | B65: Waterproofing, DPC & Insulation | C65: Admixtures | D65: Integral waterproofing compound (powder/liquid) | E65: e.g. 'Puddlo'-type per drawing | F65: kg | G65: DPC concrete, tank concrete & plaster, manhole plaster | H65: Q = Σ [WI qty × Recipe coefficient] × (1 + Wastage %) — driven by WI-CN-11, WI-CN-12, WI-PL-04 (see Recipes) | I65: Cement in DPC/tank items | K65: Architecture | L65: - | M65: kg | N65: RECIPE | O65: WI-CN-11, WI-CN-12, WI-PL-04 | P65: W_MISC | Q65: =IFERROR(INDEX(Wastage_Factors!$B$2:$B$60,MATCH(P65,Wastage_Factors!$A$2:$A$60,0)),0) -> 0.05 | R65: S1 | S65: Standard | T65: Specified | U65: sh.14, 16, 24 ('Puddlo') | V65: DPC-01
A66: WPF-008 | B66: Waterproofing, DPC & Insulation | C66: Insulation | D66: Roof thermal insulation board (EPS/XPS 1-2in) | E66: EPS 15-20 kg/m3 or XPS | F66: sft | G66: Roof insulation (energy code friendly alternative to mud) | H66: Q = Σ [WI qty × Recipe coefficient] × (1 + Wastage %) — driven by WI-WP-02 (see Recipes) | I66: ROOF_AREA | J66: BCP Energy Provisions exist; XPS preferred under wet screeds. | K66: Architecture | L66: - | M66: sft | N66: RECIPE | O66: WI-WP-02 | P66: W_MISC | Q66: =IFERROR(INDEX(Wastage_Factors!$B$2:$B$60,MATCH(P66,Wastage_Factors!$A$2:$A$60,0)),0) -> 0.05 | R66: S3 | S66: Alternative | T66: Not shown | U66: - | V66: WP-01
A67: WPF-009 | B67: Waterproofing, DPC & Insulation | C67: Traditional | D67: Earth for roof insulation & mud plaster | E67: Clayey earth, free of stones | F67: cft | G67: Traditional roof treatment 3-4in + 1in leeping | H67: Q = Σ [WI qty × Recipe coefficient] × (1 + Wastage %) — driven by WI-WP-01 (see Recipes) | I67: ROOF_AREA | J67: Adds ~40-50 psf dead load - structural engineer must allow for it. | K67: Architecture | L67: - | M67: cft | N67: RECIPE | O67: WI-WP-01 | P67: W_EARTH | Q67: =IFERROR(INDEX(Wastage_Factors!$B$2:$B$60,MATCH(P67,Wastage_Factors!$A$2:$A$60,0)),0) -> 0 | R67: S3 | S67: Standard | T67: Not shown | U67: - | V67: ROOF-01
A68: WPF-010 | B68: Waterproofing, DPC & Insulation | C68: Traditional | D68: Straw (bhoosa) for mud plaster | E68: Wheat straw | F68: kg | G68: Mud plaster reinforcement | H68: Q = Σ [WI qty × Recipe coefficient] × (1 + Wastage %) — driven by WI-WP-01 (see Recipes) | I68: ROOF_AREA | K68: Architecture | L68: - | M68: kg | N68: RECIPE | O68: WI-WP-01 | P68: W_MISC | Q68: =IFERROR(INDEX(Wastage_Factors!$B$2:$B$60,MATCH(P68,Wastage_Factors!$A$2:$A$60,0)),0) -> 0.05 | R68: S3 | S68: Standard | T68: Not shown | U68: - | V68: ROOF-01
A69: WPF-011 | B69: Waterproofing, DPC & Insulation | C69: Joints | D69: PVC water stop 6in | E69: Dumb-bell/centre-bulb | F69: rft | G69: Construction joints in UG/septic tank walls | H69: Q = wall/base construction joint length (tank perimeter x lifts) × (1 + Wastage %) | I69: TANK_UG, TANK_SEPTIC | K69: Plumbing | L69: - | M69: rft | N69: LEN(tank.perimeter)*lifts | P69: W_MISC | Q69: =IFERROR(INDEX(Wastage_Factors!$B$2:$B$60,MATCH(P69,Wastage_Factors!$A$2:$A$60,0)),0) -> 0.05 | R69: S1 | S69: Recommended | T69: Not shown | U69: sh.16
A70: WPF-012 | B70: Waterproofing, DPC & Insulation | C70: Sealants | D70: PU / polysulphide sealant | E70: Gun-grade, 600 ml sausage | F70: tube | G70: Expansion joints, pipe penetrations, window perimeters (external) | H70: Q = joint length / bead length per tube × (1 + Wastage %) | I70: ELEVATIONS | K70: Architecture | L70: - | M70: rft | N70: LEN(joints)/K_SIL_RFT_TUBE | P70: W_MISC | Q70: =IFERROR(INDEX(Wastage_Factors!$B$2:$B$60,MATCH(P70,Wastage_Factors!$A$2:$A$60,0)),0) -> 0.05 | R70: S6 | S70: Standard | T70: Not shown | U70: -
A71: WPF-013 | B71: Waterproofing, DPC & Insulation | C71: Joints | D71: Expansion joint filler board | E71: Bitumen-impregnated fibre board 3/4in | F71: rft | G71: Separation joints: porch slab, boundary wall, building/adjacent | H71: Q = length of separation joints × (1 + Wastage %) | I71: Site plan | K71: Architecture | L71: - | M71: rft | N71: LEN(exp_joints) | P71: W_MISC | Q71: =IFERROR(INDEX(Wastage_Factors!$B$2:$B$60,MATCH(P71,Wastage_Factors!$A$2:$A$60,0)),0) -> 0.05 | R71: S8 | S71: Recommended | T71: Not shown | U71: -
A72: WPF-014 | B72: Waterproofing, DPC & Insulation | C72: Accessories | D72: Fibreglass mesh for waterproofing corners | E72: Alkali-resistant | F72: rft | G72: Wall-floor junctions in wet areas | H72: Q = wet room perimeter + pipe penetrations x 1 rft × (1 + Wastage %) | I72: ROOM(wet) | K72: Architecture | L72: - | M72: rft | N72: SUM(wet.perim) | P72: W_MISC | Q72: =IFERROR(INDEX(Wastage_Factors!$B$2:$B$60,MATCH(P72,Wastage_Factors!$A$2:$A$60,0)),0) -> 0.05 | R72: S5 | S72: Standard | T72: Not shown | U72: -
A73: PLS-001 | B73: Plaster & Screeds | C73: Accessories | D73: Corner beads (PVC/GI) | E73: Perforated angle bead | F73: rft | G73: External corners of walls, columns, window/door reveals | H73: Q = Σ [WI qty × Recipe coefficient] × (1 + Wastage %) — driven by WI-PL-01, WI-PL-02 (see Recipes) | I73: ROOM, OPENINGS | J73: Better measured as corners x height when geometry available. | K73: Architecture | L73: - | M73: rft | N73: RECIPE | O73: WI-PL-01, WI-PL-02 | P73: W_MISC | Q73: =IFERROR(INDEX(Wastage_Factors!$B$2:$B$60,MATCH(P73,Wastage_Factors!$A$2:$A$60,0)),0) -> 0.05 | R73: S5 | S73: Standard | T73: Not shown | U73: - | V73: PLAS-01, PLAS-02
A74: PLS-002 | B74: Plaster & Screeds | C74: Accessories | D74: Expanded metal lath (EML) | E74: GI | F74: rft | G74: Over conduit/pipe chases | H74: Q = total concealed conduit + pipe length in walls x 1.0 × (1 + Wastage %) | I74: EL_POINTS, PB_FIXTURES | K74: Architecture | L74: - | M74: rft | N74: LEN(conduit_in_walls)+LEN(pipes_in_walls) | P74: W_MISC | Q74: =IFERROR(INDEX(Wastage_Factors!$B$2:$B$60,MATCH(P74,Wastage_Factors!$A$2:$A$60,0)),0) -> 0.05 | R74: S5 | S74: Recommended | T74: Not shown | U74: -
A75: PLS-003 | B75: Plaster & Screeds | C75: Gypsum | D75: Gypsum plaster (internal alternative) | E75: Bag 25-40 kg; ~1 kg/m2/mm | F75: bag | G75: Internal walls/ceilings (faster, crack-resistant) | H75: Q = area x thickness(mm) x 1 kg/m2/mm / bag kg × (1 + Wastage %) | I75: ROOM | K75: Architecture | L75: EN 13279 | M75: sft | N75: AREA/10.764*t_mm/bag_kg | P75: W_MISC | Q75: =IFERROR(INDEX(Wastage_Factors!$B$2:$B$60,MATCH(P75,Wastage_Factors!$A$2:$A$60,0)),0) -> 0.05 | R75: S5 | S75: Alternative | T75: Not shown | U75: -
A76: PLS-004 | B76: Plaster & Screeds | C76: Gypsum | D76: Plaster of Paris (POP) | E76: Bag | F76: bag | G76: Cornices, repairs, niches | H76: Q = cornice length x 0.1 bag/rft (allowance) × (1 + Wastage %) | I76: ROOM | K76: Architecture | L76: - | M76: rft | N76: LEN(cornice)*0.1 | P76: W_MISC | Q76: =IFERROR(INDEX(Wastage_Factors!$B$2:$B$60,MATCH(P76,Wastage_Factors!$A$2:$A$60,0)),0) -> 0.05 | R76: S6 | S76: Optional | T76: Not shown | U76: -
A77: PLS-005 | B77: Plaster & Screeds | C77: Additives | D77: Polypropylene micro-fibres | E77: 12 mm fibres, 0.9 kg/m3 | F77: kg | G77: Screeds, roof topping - crack control | H77: Q = Σ [WI qty × Recipe coefficient] × (1 + Wastage %) — driven by WI-WP-04 (see Recipes) | I77: ROOF_AREA, ROOM(wet) | K77: Architecture | L77: - | M77: kg | N77: RECIPE | O77: WI-WP-04 | P77: W_MISC | Q77: =IFERROR(INDEX(Wastage_Factors!$B$2:$B$60,MATCH(P77,Wastage_Factors!$A$2:$A$60,0)),0) -> 0.05 | R77: S3 | S77: Optional | T77: Not shown | U77: -
A78: PLS-006 | B78: Plaster & Screeds | C78: Hardener | D78: Floor hardener (dry-shake) | E78: Non-metallic | F78: kg | G78: Porch / garage / store floors | H78: Q = area x 0.5 kg/sft (per manufacturer) × (1 + Wastage %) | I78: PORCH | K78: Architecture | L78: - | M78: sft | N78: AREA*0.5 | P78: W_MISC | Q78: =IFERROR(INDEX(Wastage_Factors!$B$2:$B$60,MATCH(P78,Wastage_Factors!$A$2:$A$60,0)),0) -> 0.05 | R78: S6 | S78: Optional | T78: Not shown | U78: -
A79: FLR-001 | B79: Flooring & Tiling | C79: Porcelain | D79: Porcelain floor tiles 24x24in (600x600mm) | E79: Glazed/polished, PEI III-IV, rectified | F79: sft | G79: Bedrooms, lounges, drawing, corridors | H79: Q = Σ [WI qty × Recipe coefficient] × (1 + Wastage %) — driven by WI-FL-01 (see Recipes) | I79: ROOM (non-wet), Room_Finish_Defaults | J79: Buy in boxes (sft per box by size). Local: Master, Shabbir, Stile; imported Spanish/Chinese. Diagonal laying -> use 12% wastage. | K79: Architecture | L79: ISO 13006 | M79: sft | N79: RECIPE | O79: WI-FL-01 | P79: W_TILE_FLR | Q79: =IFERROR(INDEX(Wastage_Factors!$B$2:$B$60,MATCH(P79,Wastage_Factors!$A$2:$A$60,0)),0) -> 0.07 | R79: S6 | S79: Standard | T79: Not shown | U79: Room labels on plans (sh.2-3, 8-9) | V79: FLR-01
A80: FLR-002 | B80: Flooring & Tiling | C80: Ceramic | D80: Ceramic anti-skid floor tiles 12x12 / 16x16in | E80: R10-R11 slip rating | F80: sft | G80: Baths, kitchen, laundry, terraces | H80: Q = Σ [WI qty × Recipe coefficient] × (1 + Wastage %) — driven by WI-FL-02 (see Recipes) | I80: ROOM (wet) | K80: Architecture | L80: ISO 13006 | M80: sft | N80: RECIPE | O80: WI-FL-02 | P80: W_TILE_FLR | Q80: =IFERROR(INDEX(Wastage_Factors!$B$2:$B$60,MATCH(P80,Wastage_Factors!$A$2:$A$60,0)),0) -> 0.07 | R80: S6 | S80: Standard | T80: Not shown | U80: sh.8-9 | V80: FLR-01
A81: FLR-003 | B81: Flooring & Tiling | C81: Wall tiles | D81: Ceramic/porcelain wall tiles 12x24in | E81: Glazed | F81: sft | G81: Bath walls (full height 8ft), kitchen backsplash (2-2.5ft above counter) | H81: Q = Σ [WI qty × Recipe coefficient] × (1 + Wastage %) — driven by WI-FL-03 (see Recipes) | I81: ROOM (wet), Room_Finish_Defaults | K81: Architecture | L81: ISO 13006 | M81: sft | N81: RECIPE | O81: WI-FL-03 | P81: W_TILE_WALL | Q81: =IFERROR(INDEX(Wastage_Factors!$B$2:$B$60,MATCH(P81,Wastage_Factors!$A$2:$A$60,0)),0) -> 0.08 | R81: S6 | S81: Standard | T81: Not shown | U81: sh.21-22 (fixtures) | V81: FLR-01
A82: FLR-004 | B82: Flooring & Tiling | C82: Marble | D82: Marble flooring slabs/tiles 3/4in | E82: Local (Botticino, Sunny Grey, Verona, Ziarat) or imported | F82: sft | G82: Lobbies, stair landings, optional rooms | H82: Q = Σ [WI qty × Recipe coefficient] × (1 + Wastage %) — driven by WI-FL-04 (see Recipes) | I82: ROOM | K82: Architecture | L82: - | M82: sft | N82: RECIPE | O82: WI-FL-04 | P82: W_MARBLE | Q82: =IFERROR(INDEX(Wastage_Factors!$B$2:$B$60,MATCH(P82,Wastage_Factors!$A$2:$A$60,0)),0) -> 0.1 | R82: S6 | S82: Standard | T82: Not shown | U82: - | V82: FLR-01
A83: FLR-005 | B83: Flooring & Tiling | C83: Granite | D83: Granite slab 3/4in | E83: Black/grey granite | F83: sft | G83: Thresholds, stair nosings (premium), counters | H83: Q = area from details x (1 + w) | I83: STAIR, KITCHEN | K83: Architecture | L83: - | M83: sft | N83: AREA | P83: W_MARBLE | Q83: =IFERROR(INDEX(Wastage_Factors!$B$2:$B$60,MATCH(P83,Wastage_Factors!$A$2:$A$60,0)),0) -> 0.1 | R83: S6 | S83: Optional | T83: Not shown | U83: -
A84: FLR-006 | B84: Flooring & Tiling | C84: Stairs | D84: Marble/granite for stair treads & risers | E84: Treads 1.25in / risers 3/4in | F84: sft | G84: Staircase GF-FF-Mumty | H84: Q = Σ [WI qty × Recipe coefficient] × (1 + Wastage %) — driven by WI-FL-06 (see Recipes) | I84: STAIR | K84: Architecture | L84: - | M84: rft | N84: RECIPE | O84: WI-FL-06 | P84: W_MARBLE | Q84: =IFERROR(INDEX(Wastage_Factors!$B$2:$B$60,MATCH(P84,Wastage_Factors!$A$2:$A$60,0)),0) -> 0.1 | R84: S6 | S84: Standard | T84: Implied | U84: sh.8-10 (stair UP/DN)
A85: FLR-007 | B85: Flooring & Tiling | C85: Skirting | D85: Skirting 4in (tile cut / marble strip) | E85: Matching floor | F85: sft | G85: All non-tiled-wall rooms | H85: Q = Σ [WI qty × Recipe coefficient] × (1 + Wastage %) — driven by WI-FL-05 (see Recipes) | I85: ROOM, DOOR_SCHED | K85: Architecture | L85: - | M85: rft | N85: RECIPE | O85: WI-FL-05 | P85: W_TILE_FLR | Q85: =IFERROR(INDEX(Wastage_Factors!$B$2:$B$60,MATCH(P85,Wastage_Factors!$A$2:$A$60,0)),0) -> 0.07 | R85: S6 | S85: Standard | T85: Not shown | U85: -
A86: FLR-008 | B86: Flooring & Tiling | C86: Sills | D86: Marble window sills & door thresholds | E86: 3/4in, 6-9in deep | F86: sft | G86: Every window & external door | H86: Q = Σ [WI qty × Recipe coefficient] × (1 + Wastage %) — driven by WI-FL-08 (see Recipes) | I86: WIN_SCHED, DOOR_SCHED | K86: Architecture | L86: - | M86: rft | N86: RECIPE | O86: WI-FL-08 | P86: W_MARBLE | Q86: =IFERROR(INDEX(Wastage_Factors!$B$2:$B$60,MATCH(P86,Wastage_Factors!$A$2:$A$60,0)),0) -> 0.1 | R86: S6 | S86: Standard | T86: Implied | U86: sh.17-19
A87: FLR-010 | B87: Flooring & Tiling | C87: Adhesive | D87: Cement-based tile adhesive (C1/C2) | E87: 20-25 kg bag | F87: kg | G87: Wall tiles, large-format tiles, skirting | H87: Q = Σ [WI qty × Recipe coefficient] × (1 + Wastage %) — driven by WI-FL-03, WI-FL-05 (see Recipes) | I87: FLR-003 area | J87: If thin-bed method is also used for floors, switch WI-FL-01/02 recipe from mortar bed to adhesive. | K87: Architecture | L87: EN 12004 | M87: sft | N87: RECIPE | O87: WI-FL-03, WI-FL-05 | P87: W_ADHESIVE | Q87: =IFERROR(INDEX(Wastage_Factors!$B$2:$B$60,MATCH(P87,Wastage_Factors!$A$2:$A$60,0)),0) -> 0.05 | R87: S6 | S87: Standard | T87: Not shown | U87: - | V87: FLR-01
A88: FLR-011 | B88: Flooring & Tiling | C88: Grout | D88: Tile grout (cementitious / epoxy) | E88: Sanded/unsanded; epoxy in wet areas (premium) | F88: kg | G88: All tile joints | H88: Q = Σ [WI qty × Recipe coefficient] × (1 + Wastage %) — driven by WI-FL-01, WI-FL-02, WI-FL-03 (see Recipes) | I88: Tile areas | K88: Architecture | L88: EN 13888 | M88: sft | N88: RECIPE | O88: WI-FL-01, WI-FL-02, WI-FL-03 | P88: W_GROUT | Q88: =IFERROR(INDEX(Wastage_Factors!$B$2:$B$60,MATCH(P88,Wastage_Factors!$A$2:$A$60,0)),0) -> 0.1 | R88: S6 | S88: Standard | T88: Not shown | U88: - | V88: FLR-01
A89: FLR-012 | B89: Flooring & Tiling | C89: Accessories | D89: Tile spacers / levelling clips | E89: 2-3 mm | F89: Nos | G89: Tile laying | H89: Q = Σ [WI qty × Recipe coefficient] × (1 + Wastage %) — driven by WI-FL-01, WI-FL-02, WI-FL-03 (see Recipes) | I89: Tile areas | K89: Architecture | L89: - | M89: Nos | N89: RECIPE | O89: WI-FL-01, WI-FL-02, WI-FL-03 | P89: W_MISC | Q89: =IFERROR(INDEX(Wastage_Factors!$B$2:$B$60,MATCH(P89,Wastage_Factors!$A$2:$A$60,0)),0) -> 0.05 | R89: S6 | S89: Standard | T89: Not shown | U89: - | V89: FLR-01
A90: FLR-013 | B90: Flooring & Tiling | C90: Trims | D90: Tile edge trims (aluminium/PVC) | E90: L/round profile | F90: rft | G90: External corners of tiled walls, niche edges | H90: Q = external corners x tile height + niches × (1 + Wastage %) | I90: ROOM(wet) | K90: Architecture | L90: - | M90: rft | N90: COUNT(corners)*tile_h | P90: W_MISC | Q90: =IFERROR(INDEX(Wastage_Factors!$B$2:$B$60,MATCH(P90,Wastage_Factors!$A$2:$A$60,0)),0) -> 0.05 | R90: S6 | S90: Optional | T90: Not shown | U90: -
A91: FLR-014 | B91: Flooring & Tiling | C91: Finishing | D91: Marble grinding & polishing (service + consumables) | E91: 3-stage diamond, wax | F91: sft | G91: In-situ marble floors | H91: Q = Σ [WI qty × Recipe coefficient] × (1 + Wastage %) — driven by WI-FL-04 (see Recipes) | I91: FLR-004 area | K91: Architecture | L91: - | M91: sft | N91: RECIPE | O91: WI-FL-04 | P91: W_NIL | Q91: =IFERROR(INDEX(Wastage_Factors!$B$2:$B$60,MATCH(P91,Wastage_Factors!$A$2:$A$60,0)),0) -> 0 | R91: S6 | S91: Standard | T91: Not shown | U91: - | V91: FLR-01
A92: FLR-015 | B92: Flooring & Tiling | C92: Terrazzo | D92: Terrazzo / chips flooring (economy alternative) | E92: Marble chips + grey/white cement + glass/brass strips | F92: sft | G92: Economy floors, store, stairs | H92: Q = area x (1 + w); chips 0.05 cft/sft, cement 0.05 bag/sft (allowance) | I92: ROOM | K92: Architecture | L92: - | M92: sft | N92: AREA | P92: W_TILE_FLR | Q92: =IFERROR(INDEX(Wastage_Factors!$B$2:$B$60,MATCH(P92,Wastage_Factors!$A$2:$A$60,0)),0) -> 0.07 | R92: S6 | S92: Alternative | T92: Not shown | U92: -
A93: FLR-016 | B93: Flooring & Tiling | C93: Wood/vinyl | D93: Laminate / engineered wood / SPC vinyl flooring + underlay | E93: AC4 laminate / SPC 4-5mm | F93: sft | G93: Premium bedrooms | H93: Q = room area x (1 + w) ; underlay = area; skirting = perimeter | I93: ROOM | K93: Architecture | L93: EN 13329 | M93: sft | N93: AREA(room) | P93: W_TILE_FLR | Q93: =IFERROR(INDEX(Wastage_Factors!$B$2:$B$60,MATCH(P93,Wastage_Factors!$A$2:$A$60,0)),0) -> 0.07 | R93: S6 | S93: Premium | T93: Not shown | U93: -
A94: FLR-018 | B94: Flooring & Tiling | C94: Stairs | D94: Anti-slip stair nosing | E94: Aluminium/rubber insert | F94: rft | G94: Stair treads | H94: Q = Σ [WI qty × Recipe coefficient] × (1 + Wastage %) — driven by WI-FL-06 (see Recipes) | I94: STAIR | K94: Architecture | L94: - | M94: rft | N94: RECIPE | O94: WI-FL-06 | P94: W_MISC | Q94: =IFERROR(INDEX(Wastage_Factors!$B$2:$B$60,MATCH(P94,Wastage_Factors!$A$2:$A$60,0)),0) -> 0.05 | R94: S6 | S94: Optional | T94: Not shown | U94: -
A95: DWG-001 | B95: Doors, Windows & Glazing | C95: Frames | D95: Door frame (chogath) - solid seasoned hardwood | E95: Deodar/Kail/Ash, 5in single rebate or 10in double rebate x ~2.75in (drawing sh.20) | F95: cft | G95: All internal & external doors (15 Nos in sample) | H95: Q = Σ [WI qty × Recipe coefficient] × (1 + Wastage %) — driven by WI-DW-01 (see Recipes) | I95: DOOR_SCHED (W, H, count, rebate) | J95: Frames are fixed during masonry (S2) - early procurement item. Termite-treat timber. | K95: Architecture | L95: - | M95: rft | N95: RECIPE | O95: WI-DW-01 | P95: W_TIMBER | Q95: =IFERROR(INDEX(Wastage_Factors!$B$2:$B$60,MATCH(P95,Wastage_Factors!$A$2:$A$60,0)),0) -> 0.15 | R95: S2 | S95: Standard | T95: Specified | U95: Chogath schedule (sh.20) | V95: DOOR-01
A96: DWG-002 | B96: Doors, Windows & Glazing | C96: Shutters | D96: Solid/semi-solid wood panel door shutter 1.75in | E96: Deodar/Ash panels, or solid core with veneer | F96: sft | G96: Main door, drawing door, bedroom doors | H96: Q = Σ [WI qty × Recipe coefficient] × (1 + Wastage %) — driven by WI-DW-02 (see Recipes) | I96: DOOR_SCHED | K96: Architecture | L96: - | M96: sft | N96: RECIPE | O96: WI-DW-02 | P96: W_TIMBER | Q96: =IFERROR(INDEX(Wastage_Factors!$B$2:$B$60,MATCH(P96,Wastage_Factors!$A$2:$A$60,0)),0) -> 0.15 | R96: S6 | S96: Standard | T96: Specified | U96: sh.17-20 | V96: DOOR-01
A97: DWG-003 | B97: Doors, Windows & Glazing | C97: Shutters | D97: Flush door shutter (MDF/ply skin, veneer or laminate) | E97: Solid-core 1.5-1.75in | F97: sft | G97: Internal doors (economy/standard) | H97: Q = sum(door W x H) for flush-type doors × (1 + Wastage %) | I97: DOOR_SCHED | K97: Architecture | L97: - | M97: sft | N97: SUM(door.W*door.H | type=flush) | P97: W_TIMBER | Q97: =IFERROR(INDEX(Wastage_Factors!$B$2:$B$60,MATCH(P97,Wastage_Factors!$A$2:$A$60,0)),0) -> 0.15 | R97: S6 | S97: Alternative | T97: Not shown | U97: sh.20
A98: DWG-004 | B98: Doors, Windows & Glazing | C98: Shutters | D98: Bathroom door (WPC/PVC/fibreglass) | E98: Water-resistant, with frame | F98: Nos | G98: 4 bath doors 2'-6"x7' (sh.20) | H98: Q = count of bath doors | I98: DOOR_SCHED | K98: Architecture | L98: - | M98: Nos | N98: COUNT(door | type=bath) | P98: W_NIL | Q98: =IFERROR(INDEX(Wastage_Factors!$B$2:$B$60,MATCH(P98,Wastage_Factors!$A$2:$A$60,0)),0) -> 0 | R98: S6 | S98: Standard | T98: Specified | U98: sh.20 (4 Nos)
A99: DWG-005 | B99: Doors, Windows & Glazing | C99: Shutters | D99: Main entrance door (solid wood, double leaf) | E99: 4'-6"x8' double (sh.20) | F99: Nos | G99: Main entrance | H99: Q = count | I99: DOOR_SCHED | K99: Architecture | L99: - | M99: Nos | N99: COUNT(door | type=main) | P99: W_NIL | Q99: =IFERROR(INDEX(Wastage_Factors!$B$2:$B$60,MATCH(P99,Wastage_Factors!$A$2:$A$60,0)),0) -> 0 | R99: S6 | S99: Standard | T99: Specified | U99: sh.20 (1 No)
A100: DWG-006 | B100: Doors, Windows & Glazing | C100: Hardware | D100: Door hardware set per leaf | E100: 3-4 SS butt hinges 4in, mortise lock/cylinder, lever handles, 2 tower bolts, door stopper, (closer for main) | F100: set | G100: All door leaves | H100: Q = Σ [WI qty × Recipe coefficient] × (1 + Wastage %) — driven by WI-DW-03 (see Recipes) | I100: DOOR_SCHED (leaves) | J100: Double doors = 2 leaves; add flush bolts. | K100: Architecture | L100: - | M100: Nos | N100: RECIPE | O100: WI-DW-03 | P100: W_NIL | Q100: =IFERROR(INDEX(Wastage_Factors!$B$2:$B$60,MATCH(P100,Wastage_Factors!$A$2:$A$60,0)),0) -> 0 | R100: S7 | S100: Standard | T100: Not shown | U100: sh.20
...

Sheet Work_Items
A1: WI_ID | B1: Scope | C1: Division | D1: Work Item Description | E1: Unit (FPS) | F1: Unit (SI) | G1: Measurement Rule | H1: Quantity Formula (engine expression) | I1: Required Inputs | J1: Default Specification | K1: Legacy App Code | L1: No. of Recipe Lines
A2: WI-PRE-01 | B2: Complete | C2: Preliminaries | D2: Site clearance, setting out & temporary works | E2: LS | F2: LS | G2: Lump sum per project | H2: LS | I2: SITE_W, SITE_D | J2: Hoarding, store, temporary water/electricity | K2: PRELIM-01 | L2: =COUNTIF(Recipes!$A$2:$A$1000,A2) -> 0
A3: WI-PRE-02 | B3: Complete | C3: Preliminaries | D3: Construction water (tanker / bore) | E3: gal | F3: L | G3: Derived from total cement consumption | H3: SUM(cement_bags) * K_WATER_L_BAG / 4.546 | I3: All concrete/mortar work items | J3: Tanker water if no CDA/bore supply | L3: =COUNTIF(Recipes!$A$2:$A$1000,A3) -> 1
A4: WI-EW-01 | B4: Structure | C4: Earthwork | D4: Excavation for strip foundations | E4: cft | F4: m3 | G4: Trench length along wall centreline x (bottom width of PCC + 2 x working space) x depth below NSL; no deduction for pipes <6in | H4: SUM(strip.len_cl * (strip.pcc_w + 2*P_WORKSPACE) * strip.depth) | I4: FDN_STRIP_LEN, FDN_SECTION, FDN_DEPTH | J4: Ordinary soil | K4: EXC-01 | L4: =COUNTIF(Recipes!$A$2:$A$1000,A4) -> 0
A5: WI-EW-02 | B5: Structure | C5: Earthwork | D5: Excavation for isolated column footings | E5: cft | F5: m3 | G5: (L+2ws) x (B+2ws) x D per footing x count | H5: SUM(ftg.n * (ftg.L+2*P_WORKSPACE)*(ftg.B+2*P_WORKSPACE)*ftg.D) | I5: FTG_ISO | K5: EXC-01 | L5: =COUNTIF(Recipes!$A$2:$A$1000,A5) -> 0
A6: WI-EW-03 | B6: Plumbing | C6: Earthwork | D6: Excavation for tanks, septic, manholes, sewer trenches | E6: cft | F6: m3 | G6: External plan dims + working space x depth; trench = length x 2ft x avg depth | H6: SUM(tank.ext_L*tank.ext_B*tank.D) + sewer.len*2*sewer.avg_depth | I6: TANK_UG, TANK_SEPTIC, SEWER_EXT_LEN, MH_COUNT | L6: =COUNTIF(Recipes!$A$2:$A$1000,A6) -> 0
A7: WI-EW-04 | B7: Structure | C7: Earthwork | D7: Backfill with excavated earth, compacted in 6in layers | E7: cft | F7: m3 | G7: Excavation minus volume of PCC, footing, masonry below NGL | H7: WI-EW-01 + WI-EW-02 - V(below NGL structures) | I7: Derived | K7: BACKFILL-01 | L7: =COUNTIF(Recipes!$A$2:$A$1000,A7) -> 0
A8: WI-EW-05 | B8: Structure | C8: Earthwork | D8: Plinth filling with imported earth, compacted | E8: cft | F8: m3 | G8: GF internal floor area x (plinth height - floor build-up thickness) | H8: GF.net_floor_area * (H_PLINTH - T_FLOOR_BUILDUP) | I8: H_PLINTH, ROOM (GF), T_FLOOR_BUILDUP | J8: Good earth free of organics | K8: PLINTH-FILL-01 | L8: =COUNTIF(Recipes!$A$2:$A$1000,A8) -> 1
A9: WI-EW-06 | B9: Structure | C9: Earthwork | D9: Sand filling under floors | E9: cft | F9: m3 | G9: GF floor area x sand thickness | H9: GF.net_floor_area * P_SAND_FILL_T | I9: ROOM (GF) | J9: 3-4 in | L9: =COUNTIF(Recipes!$A$2:$A$1000,A9) -> 1
A10: WI-EW-07 | B10: Structure | C10: Earthwork | D10: Anti-termite treatment (foundation trenches, plinth, floor) | E10: sft | F10: m2 | G10: Trench bottom+sides area + plinth fill surface | H10: WI-EW-01 surfaces + GF.floor_area | I10: Derived | J10: Chlorpyrifos/imidacloprid emulsion per label | K10: AT-01 | L10: =COUNTIF(Recipes!$A$2:$A$1000,A10) -> 1
A11: WI-EW-08 | B11: Structure | C11: Earthwork | D11: Polythene vapour barrier under GF floor PCC | E11: sft | F11: m2 | G11: GF floor area | H11: GF.net_floor_area | I11: ROOM (GF) | J11: 500-1000 gauge | L11: =COUNTIF(Recipes!$A$2:$A$1000,A11) -> 1
A12: WI-EW-09 | B12: Structure | C12: Earthwork | D12: Disposal of surplus earth | E12: cft | F12: m3 | G12: Excavation - backfill reused (loose) | H12: (WI-EW-01+WI-EW-02+WI-EW-03-WI-EW-04) * P_BULKING | I12: Derived | L12: =COUNTIF(Recipes!$A$2:$A$1000,A12) -> 1
A13: WI-CN-01 | B13: Structure | C13: Concrete | D13: PCC 1:4:8 in foundation base | E13: cft | F13: m3 | G13: Strip: length x PCC width x thickness; isolated: (L+2p)(B+2p)t | H13: SUM(strip.len_cl*strip.pcc_w*strip.pcc_t) + SUM(ftg.n*(ftg.L+2p)*(ftg.B+2p)*t) | I13: FDN_SECTION, FTG_ISO | J13: Drawing: PCC 1:4:8 | K13: PCC-01 | L13: =COUNTIF(Recipes!$A$2:$A$1000,A13) -> 3
A14: WI-CN-02 | B14: Structure | C14: Concrete | D14: PCC 1:4:8 floor base (GF, porch) | E14: cft | F14: m3 | G14: Floor area x thickness | H14: GF.net_floor_area * P_FLOOR_PCC_T | I14: ROOM (GF), PORCH | J14: 3 in | K14: GF-PCC-01 | L14: =COUNTIF(Recipes!$A$2:$A$1000,A14) -> 3
A15: WI-CN-03 | B15: Structure | C15: Concrete | D15: RCC 1:2:4 in isolated footings | E15: cft | F15: m3 | G15: n x L x B x D (+ pedestal) | H15: SUM(ftg.n*ftg.L*ftg.B*ftg.D) | I15: FTG_ISO | J15: Drawing C1 4x4, C2/C3 3x3 | K15: FTG-CONC-01 | L15: =COUNTIF(Recipes!$A$2:$A$1000,A15) -> 4
A16: WI-CN-04 | B16: Structure | C16: Concrete | D16: RCC in plinth / grade beams | E16: cft | F16: m3 | G16: Length x b x d | H16: SUM(pb.len*pb.b*pb.d) | I16: PLINTH_BEAM | J16: If specified (not in sample) | L16: =COUNTIF(Recipes!$A$2:$A$1000,A16) -> 4
A17: WI-CN-05 | B17: Structure | C17: Concrete | D17: RCC in columns | E17: cft | F17: m3 | G17: n x b x d x height (footing top to roof) | H17: SUM(col.n*col.b*col.d*col.h) | I17: COL | J17: C1 9x18, C2/C3 15x15 | K17: COL-CONC-01 | L17: =COUNTIF(Recipes!$A$2:$A$1000,A17) -> 4
A18: WI-CN-06 | B18: Structure | C18: Concrete | D18: RCC in beams (below slab soffit) | E18: cft | F18: m3 | G18: Length (clear) x b x (D - slab t) | H18: SUM(beam.len*beam.b*(beam.D-T_SLAB)) | I18: BEAM | K18: BEAM-CONC-01 | L18: =COUNTIF(Recipes!$A$2:$A$1000,A18) -> 4
A19: WI-CN-07 | B19: Structure | C19: Concrete | D19: RCC in floor & roof slabs | E19: cft | F19: m3 | G19: Slab area (outer face of bearing walls) - voids (stair, shafts) x thickness; per floor | H19: SUM(slab.area - slab.voids) * T_SLAB | I19: SLAB_AREA, SLAB_VOID, T_SLAB | J19: 6 in per elevations | K19: SLAB-CONC-01 | L19: =COUNTIF(Recipes!$A$2:$A$1000,A19) -> 4
A20: WI-CN-08 | B20: Structure | C20: Concrete | D20: RCC in staircase (waist, steps, landings) | E20: cft | F20: m3 | G20: Waist: inclined length x width x waist t; steps: 0.5 x R x G x width x n; landings: area x t | H20: stair.waist + stair.steps + stair.landings | I20: STAIR | K20: STAIR-CONC-01 | L20: =COUNTIF(Recipes!$A$2:$A$1000,A20) -> 4
A21: WI-CN-09 | B21: Structure | C21: Concrete | D21: RCC lintels & seismic bands (lintel/roof/sill) | E21: cft | F21: m3 | G21: Lintel: (opening W + 2 x bearing 9in) x wall t x depth; bands: wall centreline length x t x depth | H21: SUM(opening.W+2*P_BEARING)*t*d + SUM(wall.len_cl)*t*band_d | I21: WALL_CL_LEN, OPENINGS, BAND_LEN | J21: Recommend continuous bands (zone 2B) | K21: LINTEL-CONC-01 | L21: =COUNTIF(Recipes!$A$2:$A$1000,A21) -> 4
A22: WI-CN-10 | B22: Structure | C22: Concrete | D22: RCC chajjas, projections, balcony slabs, canopies | E22: cft | F22: m3 | G22: Length x projection x avg thickness | H22: SUM(proj.len*proj.w*proj.t) | I22: ELEVATIONS, BALCONY | L22: =COUNTIF(Recipes!$A$2:$A$1000,A22) -> 3
A23: WI-CN-11 | B23: Plumbing | C23: Concrete | D23: RCC in UG water tank / septic tank (base, walls, cover) | E23: cft | F23: m3 | G23: Base + walls (centreline perimeter x t x h) + cover slab - openings | H23: tank.base + tank.walls + tank.cover | I23: TANK_UG, TANK_SEPTIC | J23: Drawing: RCC 1:2:4, 6in walls, 4in slab | L23: =COUNTIF(Recipes!$A$2:$A$1000,A23) -> 4
A24: WI-CN-12 | B24: Structure | C24: Concrete | D24: DPC 1.5in PCC 1:2:4 with WP admixture, bitumen & polythene | E24: sft | F24: m2 | G24: Length of all walls at plinth x wall thickness (no deduction for door openings unless specified) | H24: SUM(wall_GF.len_cl * wall.t) | I24: WALL_CL_LEN (GF) | J24: Drawing sheet 14/15 | K24: DPC-01 | L24: =COUNTIF(Recipes!$A$2:$A$1000,A24) -> 6
A25: WI-CN-13 | B25: External | C25: Concrete | D25: Plinth protection / apron PCC 1:2:4 3in | E25: sft | F25: m2 | G25: External perimeter x apron width | H25: ext_perimeter * P_APRON_W | I25: Building footprint | J25: 2-3 ft wide | L25: =COUNTIF(Recipes!$A$2:$A$1000,A25) -> 3
A26: WI-RF-01 | B26: Structure | C26: Reinforcement | D26: Reinforcement in footings | E26: kg | F26: kg | G26: BBS if available; else V_footing x ratio | H26: BBS or WI-CN-03 * K_ST_FTG | I26: FTG_ISO / BBS | J26: ASTM A615 Gr60 | K26: FTG-STEEL-01 | L26: =COUNTIF(Recipes!$A$2:$A$1000,A26) -> 3
A27: WI-RF-02 | B27: Structure | C27: Reinforcement | D27: Reinforcement in columns | E27: kg | F27: kg | G27: BBS; else V x ratio (incl. laps, ties) | H27: BBS or WI-CN-05 * K_ST_COL | I27: COL / BBS | K27: COL-STEEL-01 | L27: =COUNTIF(Recipes!$A$2:$A$1000,A27) -> 4
A28: WI-RF-03 | B28: Structure | C28: Reinforcement | D28: Reinforcement in beams & plinth beams | E28: kg | F28: kg | G28: BBS; else V x ratio | H28: BBS or (WI-CN-06*K_ST_BEAM + WI-CN-04*K_ST_PB) | I28: BEAM / BBS | K28: BEAM-STEEL-01 | L28: =COUNTIF(Recipes!$A$2:$A$1000,A28) -> 4
A29: WI-RF-04 | B29: Structure | C29: Reinforcement | D29: Reinforcement in slabs | E29: kg | F29: kg | G29: BBS; else V x ratio | H29: BBS or WI-CN-07 * K_ST_SLAB | I29: SLAB / BBS | K29: SLAB-STEEL-01 | L29: =COUNTIF(Recipes!$A$2:$A$1000,A29) -> 3
A30: WI-RF-05 | B30: Structure | C30: Reinforcement | D30: Reinforcement in stairs | E30: kg | F30: kg | G30: BBS; else V x ratio | H30: BBS or WI-CN-08 * K_ST_STAIR | I30: STAIR / BBS | K30: STAIR-STEEL-01 | L30: =COUNTIF(Recipes!$A$2:$A$1000,A30) -> 3
A31: WI-RF-06 | B31: Structure | C31: Reinforcement | D31: Reinforcement in lintels, bands, chajjas | E31: kg | F31: kg | G31: BBS; else V x ratio | H31: BBS or (WI-CN-09+WI-CN-10) * K_ST_LINTEL | I31: BBS | K31: LINTEL-STEEL-01 | L31: =COUNTIF(Recipes!$A$2:$A$1000,A31) -> 3
A32: WI-RF-07 | B32: Plumbing | C32: Reinforcement | D32: Reinforcement in tanks (3/8in @ 6-12in c/c both faces) | E32: kg | F32: kg | G32: BBS from tank detail; else V x ratio | H32: BBS or WI-CN-11 * K_ST_TANK | I32: TANK details | J32: Drawing sheet 16 | L32: =COUNTIF(Recipes!$A$2:$A$1000,A32) -> 2
A33: WI-FW-01 | B33: Structure | C33: Formwork | D33: Formwork to slabs & beam soffits (steel shuttering, hired) | E33: sft | F33: m2 | G33: Soffit area + beam sides | H33: SUM(slab.area) + SUM(beam.len*2*(beam.D-T_SLAB)) | I33: SLAB_AREA, BEAM | K33: FORM-SLAB-01 | L33: =COUNTIF(Recipes!$A$2:$A$1000,A33) -> 4
A34: WI-FW-02 | B34: Structure | C34: Formwork | D34: Formwork to columns, footings, lintels, stairs, tanks (ply/timber) | E34: sft | F34: m2 | G34: Contact area of concrete surfaces | H34: SUM(contact areas) | I34: COL, FTG_ISO, STAIR, TANK, OPENINGS | K34: FORM-COL-01 | L34: =COUNTIF(Recipes!$A$2:$A$1000,A34) -> 4
A35: WI-MS-01 | B35: Structure | C35: Masonry | D35: Brick masonry in stepped foundations 1:6 (below DPC) | E35: cft | F35: m3 | G35: Sum over steps: centreline length x step width x step height; T-junction correction | H35: SUM(strip.len_cl * SUM(step.w*step.h)) | I35: FDN_SECTION, FDN_STRIP_LEN | J35: Drawing sections 1.1-6.6 | K35: FDN-MAS-01 | L35: =COUNTIF(Recipes!$A$2:$A$1000,A35) -> 3
A36: WI-MS-02 | B36: Structure | C36: Masonry | D36: Brick masonry 9in in superstructure 1:6 | E36: cft | F36: m3 | G36: Centreline length x height x 0.75 ft - openings - lintels/bands/columns embedded | H36: SUM(wall9.len_cl*wall.h*0.75) - SUM(openings in 9in walls)*0.75 - V(lintels,bands,cols) | I36: WALL_CL_LEN, WALL_H, OPENINGS | K36: MAS-01 | L36: =COUNTIF(Recipes!$A$2:$A$1000,A36) -> 4
A37: WI-MS-03 | B37: Architecture | C37: Masonry | D37: Brick masonry 4.5in partitions 1:4 | E37: sft | F37: m2 | G37: Length x height - openings | H37: SUM(wall45.len*wall.h) - SUM(openings in 4.5in walls) | I37: WALL_CL_LEN, OPENINGS | K37: MAS-01 | L37: =COUNTIF(Recipes!$A$2:$A$1000,A37) -> 3
A38: WI-MS-04 | B38: Structure | C38: Masonry | D38: Parapet walls 9in / 4.5in | E38: cft | F38: m3 | G38: Roof perimeter x parapet height x t | H38: roof.perimeter * H_PARAPET * t | I38: ROOF_AREA, H_PARAPET | J38: Drawing: 2-3 ft | K38: MAS-01 | L38: =COUNTIF(Recipes!$A$2:$A$1000,A38) -> 3
A39: WI-MS-05 | B39: Structure | C39: Masonry | D39: Brick soling (flat) under GF floors | E39: sft | F39: m2 | G39: GF floor area | H39: GF.net_floor_area | I39: ROOM (GF) | K39: GF-SOL-01 | L39: =COUNTIF(Recipes!$A$2:$A$1000,A39) -> 2
A40: WI-MS-06 | B40: Architecture | C40: Masonry | D40: Concrete block masonry 8in (alternative) | E40: sft | F40: m2 | G40: Length x height - openings | H40: SUM(len*h) - openings | I40: WALL_CL_LEN | J40: Only if specified | L40: =COUNTIF(Recipes!$A$2:$A$1000,A40) -> 3
A41: WI-PL-01 | B41: Architecture | C41: Plaster | D41: Internal cement plaster 1/2in (walls) | E41: sft | F41: m2 | G41: Room perimeter x (floor-to-ceiling ht) - openings >5 sft (deduct one face); add jambs/reveals | H41: SUM(room.perim*room.h) - openings + reveals | I41: ROOM, OPENINGS | J41: Mix per Recipes (default 1:6) | K41: PLAS-01 | L41: =COUNTIF(Recipes!$A$2:$A$1000,A41) -> 3
A42: WI-PL-02 | B42: Architecture | C42: Plaster | D42: External cement plaster 3/4in | E42: sft | F42: m2 | G42: Elevation areas (all faces incl. parapets both sides, boundary wall) - openings | H42: SUM(facade.area) + parapet*2 - openings | I42: FACADE_AREA, ELEVATIONS | J42: Mix default 1:4 | K42: PLAS-02 | L42: =COUNTIF(Recipes!$A$2:$A$1000,A42) -> 4
A43: WI-PL-03 | B43: Architecture | C43: Plaster | D43: Ceiling plaster 3/8in | E43: sft | F43: m2 | G43: Ceiling area of each room (incl. beam soffits/sides) | H43: SUM(room.area) + beam sides | I43: ROOM | K43: PLAS-03 | L43: =COUNTIF(Recipes!$A$2:$A$1000,A43) -> 2
A44: WI-PL-04 | B44: Plumbing | C44: Plaster | D44: Tank/manhole plaster 1:3 with WP compound | E44: sft | F44: m2 | G44: Internal surfaces of tanks/chambers | H44: SUM(tank.internal_area) | I44: TANK details | J44: Drawing: 1/2in with Puddlo | L44: =COUNTIF(Recipes!$A$2:$A$1000,A44) -> 3
A45: WI-WP-01 | B45: Architecture | C45: Waterproofing | D45: Roof treatment: bitumen 2 coats + polythene + earth + mud plaster + brick tiles | E45: sft | F45: m2 | G45: Roof area inside parapets (incl. mumty roof) + upturn 1ft on parapets | H45: roof.area + roof.perimeter*1 | I45: ROOF_AREA | J45: Traditional PK method | K45: ROOF-01 | L45: =COUNTIF(Recipes!$A$2:$A$1000,A45) -> 9
A46: WI-WP-02 | B46: Architecture | C46: Waterproofing | D46: Roof treatment alternative: EPS/XPS insulation + screed + membrane/tiles | E46: sft | F46: m2 | G46: As WI-WP-01 | H46: roof.area + upturns | I46: ROOF_AREA | J46: Premium alternative | K46: WP-01 | L46: =COUNTIF(Recipes!$A$2:$A$1000,A46) -> 4
A47: WI-WP-03 | B47: Architecture | C47: Waterproofing | D47: Wet-area waterproofing (baths, kitchen, laundry, terraces) | E47: sft | F47: m2 | G47: Floor area + 1ft upturn; shower walls to 6ft | H47: SUM(wet.area + wet.perim*1) + shower walls | I47: ROOM (wet), TERRACE_AREA | J47: Cementitious 2-component | K47: WP-01 | L47: =COUNTIF(Recipes!$A$2:$A$1000,A47) -> 1
A48: WI-WP-04 | B48: Architecture | C48: Waterproofing | D48: Slope screed 1:4 (roof, terraces, baths) | E48: sft | F48: m2 | G48: Area | H48: roof.area + terraces + baths | I48: ROOF_AREA, ROOM | J48: avg 2in | L48: =COUNTIF(Recipes!$A$2:$A$1000,A48) -> 3
A49: WI-FL-01 | B49: Architecture | C49: Flooring | D49: Porcelain floor tiles on mortar bed (rooms, lounges) | E49: sft | F49: m2 | G49: Room net floor area (inside plaster) + door thresholds | H49: SUM(room.area where finish=porcelain) | I49: ROOM, Room_Defaults | J49: 24x24 in | K49: FLR-01 | L49: =COUNTIF(Recipes!$A$2:$A$1000,A49) -> 5
A50: WI-FL-02 | B50: Architecture | C50: Flooring | D50: Ceramic anti-skid floor tiles (baths, kitchen, laundry) | E50: sft | F50: m2 | G50: Room net area | H50: SUM(room.area where wet) | I50: ROOM | J50: 12x12 / 16x16 | K50: FLR-01 | L50: =COUNTIF(Recipes!$A$2:$A$1000,A50) -> 5
A51: WI-FL-03 | B51: Architecture | C51: Flooring | D51: Wall tiles (bath full height, kitchen backsplash) | E51: sft | F51: m2 | G51: Perimeter x tile height - openings | H51: SUM(room.perim*tile_h) - openings | I51: ROOM, Room_Defaults | J51: 8-9 ft in baths | K51: FLR-01 | L51: =COUNTIF(Recipes!$A$2:$A$1000,A51) -> 4
A52: WI-FL-04 | B52: Architecture | C52: Flooring | D52: Marble flooring (stairs landings, lobby, optional rooms) | E52: sft | F52: m2 | G52: Area | H52: SUM(area where finish=marble) | I52: ROOM | J52: 3/4 in local marble | K52: FLR-01 | L52: =COUNTIF(Recipes!$A$2:$A$1000,A52) -> 5
A53: WI-FL-05 | B53: Architecture | C53: Flooring | D53: Skirting 4in | E53: rft | F53: m | G53: Room perimeter - door widths | H53: SUM(room.perim) - SUM(door.W) | I53: ROOM, DOOR_SCHED | L53: =COUNTIF(Recipes!$A$2:$A$1000,A53) -> 2
A54: WI-FL-06 | B54: Architecture | C54: Flooring | D54: Stair treads & risers marble | E54: rft | F54: m | G54: n_steps x stair width | H54: stair.n_steps * stair.width | I54: STAIR | L54: =COUNTIF(Recipes!$A$2:$A$1000,A54) -> 2
A55: WI-FL-07 | B55: External | C55: Flooring | D55: Outdoor pavers / tiles (porch, driveway, terraces) | E55: sft | F55: m2 | G55: Area | H55: porch.area + terraces + driveway | I55: PORCH, TERRACE_AREA, PAVING_AREA | J55: 60/80mm pavers | L55: =COUNTIF(Recipes!$A$2:$A$1000,A55) -> 2
A56: WI-FL-08 | B56: Architecture | C56: Flooring | D56: Window sills & door thresholds (marble) | E56: rft | F56: m | G56: Sum of window widths + door widths | H56: SUM(win.W) + SUM(door.W) | I56: WIN_SCHED, DOOR_SCHED | L56: =COUNTIF(Recipes!$A$2:$A$1000,A56) -> 1
A57: WI-DW-01 | B57: Architecture | C57: Doors | D57: Door frames (chogath) solid wood | E57: rft | F57: m | G57: Per door: 2 x height + width (3-sided) | H57: SUM(door.n*(2*door.H+door.W)) | I57: DOOR_SCHED | J57: Drawing sheet 20: 5in/10in | K57: DOOR-01 | L57: =COUNTIF(Recipes!$A$2:$A$1000,A57) -> 2
A58: WI-DW-02 | B58: Architecture | C58: Doors | D58: Door shutters | E58: sft | F58: m2 | G58: Leaf W x H per door | H58: SUM(door.n*door.W*door.H) | I58: DOOR_SCHED | K58: DOOR-01 | L58: =COUNTIF(Recipes!$A$2:$A$1000,A58) -> 1
A59: WI-DW-03 | B59: Architecture | C59: Doors | D59: Door hardware sets | E59: Nos | F59: Nos | G59: 1 set per leaf | H59: SUM(door.n*door.leaves) | I59: DOOR_SCHED | L59: =COUNTIF(Recipes!$A$2:$A$1000,A59) -> 1
A60: WI-DW-04 | B60: Architecture | C60: Windows | D60: Aluminium/uPVC windows with glazing | E60: sft | F60: m2 | G60: Opening W x H per window | H60: SUM(win.n*win.W*win.H) | I60: WIN_SCHED | J60: Drawing gives sill+height only | K60: WINDOW-01 | L60: =COUNTIF(Recipes!$A$2:$A$1000,A60) -> 4
A61: WI-DW-05 | B61: Architecture | C61: Metalwork | D61: MS window grills | E61: sft | F61: m2 | G61: Window area where grills specified | H61: SUM(win.area where grill) | I61: WIN_SCHED | L61: =COUNTIF(Recipes!$A$2:$A$1000,A61) -> 1
A62: WI-DW-06 | B62: Architecture | C62: Metalwork | D62: Stair & balcony railings | E62: rft | F62: m | G62: Stair flight inclined length + landing edges; balcony/terrace edge length | H62: stair.rail_len + balcony.edge_len | I62: STAIR, BALCONY | L62: =COUNTIF(Recipes!$A$2:$A$1000,A62) -> 1
A63: WI-DW-07 | B63: External | C63: Metalwork | D63: Main gate MS | E63: sft | F63: m2 | G63: Gate W x H | H63: gate.W*gate.H | I63: GATE | L63: =COUNTIF(Recipes!$A$2:$A$1000,A63) -> 1
A64: WI-CL-01 | B64: Architecture | C64: Ceiling | D64: Gypsum board false ceiling (bulkhead/partial) | E64: sft | F64: m2 | G64: Room area x false-ceiling fraction | H64: SUM(room.area*room.fc_pct) | I64: ROOM, Room_Defaults | L64: =COUNTIF(Recipes!$A$2:$A$1000,A64) -> 3
A65: WI-PT-01 | B65: Architecture | C65: Paint | D65: Interior walls: putty 2 coats + primer + emulsion 2 coats | E65: sft | F65: m2 | G65: Plastered internal wall area (= WI-PL-01) - tiled area | H65: WI-PL-01 - WI-FL-03 | I65: Derived | K65: PAINT-01 | L65: =COUNTIF(Recipes!$A$2:$A$1000,A65) -> 3
A66: WI-PT-02 | B66: Architecture | C66: Paint | D66: Ceilings: putty + primer + emulsion | E66: sft | F66: m2 | G66: Rule: ceiling plaster area | H66: WI-PL-03 | I66: Derived | K66: PAINT-03 | L66: =COUNTIF(Recipes!$A$2:$A$1000,A66) -> 3
A67: WI-PT-03 | B67: Architecture | C67: Paint | D67: Exterior: primer + weather coat 2 coats | E67: sft | F67: m2 | G67: Rule: external plaster area - cladding | H67: WI-PL-02 - cladding | I67: Derived | K67: PAINT-02 | L67: =COUNTIF(Recipes!$A$2:$A$1000,A67) -> 2
A68: WI-PT-04 | B68: Architecture | C68: Paint | D68: Enamel on MS works (grills, gate, railings) | E68: sft | F68: m2 | G68: Both faces of grill/gate area | H68: 2*(WI-DW-05+WI-DW-07) + railings*2 | I68: Derived | L68: =COUNTIF(Recipes!$A$2:$A$1000,A68) -> 3
A69: WI-PT-05 | B69: Architecture | C69: Paint | D69: Wood polish/lacquer on doors & frames | E69: sft | F69: m2 | G69: 2 faces of shutters + frame surfaces | H69: 2*WI-DW-02 + WI-DW-01*(K_CHOG_W+2*K_CHOG_T)/12 | I69: Derived | L69: =COUNTIF(Recipes!$A$2:$A$1000,A69) -> 2
A70: WI-EL-01 | B70: Electrical | C70: Wiring | D70: Light point (incl. switch, box, 3/29 wire, conduit) | E70: Nos | F70: Nos | G70: Count light symbols (all types) per floor | H70: COUNT(symbol in [light,downlight,tube,wall light,chandelier,step,mirror]) | I70: EL_POINTS | K70: ELEC-01 | L70: =COUNTIF(Recipes!$A$2:$A$1000,A70) -> 6
A71: WI-EL-02 | B71: Electrical | C71: Wiring | D71: Fan point (incl. regulator) | E71: Nos | F71: Nos | G71: Count ceiling fan symbols | H71: COUNT(symbol=ceiling_fan) | I71: EL_POINTS | K71: ELEC-01 | L71: =COUNTIF(Recipes!$A$2:$A$1000,A71) -> 6
A72: WI-EL-03 | B72: Electrical | C72: Wiring | D72: 13A socket point (7/29) | E72: Nos | F72: Nos | G72: Count 2x13A switched sockets, fridge sockets | H72: COUNT(symbol in [socket_13A,fridge]) | I72: EL_POINTS | K72: ELEC-01 | L72: =COUNTIF(Recipes!$A$2:$A$1000,A72) -> 6
A73: WI-EL-04 | B73: Electrical | C73: Wiring | D73: 15A power / geyser / cooker point | E73: Nos | F73: Nos | G73: Count 15A, water heater, cooker symbols | H73: COUNT(symbol in [socket_15A,water_heater,cooker]) | I73: EL_POINTS | K73: ELEC-01 | L73: =COUNTIF(Recipes!$A$2:$A$1000,A73) -> 5
A74: WI-EL-05 | B74: Electrical | C74: Wiring | D74: AC point (7/36, 1in conduit, isolator) | E74: Nos | F74: Nos | G74: Count split unit / AC switch symbols | H74: COUNT(symbol in [split_ac,ac_switch]) | I74: EL_POINTS | K74: ELEC-01 | L74: =COUNTIF(Recipes!$A$2:$A$1000,A74) -> 5
A75: WI-EL-06 | B75: Electrical | C75: Wiring | D75: Low-voltage points (TV, data, intercom, CCTV) | E75: Nos | F75: Nos | G75: Count symbols | H75: COUNT(symbol in [tv,data,intercom,cctv]) | I75: EL_POINTS | L75: =COUNTIF(Recipes!$A$2:$A$1000,A75) -> 3
A76: WI-EL-07 | B76: Electrical | C76: Distribution | D76: Sub-main feeders (main DB to floor DBs), 7/44 | E76: rft | F76: m | G76: Vertical rise + horizontal route | H76: SUM(floor_db.route_len) | I76: EL_DB_DIST, H_FLOOR | L76: =COUNTIF(Recipes!$A$2:$A$1000,A76) -> 3
A77: WI-EL-08 | B77: Electrical | C77: Distribution | D77: Distribution boards with MCBs/RCCB | E77: Nos | F77: Nos | G77: 1 main + 1 per floor (+ UPS/solar DB) | H77: N_FLOORS + 1 | I77: N_FLOORS | L77: =COUNTIF(Recipes!$A$2:$A$1000,A77) -> 2
A78: WI-EL-09 | B78: Electrical | C78: Earthing | D78: Earthing pit complete (drawing detail) | E78: Nos | F78: Nos | G78: Min 1 per DB system; 2 recommended | H78: P_EARTH_PITS | I78: EL detail sheet 29-30 | J78: Copper spike / GI pipe 10ft | L78: =COUNTIF(Recipes!$A$2:$A$1000,A78) -> 2
A79: WI-EL-10 | B79: Electrical | C79: Fixtures | D79: Light fixtures & fans supply | E79: Nos | F79: Nos | G79: Rule: counts from WI-EL-01/02 by fixture type | H79: by symbol | I79: EL_POINTS | L79: =COUNTIF(Recipes!$A$2:$A$1000,A79) -> 0
A80: WI-HV-01 | B80: HVAC | C80: AC | D80: Split AC pre-piping (copper, insulation, drain, cable) | E80: Nos | F80: Nos | G80: 1 per AC point | H80: COUNT(split_ac) | I80: AC_UNITS | L80: =COUNTIF(Recipes!$A$2:$A$1000,A80) -> 6
A81: WI-HV-02 | B81: HVAC | C81: Ventilation | D81: Exhaust fan installation | E81: Nos | F81: Nos | G81: 1 per bath/kitchen/laundry (symbol count) | H81: COUNT(exhaust_fan) | I81: EXH_FANS | L81: =COUNTIF(Recipes!$A$2:$A$1000,A81) -> 1
A82: WI-PB-01 | B82: Plumbing | C82: Sanitary | D82: WC complete (concealed cistern, wall-hung) | E82: Nos | F82: Nos | G82: Count WC symbols | H82: COUNT(wc) | I82: PB_FIXTURES | J82: Drawing: concealed WC | K82: PLUMB-01 | L82: =COUNTIF(Recipes!$A$2:$A$1000,A82) -> 6
A83: WI-PB-02 | B83: Plumbing | C83: Sanitary | D83: Wash basin/vanity complete | E83: Nos | F83: Nos | G83: Count | H83: COUNT(basin) | I83: PB_FIXTURES | K83: PLUMB-01 | L83: =COUNTIF(Recipes!$A$2:$A$1000,A83) -> 7
A84: WI-PB-03 | B84: Plumbing | C84: Sanitary | D84: Shower complete (concealed mixer) | E84: Nos | F84: Nos | G84: Count | H84: COUNT(shower) | I84: PB_FIXTURES | K84: PLUMB-01 | L84: =COUNTIF(Recipes!$A$2:$A$1000,A84) -> 4
A85: WI-PB-04 | B85: Plumbing | C85: Sanitary | D85: Health faucet (Muslim shower) | E85: Nos | F85: Nos | G85: 1 per WC | H85: COUNT(wc) | I85: PB_FIXTURES | K85: PLUMB-01 | L85: =COUNTIF(Recipes!$A$2:$A$1000,A85) -> 2
A86: WI-PB-05 | B86: Plumbing | C86: Drainage | D86: Floor trap with waste line | E86: Nos | F86: Nos | G86: Count F.T symbols | H86: COUNT(FT) | I86: PB_FT | J86: Drawing: F.T | K86: PLUMB-01 | L86: =COUNTIF(Recipes!$A$2:$A$1000,A86) -> 2
A87: WI-PB-06 | B87: Plumbing | C87: Water supply | D87: Bathroom group risers, vents, fittings (per bathroom) | E87: Nos | F87: Nos | G87: 1 per bathroom | H87: COUNT(bathroom) | I87: ROOM (bath) | L87: =COUNTIF(Recipes!$A$2:$A$1000,A87) -> 7
A88: WI-PB-07 | B88: Kitchen | C88: Sanitary | D88: Kitchen sink point complete | E88: Nos | F88: Nos | G88: Count | H88: COUNT(kitchen_sink) | I88: PB_FIXTURES | K88: KITCH-01 | L88: =COUNTIF(Recipes!$A$2:$A$1000,A88) -> 6
A89: WI-PB-08 | B89: Plumbing | C89: Sanitary | D89: Washing machine point | E89: Nos | F89: Nos | G89: Count (laundry) | H89: COUNT(wm) | I89: ROOM (laundry) | L89: =COUNTIF(Recipes!$A$2:$A$1000,A89) -> 2
A90: WI-PB-09 | B90: Plumbing | C90: Drainage | D90: Rainwater pipes 3-4in | E90: rft | F90: m | G90: n_RWP x (building height + 2ft) | H90: RWP_COUNT*(H_total+2) | I90: RWP_COUNT | J90: Drawing: 3in/4in RWP | K90: WSD-01 | L90: =COUNTIF(Recipes!$A$2:$A$1000,A90) -> 2
A91: WI-PB-10 | B91: Plumbing | C91: Drainage | D91: Roof outlet khura with grating | E91: Nos | F91: Nos | G91: 1 per RWP | H91: RWP_COUNT | I91: RWP_COUNT | J91: Drawing: khura 2x2 ft | L91: =COUNTIF(Recipes!$A$2:$A$1000,A91) -> 1
A92: WI-PB-11 | B92: Plumbing | C92: Drainage | D92: External sewer line with sand bedding | E92: rft | F92: m | G92: Measured along route from GT/MH to street | H92: SUM(sewer.len) | I92: SEWER_EXT_LEN | J92: RCC/uPVC 6in | K92: WSD-01 | L92: =COUNTIF(Recipes!$A$2:$A$1000,A92) -> 2
A93: WI-PB-12 | B93: Plumbing | C93: Drainage | D93: Manhole up to 3ft depth complete | E93: Nos | F93: Nos | G93: Count M.H symbols | H93: COUNT(MH) | I93: PB_MH | J93: Drawing sheet 24 | K93: WSD-01 | L93: =COUNTIF(Recipes!$A$2:$A$1000,A93) -> 6
A94: WI-PB-13 | B94: Plumbing | C94: Drainage | D94: Gully trap complete | E94: Nos | F94: Nos | G94: Count G.T symbols | H94: COUNT(GT) | I94: PB_GT | K94: WSD-01 | L94: =COUNTIF(Recipes!$A$2:$A$1000,A94) -> 5
A95: WI-PB-14 | B95: Plumbing | C95: Water supply | D95: Pumps, OH tank, main supply, valves (system) | E95: LS | F95: LS | G95: 1 per house | H95: 1 | I95: TANK_OH, PB legend | J95: 600 gal FG tank per drawing | K95: WSD-01 | L95: =COUNTIF(Recipes!$A$2:$A$1000,A95) -> 0
A96: WI-GS-01 | B96: Plumbing | C96: Gas | D96: Gas point (GI pipe, valve, fittings) | E96: Nos | F96: Nos | G96: Count gas points (cooker + heaters + geyser) | H96: COUNT(gas_point) | I96: GAS_POINTS | J96: Drawing: 3/4in GI | L96: =COUNTIF(Recipes!$A$2:$A$1000,A96) -> 3
A97: WI-KT-01 | B97: Kitchen | C97: Kitchen | D97: Base cabinets | E97: rft | F97: m | G97: Counter run length | H97: SUM(kitchen.counter_len) | I97: ROOM (kitchen) | K97: KITCH-01 | L97: =COUNTIF(Recipes!$A$2:$A$1000,A97) -> 4
A98: WI-KT-02 | B98: Kitchen | C98: Kitchen | D98: Wall cabinets | E98: rft | F98: m | G98: Wall cabinet run | H98: SUM(kitchen.wallcab_len) | I98: ROOM (kitchen) | K98: KITCH-01 | L98: =COUNTIF(Recipes!$A$2:$A$1000,A98) -> 3
A99: WI-KT-03 | B99: Kitchen | C99: Kitchen | D99: Countertop | E99: rft | F99: m | G99: Counter run | H99: SUM(kitchen.counter_len) | I99: ROOM (kitchen) | K99: KITCH-01 | L99: =COUNTIF(Recipes!$A$2:$A$1000,A99) -> 1
A100: WI-JN-01 | B100: Architecture | C100: Joinery | D100: Built-in wardrobes | E100: sft | F100: m2 | G100: Face area = length x height | H100: SUM(wardrobe.L*wardrobe.H) | I100: WARDROBE | J100: Drawing: 3 wardrobes FF | L100: =COUNTIF(Recipes!$A$2:$A$1000,A100) -> 3
...

Sheet Recipes
A1: WI_ID | B1: Work Item | C1: Mat_ID | D1: Material | E1: Driver Coeff_ID | F1: Mix_Ref | G1: Mix_Component | H1: Coefficient (material per unit of WI) | I1: Coeff Unit | J1: Basis | K1: Material Unit | L1: Wastage %
A2: WI-PRE-02 | B2: =INDEX(Work_Items!$D$2:$D$300,MATCH(A2,Work_Items!$A$2:$A$300,0)) -> Construction water (tanker / bore) | C2: MSC-001 | D2: =INDEX(Material_Master!$D$2:$D$1000,MATCH(C2,Material_Master!$A$2:$A$1000,0)) -> Construction water (tanker/bore) for mixing & curing | E2: K_ONE | H2: =Coefficients!$D$2 -> 1 | I2: gal/gal | J2: Qty computed in work item | K2: =INDEX(Material_Master!$F$2:$F$1000,MATCH(C2,Material_Master!$A$2:$A$1000,0)) -> gal | L2: =INDEX(Material_Master!$Q$2:$Q$1000,MATCH(C2,Material_Master!$A$2:$A$1000,0)) -> 0
A3: WI-EW-05 | B3: =INDEX(Work_Items!$D$2:$D$300,MATCH(A3,Work_Items!$A$2:$A$300,0)) -> Plinth filling with imported earth, compacted | C3: EW-002 | D3: =INDEX(Material_Master!$D$2:$D$1000,MATCH(C3,Material_Master!$A$2:$A$1000,0)) -> Imported earth for plinth filling | E3: K_FILL_COMPACT | H3: =Coefficients!$D$67 -> 1.2 | I3: cft/cft | J3: Loose imported earth per compacted cft | K3: =INDEX(Material_Master!$F$2:$F$1000,MATCH(C3,Material_Master!$A$2:$A$1000,0)) -> cft | L3: =INDEX(Material_Master!$Q$2:$Q$1000,MATCH(C3,Material_Master!$A$2:$A$1000,0)) -> 0
A4: WI-EW-06 | B4: =INDEX(Work_Items!$D$2:$D$300,MATCH(A4,Work_Items!$A$2:$A$300,0)) -> Sand filling under floors | C4: EW-003 | D4: =INDEX(Material_Master!$D$2:$D$1000,MATCH(C4,Material_Master!$A$2:$A$1000,0)) -> Sand filling under floors (local 'bhal' / kassi sand) | E4: K_SAND_COMPACT | H4: =Coefficients!$D$68 -> 1.15 | I4: cft/cft | K4: =INDEX(Material_Master!$F$2:$F$1000,MATCH(C4,Material_Master!$A$2:$A$1000,0)) -> cft | L4: =INDEX(Material_Master!$Q$2:$Q$1000,MATCH(C4,Material_Master!$A$2:$A$1000,0)) -> 0.1
A5: WI-EW-07 | B5: =INDEX(Work_Items!$D$2:$D$300,MATCH(A5,Work_Items!$A$2:$A$300,0)) -> Anti-termite treatment (foundation trenches, plinth, floor) | C5: EW-004 | D5: =INDEX(Material_Master!$D$2:$D$1000,MATCH(C5,Material_Master!$A$2:$A$1000,0)) -> Anti-termite chemical | E5: K_AT_L_SFT | H5: =Coefficients!$D$69 -> 0.025 | I5: L/sft | J5: Per label | K5: =INDEX(Material_Master!$F$2:$F$1000,MATCH(C5,Material_Master!$A$2:$A$1000,0)) -> L | L5: =INDEX(Material_Master!$Q$2:$Q$1000,MATCH(C5,Material_Master!$A$2:$A$1000,0)) -> 0.05
A6: WI-EW-08 | B6: =INDEX(Work_Items!$D$2:$D$300,MATCH(A6,Work_Items!$A$2:$A$300,0)) -> Polythene vapour barrier under GF floor PCC | C6: EW-007 | D6: =INDEX(Material_Master!$D$2:$D$1000,MATCH(C6,Material_Master!$A$2:$A$1000,0)) -> Polythene vapour barrier under GF floor | E6: K_RF_POLY | H6: =Coefficients!$D$54 -> 1.15 | I6: sft/sft | J6: incl. overlap | K6: =INDEX(Material_Master!$F$2:$F$1000,MATCH(C6,Material_Master!$A$2:$A$1000,0)) -> sft | L6: =INDEX(Material_Master!$Q$2:$Q$1000,MATCH(C6,Material_Master!$A$2:$A$1000,0)) -> 0.05
A7: WI-EW-09 | B7: =INDEX(Work_Items!$D$2:$D$300,MATCH(A7,Work_Items!$A$2:$A$300,0)) -> Disposal of surplus earth | C7: EW-001 | D7: =INDEX(Material_Master!$D$2:$D$1000,MATCH(C7,Material_Master!$A$2:$A$1000,0)) -> Surplus excavated earth - disposal (tractor trolley loads) | E7: K_ONE | H7: =Coefficients!$D$2 -> 1 | I7: cft/cft | K7: =INDEX(Material_Master!$F$2:$F$1000,MATCH(C7,Material_Master!$A$2:$A$1000,0)) -> cft | L7: =INDEX(Material_Master!$Q$2:$Q$1000,MATCH(C7,Material_Master!$A$2:$A$1000,0)) -> 0
A8: WI-CN-01 | B8: =INDEX(Work_Items!$D$2:$D$300,MATCH(A8,Work_Items!$A$2:$A$300,0)) -> PCC 1:4:8 in foundation base | C8: CON-001 | D8: =INDEX(Material_Master!$D$2:$D$1000,MATCH(C8,Material_Master!$A$2:$A$1000,0)) -> Ordinary Portland Cement (OPC) - 50 kg bag | E8: K_ONE | F8: MX_PCC148 | G8: cement | H8: =Coefficients!$D$2*Mix_Design!$J$2 -> 0.096608277 | I8: bag/cft | J8: Mix_Design | K8: =INDEX(Material_Master!$F$2:$F$1000,MATCH(C8,Material_Master!$A$2:$A$1000,0)) -> bag | L8: =INDEX(Material_Master!$Q$2:$Q$1000,MATCH(C8,Material_Master!$A$2:$A$1000,0)) -> 0.02
A9: WI-CN-01 | B9: =INDEX(Work_Items!$D$2:$D$300,MATCH(A9,Work_Items!$A$2:$A$300,0)) -> PCC 1:4:8 in foundation base | C9: CON-004 | D9: =INDEX(Material_Master!$D$2:$D$1000,MATCH(C9,Material_Master!$A$2:$A$1000,0)) -> Coarse sand for concrete (Lawrencepur) | E9: K_ONE | F9: MX_PCC148 | G9: sand | H9: =Coefficients!$D$2*Mix_Design!$K$2 -> 0.47384615 | I9: cft/cft | J9: Mix_Design | K9: =INDEX(Material_Master!$F$2:$F$1000,MATCH(C9,Material_Master!$A$2:$A$1000,0)) -> cft | L9: =INDEX(Material_Master!$Q$2:$Q$1000,MATCH(C9,Material_Master!$A$2:$A$1000,0)) -> 0.1
A10: WI-CN-01 | B10: =INDEX(Work_Items!$D$2:$D$300,MATCH(A10,Work_Items!$A$2:$A$300,0)) -> PCC 1:4:8 in foundation base | C10: CON-008 | D10: =INDEX(Material_Master!$D$2:$D$1000,MATCH(C10,Material_Master!$A$2:$A$1000,0)) -> Crushed stone 1.5in down (or brick ballast) | E10: K_ONE | F10: MX_PCC148 | G10: agg | H10: =Coefficients!$D$2*Mix_Design!$L$2 -> 0.94769231 | I10: cft/cft | J10: Mix_Design | K10: =INDEX(Material_Master!$F$2:$F$1000,MATCH(C10,Material_Master!$A$2:$A$1000,0)) -> cft | L10: =INDEX(Material_Master!$Q$2:$Q$1000,MATCH(C10,Material_Master!$A$2:$A$1000,0)) -> 0.075
A11: WI-CN-02 | B11: =INDEX(Work_Items!$D$2:$D$300,MATCH(A11,Work_Items!$A$2:$A$300,0)) -> PCC 1:4:8 floor base (GF, porch) | C11: CON-001 | D11: =INDEX(Material_Master!$D$2:$D$1000,MATCH(C11,Material_Master!$A$2:$A$1000,0)) -> Ordinary Portland Cement (OPC) - 50 kg bag | E11: K_ONE | F11: MX_PCC148 | G11: cement | H11: =Coefficients!$D$2*Mix_Design!$J$2 -> 0.096608277 | I11: bag/cft | J11: Mix_Design | K11: =INDEX(Material_Master!$F$2:$F$1000,MATCH(C11,Material_Master!$A$2:$A$1000,0)) -> bag | L11: =INDEX(Material_Master!$Q$2:$Q$1000,MATCH(C11,Material_Master!$A$2:$A$1000,0)) -> 0.02
A12: WI-CN-02 | B12: =INDEX(Work_Items!$D$2:$D$300,MATCH(A12,Work_Items!$A$2:$A$300,0)) -> PCC 1:4:8 floor base (GF, porch) | C12: CON-004 | D12: =INDEX(Material_Master!$D$2:$D$1000,MATCH(C12,Material_Master!$A$2:$A$1000,0)) -> Coarse sand for concrete (Lawrencepur) | E12: K_ONE | F12: MX_PCC148 | G12: sand | H12: =Coefficients!$D$2*Mix_Design!$K$2 -> 0.47384615 | I12: cft/cft | J12: Mix_Design | K12: =INDEX(Material_Master!$F$2:$F$1000,MATCH(C12,Material_Master!$A$2:$A$1000,0)) -> cft | L12: =INDEX(Material_Master!$Q$2:$Q$1000,MATCH(C12,Material_Master!$A$2:$A$1000,0)) -> 0.1
A13: WI-CN-02 | B13: =INDEX(Work_Items!$D$2:$D$300,MATCH(A13,Work_Items!$A$2:$A$300,0)) -> PCC 1:4:8 floor base (GF, porch) | C13: CON-008 | D13: =INDEX(Material_Master!$D$2:$D$1000,MATCH(C13,Material_Master!$A$2:$A$1000,0)) -> Crushed stone 1.5in down (or brick ballast) | E13: K_ONE | F13: MX_PCC148 | G13: agg | H13: =Coefficients!$D$2*Mix_Design!$L$2 -> 0.94769231 | I13: cft/cft | J13: Mix_Design | K13: =INDEX(Material_Master!$F$2:$F$1000,MATCH(C13,Material_Master!$A$2:$A$1000,0)) -> cft | L13: =INDEX(Material_Master!$Q$2:$Q$1000,MATCH(C13,Material_Master!$A$2:$A$1000,0)) -> 0.075
A14: WI-CN-03 | B14: =INDEX(Work_Items!$D$2:$D$300,MATCH(A14,Work_Items!$A$2:$A$300,0)) -> RCC 1:2:4 in isolated footings | C14: CON-001 | D14: =INDEX(Material_Master!$D$2:$D$1000,MATCH(C14,Material_Master!$A$2:$A$1000,0)) -> Ordinary Portland Cement (OPC) - 50 kg bag | E14: K_ONE | F14: MX_RCC124 | G14: cement | H14: =Coefficients!$D$2*Mix_Design!$J$4 -> 0.17941537 | I14: bag/cft | J14: Mix_Design | K14: =INDEX(Material_Master!$F$2:$F$1000,MATCH(C14,Material_Master!$A$2:$A$1000,0)) -> bag | L14: =INDEX(Material_Master!$Q$2:$Q$1000,MATCH(C14,Material_Master!$A$2:$A$1000,0)) -> 0.02
A15: WI-CN-03 | B15: =INDEX(Work_Items!$D$2:$D$300,MATCH(A15,Work_Items!$A$2:$A$300,0)) -> RCC 1:2:4 in isolated footings | C15: CON-004 | D15: =INDEX(Material_Master!$D$2:$D$1000,MATCH(C15,Material_Master!$A$2:$A$1000,0)) -> Coarse sand for concrete (Lawrencepur) | E15: K_ONE | F15: MX_RCC124 | G15: sand | H15: =Coefficients!$D$2*Mix_Design!$K$4 -> 0.44 | I15: cft/cft | J15: Mix_Design | K15: =INDEX(Material_Master!$F$2:$F$1000,MATCH(C15,Material_Master!$A$2:$A$1000,0)) -> cft | L15: =INDEX(Material_Master!$Q$2:$Q$1000,MATCH(C15,Material_Master!$A$2:$A$1000,0)) -> 0.1
A16: WI-CN-03 | B16: =INDEX(Work_Items!$D$2:$D$300,MATCH(A16,Work_Items!$A$2:$A$300,0)) -> RCC 1:2:4 in isolated footings | C16: CON-006 | D16: =INDEX(Material_Master!$D$2:$D$1000,MATCH(C16,Material_Master!$A$2:$A$1000,0)) -> Crushed stone 3/4in down (Margalla crush) | E16: K_ONE | F16: MX_RCC124 | G16: agg | H16: =Coefficients!$D$2*Mix_Design!$L$4 -> 0.88 | I16: cft/cft | J16: Mix_Design | K16: =INDEX(Material_Master!$F$2:$F$1000,MATCH(C16,Material_Master!$A$2:$A$1000,0)) -> cft | L16: =INDEX(Material_Master!$Q$2:$Q$1000,MATCH(C16,Material_Master!$A$2:$A$1000,0)) -> 0.075
A17: WI-CN-03 | B17: =INDEX(Work_Items!$D$2:$D$300,MATCH(A17,Work_Items!$A$2:$A$300,0)) -> RCC 1:2:4 in isolated footings | C17: CON-013 | D17: =INDEX(Material_Master!$D$2:$D$1000,MATCH(C17,Material_Master!$A$2:$A$1000,0)) -> Cover blocks / rebar spacers | E17: K_COVERBLK_CFT | H17: =Coefficients!$D$99 -> 1 | I17: Nos/cft | J17: Allowance | K17: =INDEX(Material_Master!$F$2:$F$1000,MATCH(C17,Material_Master!$A$2:$A$1000,0)) -> Nos | L17: =INDEX(Material_Master!$Q$2:$Q$1000,MATCH(C17,Material_Master!$A$2:$A$1000,0)) -> 0.05
A18: WI-CN-04 | B18: =INDEX(Work_Items!$D$2:$D$300,MATCH(A18,Work_Items!$A$2:$A$300,0)) -> RCC in plinth / grade beams | C18: CON-001 | D18: =INDEX(Material_Master!$D$2:$D$1000,MATCH(C18,Material_Master!$A$2:$A$1000,0)) -> Ordinary Portland Cement (OPC) - 50 kg bag | E18: K_ONE | F18: MX_RCC124 | G18: cement | H18: =Coefficients!$D$2*Mix_Design!$J$4 -> 0.17941537 | I18: bag/cft | J18: Mix_Design | K18: =INDEX(Material_Master!$F$2:$F$1000,MATCH(C18,Material_Master!$A$2:$A$1000,0)) -> bag | L18: =INDEX(Material_Master!$Q$2:$Q$1000,MATCH(C18,Material_Master!$A$2:$A$1000,0)) -> 0.02
A19: WI-CN-04 | B19: =INDEX(Work_Items!$D$2:$D$300,MATCH(A19,Work_Items!$A$2:$A$300,0)) -> RCC in plinth / grade beams | C19: CON-004 | D19: =INDEX(Material_Master!$D$2:$D$1000,MATCH(C19,Material_Master!$A$2:$A$1000,0)) -> Coarse sand for concrete (Lawrencepur) | E19: K_ONE | F19: MX_RCC124 | G19: sand | H19: =Coefficients!$D$2*Mix_Design!$K$4 -> 0.44 | I19: cft/cft | J19: Mix_Design | K19: =INDEX(Material_Master!$F$2:$F$1000,MATCH(C19,Material_Master!$A$2:$A$1000,0)) -> cft | L19: =INDEX(Material_Master!$Q$2:$Q$1000,MATCH(C19,Material_Master!$A$2:$A$1000,0)) -> 0.1
A20: WI-CN-04 | B20: =INDEX(Work_Items!$D$2:$D$300,MATCH(A20,Work_Items!$A$2:$A$300,0)) -> RCC in plinth / grade beams | C20: CON-006 | D20: =INDEX(Material_Master!$D$2:$D$1000,MATCH(C20,Material_Master!$A$2:$A$1000,0)) -> Crushed stone 3/4in down (Margalla crush) | E20: K_ONE | F20: MX_RCC124 | G20: agg | H20: =Coefficients!$D$2*Mix_Design!$L$4 -> 0.88 | I20: cft/cft | J20: Mix_Design | K20: =INDEX(Material_Master!$F$2:$F$1000,MATCH(C20,Material_Master!$A$2:$A$1000,0)) -> cft | L20: =INDEX(Material_Master!$Q$2:$Q$1000,MATCH(C20,Material_Master!$A$2:$A$1000,0)) -> 0.075
A21: WI-CN-04 | B21: =INDEX(Work_Items!$D$2:$D$300,MATCH(A21,Work_Items!$A$2:$A$300,0)) -> RCC in plinth / grade beams | C21: CON-013 | D21: =INDEX(Material_Master!$D$2:$D$1000,MATCH(C21,Material_Master!$A$2:$A$1000,0)) -> Cover blocks / rebar spacers | E21: K_COVERBLK_CFT | H21: =Coefficients!$D$99 -> 1 | I21: Nos/cft | J21: Allowance | K21: =INDEX(Material_Master!$F$2:$F$1000,MATCH(C21,Material_Master!$A$2:$A$1000,0)) -> Nos | L21: =INDEX(Material_Master!$Q$2:$Q$1000,MATCH(C21,Material_Master!$A$2:$A$1000,0)) -> 0.05
A22: WI-CN-05 | B22: =INDEX(Work_Items!$D$2:$D$300,MATCH(A22,Work_Items!$A$2:$A$300,0)) -> RCC in columns | C22: CON-001 | D22: =INDEX(Material_Master!$D$2:$D$1000,MATCH(C22,Material_Master!$A$2:$A$1000,0)) -> Ordinary Portland Cement (OPC) - 50 kg bag | E22: K_ONE | F22: MX_RCC124 | G22: cement | H22: =Coefficients!$D$2*Mix_Design!$J$4 -> 0.17941537 | I22: bag/cft | J22: Mix_Design | K22: =INDEX(Material_Master!$F$2:$F$1000,MATCH(C22,Material_Master!$A$2:$A$1000,0)) -> bag | L22: =INDEX(Material_Master!$Q$2:$Q$1000,MATCH(C22,Material_Master!$A$2:$A$1000,0)) -> 0.02
A23: WI-CN-05 | B23: =INDEX(Work_Items!$D$2:$D$300,MATCH(A23,Work_Items!$A$2:$A$300,0)) -> RCC in columns | C23: CON-004 | D23: =INDEX(Material_Master!$D$2:$D$1000,MATCH(C23,Material_Master!$A$2:$A$1000,0)) -> Coarse sand for concrete (Lawrencepur) | E23: K_ONE | F23: MX_RCC124 | G23: sand | H23: =Coefficients!$D$2*Mix_Design!$K$4 -> 0.44 | I23: cft/cft | J23: Mix_Design | K23: =INDEX(Material_Master!$F$2:$F$1000,MATCH(C23,Material_Master!$A$2:$A$1000,0)) -> cft | L23: =INDEX(Material_Master!$Q$2:$Q$1000,MATCH(C23,Material_Master!$A$2:$A$1000,0)) -> 0.1
A24: WI-CN-05 | B24: =INDEX(Work_Items!$D$2:$D$300,MATCH(A24,Work_Items!$A$2:$A$300,0)) -> RCC in columns | C24: CON-006 | D24: =INDEX(Material_Master!$D$2:$D$1000,MATCH(C24,Material_Master!$A$2:$A$1000,0)) -> Crushed stone 3/4in down (Margalla crush) | E24: K_ONE | F24: MX_RCC124 | G24: agg | H24: =Coefficients!$D$2*Mix_Design!$L$4 -> 0.88 | I24: cft/cft | J24: Mix_Design | K24: =INDEX(Material_Master!$F$2:$F$1000,MATCH(C24,Material_Master!$A$2:$A$1000,0)) -> cft | L24: =INDEX(Material_Master!$Q$2:$Q$1000,MATCH(C24,Material_Master!$A$2:$A$1000,0)) -> 0.075
A25: WI-CN-05 | B25: =INDEX(Work_Items!$D$2:$D$300,MATCH(A25,Work_Items!$A$2:$A$300,0)) -> RCC in columns | C25: CON-013 | D25: =INDEX(Material_Master!$D$2:$D$1000,MATCH(C25,Material_Master!$A$2:$A$1000,0)) -> Cover blocks / rebar spacers | E25: K_COVERBLK_CFT | H25: =Coefficients!$D$99 -> 1 | I25: Nos/cft | J25: Allowance | K25: =INDEX(Material_Master!$F$2:$F$1000,MATCH(C25,Material_Master!$A$2:$A$1000,0)) -> Nos | L25: =INDEX(Material_Master!$Q$2:$Q$1000,MATCH(C25,Material_Master!$A$2:$A$1000,0)) -> 0.05
A26: WI-CN-06 | B26: =INDEX(Work_Items!$D$2:$D$300,MATCH(A26,Work_Items!$A$2:$A$300,0)) -> RCC in beams (below slab soffit) | C26: CON-001 | D26: =INDEX(Material_Master!$D$2:$D$1000,MATCH(C26,Material_Master!$A$2:$A$1000,0)) -> Ordinary Portland Cement (OPC) - 50 kg bag | E26: K_ONE | F26: MX_RCC124 | G26: cement | H26: =Coefficients!$D$2*Mix_Design!$J$4 -> 0.17941537 | I26: bag/cft | J26: Mix_Design | K26: =INDEX(Material_Master!$F$2:$F$1000,MATCH(C26,Material_Master!$A$2:$A$1000,0)) -> bag | L26: =INDEX(Material_Master!$Q$2:$Q$1000,MATCH(C26,Material_Master!$A$2:$A$1000,0)) -> 0.02
A27: WI-CN-06 | B27: =INDEX(Work_Items!$D$2:$D$300,MATCH(A27,Work_Items!$A$2:$A$300,0)) -> RCC in beams (below slab soffit) | C27: CON-004 | D27: =INDEX(Material_Master!$D$2:$D$1000,MATCH(C27,Material_Master!$A$2:$A$1000,0)) -> Coarse sand for concrete (Lawrencepur) | E27: K_ONE | F27: MX_RCC124 | G27: sand | H27: =Coefficients!$D$2*Mix_Design!$K$4 -> 0.44 | I27: cft/cft | J27: Mix_Design | K27: =INDEX(Material_Master!$F$2:$F$1000,MATCH(C27,Material_Master!$A$2:$A$1000,0)) -> cft | L27: =INDEX(Material_Master!$Q$2:$Q$1000,MATCH(C27,Material_Master!$A$2:$A$1000,0)) -> 0.1
A28: WI-CN-06 | B28: =INDEX(Work_Items!$D$2:$D$300,MATCH(A28,Work_Items!$A$2:$A$300,0)) -> RCC in beams (below slab soffit) | C28: CON-006 | D28: =INDEX(Material_Master!$D$2:$D$1000,MATCH(C28,Material_Master!$A$2:$A$1000,0)) -> Crushed stone 3/4in down (Margalla crush) | E28: K_ONE | F28: MX_RCC124 | G28: agg | H28: =Coefficients!$D$2*Mix_Design!$L$4 -> 0.88 | I28: cft/cft | J28: Mix_Design | K28: =INDEX(Material_Master!$F$2:$F$1000,MATCH(C28,Material_Master!$A$2:$A$1000,0)) -> cft | L28: =INDEX(Material_Master!$Q$2:$Q$1000,MATCH(C28,Material_Master!$A$2:$A$1000,0)) -> 0.075
A29: WI-CN-06 | B29: =INDEX(Work_Items!$D$2:$D$300,MATCH(A29,Work_Items!$A$2:$A$300,0)) -> RCC in beams (below slab soffit) | C29: CON-013 | D29: =INDEX(Material_Master!$D$2:$D$1000,MATCH(C29,Material_Master!$A$2:$A$1000,0)) -> Cover blocks / rebar spacers | E29: K_COVERBLK_CFT | H29: =Coefficients!$D$99 -> 1 | I29: Nos/cft | J29: Allowance | K29: =INDEX(Material_Master!$F$2:$F$1000,MATCH(C29,Material_Master!$A$2:$A$1000,0)) -> Nos | L29: =INDEX(Material_Master!$Q$2:$Q$1000,MATCH(C29,Material_Master!$A$2:$A$1000,0)) -> 0.05
A30: WI-CN-07 | B30: =INDEX(Work_Items!$D$2:$D$300,MATCH(A30,Work_Items!$A$2:$A$300,0)) -> RCC in floor & roof slabs | C30: CON-001 | D30: =INDEX(Material_Master!$D$2:$D$1000,MATCH(C30,Material_Master!$A$2:$A$1000,0)) -> Ordinary Portland Cement (OPC) - 50 kg bag | E30: K_ONE | F30: MX_RCC124 | G30: cement | H30: =Coefficients!$D$2*Mix_Design!$J$4 -> 0.17941537 | I30: bag/cft | J30: Mix_Design | K30: =INDEX(Material_Master!$F$2:$F$1000,MATCH(C30,Material_Master!$A$2:$A$1000,0)) -> bag | L30: =INDEX(Material_Master!$Q$2:$Q$1000,MATCH(C30,Material_Master!$A$2:$A$1000,0)) -> 0.02
A31: WI-CN-07 | B31: =INDEX(Work_Items!$D$2:$D$300,MATCH(A31,Work_Items!$A$2:$A$300,0)) -> RCC in floor & roof slabs | C31: CON-004 | D31: =INDEX(Material_Master!$D$2:$D$1000,MATCH(C31,Material_Master!$A$2:$A$1000,0)) -> Coarse sand for concrete (Lawrencepur) | E31: K_ONE | F31: MX_RCC124 | G31: sand | H31: =Coefficients!$D$2*Mix_Design!$K$4 -> 0.44 | I31: cft/cft | J31: Mix_Design | K31: =INDEX(Material_Master!$F$2:$F$1000,MATCH(C31,Material_Master!$A$2:$A$1000,0)) -> cft | L31: =INDEX(Material_Master!$Q$2:$Q$1000,MATCH(C31,Material_Master!$A$2:$A$1000,0)) -> 0.1
A32: WI-CN-07 | B32: =INDEX(Work_Items!$D$2:$D$300,MATCH(A32,Work_Items!$A$2:$A$300,0)) -> RCC in floor & roof slabs | C32: CON-006 | D32: =INDEX(Material_Master!$D$2:$D$1000,MATCH(C32,Material_Master!$A$2:$A$1000,0)) -> Crushed stone 3/4in down (Margalla crush) | E32: K_ONE | F32: MX_RCC124 | G32: agg | H32: =Coefficients!$D$2*Mix_Design!$L$4 -> 0.88 | I32: cft/cft | J32: Mix_Design | K32: =INDEX(Material_Master!$F$2:$F$1000,MATCH(C32,Material_Master!$A$2:$A$1000,0)) -> cft | L32: =INDEX(Material_Master!$Q$2:$Q$1000,MATCH(C32,Material_Master!$A$2:$A$1000,0)) -> 0.075
A33: WI-CN-07 | B33: =INDEX(Work_Items!$D$2:$D$300,MATCH(A33,Work_Items!$A$2:$A$300,0)) -> RCC in floor & roof slabs | C33: CON-013 | D33: =INDEX(Material_Master!$D$2:$D$1000,MATCH(C33,Material_Master!$A$2:$A$1000,0)) -> Cover blocks / rebar spacers | E33: K_COVERBLK_CFT | H33: =Coefficients!$D$99 -> 1 | I33: Nos/cft | J33: Allowance | K33: =INDEX(Material_Master!$F$2:$F$1000,MATCH(C33,Material_Master!$A$2:$A$1000,0)) -> Nos | L33: =INDEX(Material_Master!$Q$2:$Q$1000,MATCH(C33,Material_Master!$A$2:$A$1000,0)) -> 0.05
A34: WI-CN-08 | B34: =INDEX(Work_Items!$D$2:$D$300,MATCH(A34,Work_Items!$A$2:$A$300,0)) -> RCC in staircase (waist, steps, landings) | C34: CON-001 | D34: =INDEX(Material_Master!$D$2:$D$1000,MATCH(C34,Material_Master!$A$2:$A$1000,0)) -> Ordinary Portland Cement (OPC) - 50 kg bag | E34: K_ONE | F34: MX_RCC124 | G34: cement | H34: =Coefficients!$D$2*Mix_Design!$J$4 -> 0.17941537 | I34: bag/cft | J34: Mix_Design | K34: =INDEX(Material_Master!$F$2:$F$1000,MATCH(C34,Material_Master!$A$2:$A$1000,0)) -> bag | L34: =INDEX(Material_Master!$Q$2:$Q$1000,MATCH(C34,Material_Master!$A$2:$A$1000,0)) -> 0.02
A35: WI-CN-08 | B35: =INDEX(Work_Items!$D$2:$D$300,MATCH(A35,Work_Items!$A$2:$A$300,0)) -> RCC in staircase (waist, steps, landings) | C35: CON-004 | D35: =INDEX(Material_Master!$D$2:$D$1000,MATCH(C35,Material_Master!$A$2:$A$1000,0)) -> Coarse sand for concrete (Lawrencepur) | E35: K_ONE | F35: MX_RCC124 | G35: sand | H35: =Coefficients!$D$2*Mix_Design!$K$4 -> 0.44 | I35: cft/cft | J35: Mix_Design | K35: =INDEX(Material_Master!$F$2:$F$1000,MATCH(C35,Material_Master!$A$2:$A$1000,0)) -> cft | L35: =INDEX(Material_Master!$Q$2:$Q$1000,MATCH(C35,Material_Master!$A$2:$A$1000,0)) -> 0.1
A36: WI-CN-08 | B36: =INDEX(Work_Items!$D$2:$D$300,MATCH(A36,Work_Items!$A$2:$A$300,0)) -> RCC in staircase (waist, steps, landings) | C36: CON-006 | D36: =INDEX(Material_Master!$D$2:$D$1000,MATCH(C36,Material_Master!$A$2:$A$1000,0)) -> Crushed stone 3/4in down (Margalla crush) | E36: K_ONE | F36: MX_RCC124 | G36: agg | H36: =Coefficients!$D$2*Mix_Design!$L$4 -> 0.88 | I36: cft/cft | J36: Mix_Design | K36: =INDEX(Material_Master!$F$2:$F$1000,MATCH(C36,Material_Master!$A$2:$A$1000,0)) -> cft | L36: =INDEX(Material_Master!$Q$2:$Q$1000,MATCH(C36,Material_Master!$A$2:$A$1000,0)) -> 0.075
A37: WI-CN-08 | B37: =INDEX(Work_Items!$D$2:$D$300,MATCH(A37,Work_Items!$A$2:$A$300,0)) -> RCC in staircase (waist, steps, landings) | C37: CON-013 | D37: =INDEX(Material_Master!$D$2:$D$1000,MATCH(C37,Material_Master!$A$2:$A$1000,0)) -> Cover blocks / rebar spacers | E37: K_COVERBLK_CFT | H37: =Coefficients!$D$99 -> 1 | I37: Nos/cft | J37: Allowance | K37: =INDEX(Material_Master!$F$2:$F$1000,MATCH(C37,Material_Master!$A$2:$A$1000,0)) -> Nos | L37: =INDEX(Material_Master!$Q$2:$Q$1000,MATCH(C37,Material_Master!$A$2:$A$1000,0)) -> 0.05
A38: WI-CN-09 | B38: =INDEX(Work_Items!$D$2:$D$300,MATCH(A38,Work_Items!$A$2:$A$300,0)) -> RCC lintels & seismic bands (lintel/roof/sill) | C38: CON-001 | D38: =INDEX(Material_Master!$D$2:$D$1000,MATCH(C38,Material_Master!$A$2:$A$1000,0)) -> Ordinary Portland Cement (OPC) - 50 kg bag | E38: K_ONE | F38: MX_RCC124 | G38: cement | H38: =Coefficients!$D$2*Mix_Design!$J$4 -> 0.17941537 | I38: bag/cft | J38: Mix_Design | K38: =INDEX(Material_Master!$F$2:$F$1000,MATCH(C38,Material_Master!$A$2:$A$1000,0)) -> bag | L38: =INDEX(Material_Master!$Q$2:$Q$1000,MATCH(C38,Material_Master!$A$2:$A$1000,0)) -> 0.02
A39: WI-CN-09 | B39: =INDEX(Work_Items!$D$2:$D$300,MATCH(A39,Work_Items!$A$2:$A$300,0)) -> RCC lintels & seismic bands (lintel/roof/sill) | C39: CON-004 | D39: =INDEX(Material_Master!$D$2:$D$1000,MATCH(C39,Material_Master!$A$2:$A$1000,0)) -> Coarse sand for concrete (Lawrencepur) | E39: K_ONE | F39: MX_RCC124 | G39: sand | H39: =Coefficients!$D$2*Mix_Design!$K$4 -> 0.44 | I39: cft/cft | J39: Mix_Design | K39: =INDEX(Material_Master!$F$2:$F$1000,MATCH(C39,Material_Master!$A$2:$A$1000,0)) -> cft | L39: =INDEX(Material_Master!$Q$2:$Q$1000,MATCH(C39,Material_Master!$A$2:$A$1000,0)) -> 0.1
A40: WI-CN-09 | B40: =INDEX(Work_Items!$D$2:$D$300,MATCH(A40,Work_Items!$A$2:$A$300,0)) -> RCC lintels & seismic bands (lintel/roof/sill) | C40: CON-007 | D40: =INDEX(Material_Master!$D$2:$D$1000,MATCH(C40,Material_Master!$A$2:$A$1000,0)) -> Crushed stone 1/2in / 3/8in down | E40: K_ONE | F40: MX_RCC124 | G40: agg | H40: =Coefficients!$D$2*Mix_Design!$L$4 -> 0.88 | I40: cft/cft | J40: Mix_Design | K40: =INDEX(Material_Master!$F$2:$F$1000,MATCH(C40,Material_Master!$A$2:$A$1000,0)) -> cft | L40: =INDEX(Material_Master!$Q$2:$Q$1000,MATCH(C40,Material_Master!$A$2:$A$1000,0)) -> 0.075
A41: WI-CN-09 | B41: =INDEX(Work_Items!$D$2:$D$300,MATCH(A41,Work_Items!$A$2:$A$300,0)) -> RCC lintels & seismic bands (lintel/roof/sill) | C41: CON-013 | D41: =INDEX(Material_Master!$D$2:$D$1000,MATCH(C41,Material_Master!$A$2:$A$1000,0)) -> Cover blocks / rebar spacers | E41: K_COVERBLK_CFT | H41: =Coefficients!$D$99 -> 1 | I41: Nos/cft | J41: Allowance | K41: =INDEX(Material_Master!$F$2:$F$1000,MATCH(C41,Material_Master!$A$2:$A$1000,0)) -> Nos | L41: =INDEX(Material_Master!$Q$2:$Q$1000,MATCH(C41,Material_Master!$A$2:$A$1000,0)) -> 0.05
A42: WI-CN-10 | B42: =INDEX(Work_Items!$D$2:$D$300,MATCH(A42,Work_Items!$A$2:$A$300,0)) -> RCC chajjas, projections, balcony slabs, canopies | C42: CON-001 | D42: =INDEX(Material_Master!$D$2:$D$1000,MATCH(C42,Material_Master!$A$2:$A$1000,0)) -> Ordinary Portland Cement (OPC) - 50 kg bag | E42: K_ONE | F42: MX_RCC124 | G42: cement | H42: =Coefficients!$D$2*Mix_Design!$J$4 -> 0.17941537 | I42: bag/cft | J42: Mix_Design | K42: =INDEX(Material_Master!$F$2:$F$1000,MATCH(C42,Material_Master!$A$2:$A$1000,0)) -> bag | L42: =INDEX(Material_Master!$Q$2:$Q$1000,MATCH(C42,Material_Master!$A$2:$A$1000,0)) -> 0.02
A43: WI-CN-10 | B43: =INDEX(Work_Items!$D$2:$D$300,MATCH(A43,Work_Items!$A$2:$A$300,0)) -> RCC chajjas, projections, balcony slabs, canopies | C43: CON-004 | D43: =INDEX(Material_Master!$D$2:$D$1000,MATCH(C43,Material_Master!$A$2:$A$1000,0)) -> Coarse sand for concrete (Lawrencepur) | E43: K_ONE | F43: MX_RCC124 | G43: sand | H43: =Coefficients!$D$2*Mix_Design!$K$4 -> 0.44 | I43: cft/cft | J43: Mix_Design | K43: =INDEX(Material_Master!$F$2:$F$1000,MATCH(C43,Material_Master!$A$2:$A$1000,0)) -> cft | L43: =INDEX(Material_Master!$Q$2:$Q$1000,MATCH(C43,Material_Master!$A$2:$A$1000,0)) -> 0.1
A44: WI-CN-10 | B44: =INDEX(Work_Items!$D$2:$D$300,MATCH(A44,Work_Items!$A$2:$A$300,0)) -> RCC chajjas, projections, balcony slabs, canopies | C44: CON-007 | D44: =INDEX(Material_Master!$D$2:$D$1000,MATCH(C44,Material_Master!$A$2:$A$1000,0)) -> Crushed stone 1/2in / 3/8in down | E44: K_ONE | F44: MX_RCC124 | G44: agg | H44: =Coefficients!$D$2*Mix_Design!$L$4 -> 0.88 | I44: cft/cft | J44: Mix_Design | K44: =INDEX(Material_Master!$F$2:$F$1000,MATCH(C44,Material_Master!$A$2:$A$1000,0)) -> cft | L44: =INDEX(Material_Master!$Q$2:$Q$1000,MATCH(C44,Material_Master!$A$2:$A$1000,0)) -> 0.075
A45: WI-CN-11 | B45: =INDEX(Work_Items!$D$2:$D$300,MATCH(A45,Work_Items!$A$2:$A$300,0)) -> RCC in UG water tank / septic tank (base, walls, cover) | C45: CON-001 | D45: =INDEX(Material_Master!$D$2:$D$1000,MATCH(C45,Material_Master!$A$2:$A$1000,0)) -> Ordinary Portland Cement (OPC) - 50 kg bag | E45: K_ONE | F45: MX_RCC124 | G45: cement | H45: =Coefficients!$D$2*Mix_Design!$J$4 -> 0.17941537 | I45: bag/cft | J45: Mix_Design | K45: =INDEX(Material_Master!$F$2:$F$1000,MATCH(C45,Material_Master!$A$2:$A$1000,0)) -> bag | L45: =INDEX(Material_Master!$Q$2:$Q$1000,MATCH(C45,Material_Master!$A$2:$A$1000,0)) -> 0.02
A46: WI-CN-11 | B46: =INDEX(Work_Items!$D$2:$D$300,MATCH(A46,Work_Items!$A$2:$A$300,0)) -> RCC in UG water tank / septic tank (base, walls, cover) | C46: CON-004 | D46: =INDEX(Material_Master!$D$2:$D$1000,MATCH(C46,Material_Master!$A$2:$A$1000,0)) -> Coarse sand for concrete (Lawrencepur) | E46: K_ONE | F46: MX_RCC124 | G46: sand | H46: =Coefficients!$D$2*Mix_Design!$K$4 -> 0.44 | I46: cft/cft | J46: Mix_Design | K46: =INDEX(Material_Master!$F$2:$F$1000,MATCH(C46,Material_Master!$A$2:$A$1000,0)) -> cft | L46: =INDEX(Material_Master!$Q$2:$Q$1000,MATCH(C46,Material_Master!$A$2:$A$1000,0)) -> 0.1
A47: WI-CN-11 | B47: =INDEX(Work_Items!$D$2:$D$300,MATCH(A47,Work_Items!$A$2:$A$300,0)) -> RCC in UG water tank / septic tank (base, walls, cover) | C47: CON-006 | D47: =INDEX(Material_Master!$D$2:$D$1000,MATCH(C47,Material_Master!$A$2:$A$1000,0)) -> Crushed stone 3/4in down (Margalla crush) | E47: K_ONE | F47: MX_RCC124 | G47: agg | H47: =Coefficients!$D$2*Mix_Design!$L$4 -> 0.88 | I47: cft/cft | J47: Mix_Design | K47: =INDEX(Material_Master!$F$2:$F$1000,MATCH(C47,Material_Master!$A$2:$A$1000,0)) -> cft | L47: =INDEX(Material_Master!$Q$2:$Q$1000,MATCH(C47,Material_Master!$A$2:$A$1000,0)) -> 0.075
A48: WI-CN-11 | B48: =INDEX(Work_Items!$D$2:$D$300,MATCH(A48,Work_Items!$A$2:$A$300,0)) -> RCC in UG water tank / septic tank (base, walls, cover) | C48: WPF-007 | D48: =INDEX(Material_Master!$D$2:$D$1000,MATCH(C48,Material_Master!$A$2:$A$1000,0)) -> Integral waterproofing compound (powder/liquid) | E48: K_TANK_WPADMIX | H48: =Coefficients!$D$233 -> 0.17941537 | I48: kg/cft | J48: Integral WP | K48: =INDEX(Material_Master!$F$2:$F$1000,MATCH(C48,Material_Master!$A$2:$A$1000,0)) -> kg | L48: =INDEX(Material_Master!$Q$2:$Q$1000,MATCH(C48,Material_Master!$A$2:$A$1000,0)) -> 0.05
A49: WI-CN-12 | B49: =INDEX(Work_Items!$D$2:$D$300,MATCH(A49,Work_Items!$A$2:$A$300,0)) -> DPC 1.5in PCC 1:2:4 with WP admixture, bitumen & polythene | C49: CON-001 | D49: =INDEX(Material_Master!$D$2:$D$1000,MATCH(C49,Material_Master!$A$2:$A$1000,0)) -> Ordinary Portland Cement (OPC) - 50 kg bag | E49: K_DPC_WET | F49: MX_DPC124 | G49: cement | H49: =Coefficients!$D$43*Mix_Design!$J$6 -> 0.022426921 | I49: bag/sft | K49: =INDEX(Material_Master!$F$2:$F$1000,MATCH(C49,Material_Master!$A$2:$A$1000,0)) -> bag | L49: =INDEX(Material_Master!$Q$2:$Q$1000,MATCH(C49,Material_Master!$A$2:$A$1000,0)) -> 0.02
A50: WI-CN-12 | B50: =INDEX(Work_Items!$D$2:$D$300,MATCH(A50,Work_Items!$A$2:$A$300,0)) -> DPC 1.5in PCC 1:2:4 with WP admixture, bitumen & polythene | C50: CON-004 | D50: =INDEX(Material_Master!$D$2:$D$1000,MATCH(C50,Material_Master!$A$2:$A$1000,0)) -> Coarse sand for concrete (Lawrencepur) | E50: K_DPC_WET | F50: MX_DPC124 | G50: sand | H50: =Coefficients!$D$43*Mix_Design!$K$6 -> 0.055 | I50: cft/sft | K50: =INDEX(Material_Master!$F$2:$F$1000,MATCH(C50,Material_Master!$A$2:$A$1000,0)) -> cft | L50: =INDEX(Material_Master!$Q$2:$Q$1000,MATCH(C50,Material_Master!$A$2:$A$1000,0)) -> 0.1
A51: WI-CN-12 | B51: =INDEX(Work_Items!$D$2:$D$300,MATCH(A51,Work_Items!$A$2:$A$300,0)) -> DPC 1.5in PCC 1:2:4 with WP admixture, bitumen & polythene | C51: CON-007 | D51: =INDEX(Material_Master!$D$2:$D$1000,MATCH(C51,Material_Master!$A$2:$A$1000,0)) -> Crushed stone 1/2in / 3/8in down | E51: K_DPC_WET | F51: MX_DPC124 | G51: agg | H51: =Coefficients!$D$43*Mix_Design!$L$6 -> 0.11 | I51: cft/sft | K51: =INDEX(Material_Master!$F$2:$F$1000,MATCH(C51,Material_Master!$A$2:$A$1000,0)) -> cft | L51: =INDEX(Material_Master!$Q$2:$Q$1000,MATCH(C51,Material_Master!$A$2:$A$1000,0)) -> 0.075
A52: WI-CN-12 | B52: =INDEX(Work_Items!$D$2:$D$300,MATCH(A52,Work_Items!$A$2:$A$300,0)) -> DPC 1.5in PCC 1:2:4 with WP admixture, bitumen & polythene | C52: WPF-001 | D52: =INDEX(Material_Master!$D$2:$D$1000,MATCH(C52,Material_Master!$A$2:$A$1000,0)) -> Bitumen (hot applied) | E52: K_DPC_BIT | H52: =Coefficients!$D$46 -> 0.28 | I52: kg/sft | J52: 2 coats | K52: =INDEX(Material_Master!$F$2:$F$1000,MATCH(C52,Material_Master!$A$2:$A$1000,0)) -> kg | L52: =INDEX(Material_Master!$Q$2:$Q$1000,MATCH(C52,Material_Master!$A$2:$A$1000,0)) -> 0.05
A53: WI-CN-12 | B53: =INDEX(Work_Items!$D$2:$D$300,MATCH(A53,Work_Items!$A$2:$A$300,0)) -> DPC 1.5in PCC 1:2:4 with WP admixture, bitumen & polythene | C53: WPF-003 | D53: =INDEX(Material_Master!$D$2:$D$1000,MATCH(C53,Material_Master!$A$2:$A$1000,0)) -> Polythene sheet (high-density) | E53: K_DPC_POLY | H53: =Coefficients!$D$49 -> 2.3 | I53: sft/sft | J53: double layer | K53: =INDEX(Material_Master!$F$2:$F$1000,MATCH(C53,Material_Master!$A$2:$A$1000,0)) -> sft | L53: =INDEX(Material_Master!$Q$2:$Q$1000,MATCH(C53,Material_Master!$A$2:$A$1000,0)) -> 0.05
A54: WI-CN-12 | B54: =INDEX(Work_Items!$D$2:$D$300,MATCH(A54,Work_Items!$A$2:$A$300,0)) -> DPC 1.5in PCC 1:2:4 with WP admixture, bitumen & polythene | C54: WPF-007 | D54: =INDEX(Material_Master!$D$2:$D$1000,MATCH(C54,Material_Master!$A$2:$A$1000,0)) -> Integral waterproofing compound (powder/liquid) | E54: K_DPC_WPADMIX | H54: =Coefficients!$D$51 -> 0.022426921 | I54: kg/sft | K54: =INDEX(Material_Master!$F$2:$F$1000,MATCH(C54,Material_Master!$A$2:$A$1000,0)) -> kg | L54: =INDEX(Material_Master!$Q$2:$Q$1000,MATCH(C54,Material_Master!$A$2:$A$1000,0)) -> 0.05
A55: WI-CN-13 | B55: =INDEX(Work_Items!$D$2:$D$300,MATCH(A55,Work_Items!$A$2:$A$300,0)) -> Plinth protection / apron PCC 1:2:4 3in | C55: CON-001 | D55: =INDEX(Material_Master!$D$2:$D$1000,MATCH(C55,Material_Master!$A$2:$A$1000,0)) -> Ordinary Portland Cement (OPC) - 50 kg bag | E55: K_APRON_WET | F55: MX_RCC124 | G55: cement | H55: =Coefficients!$D$66*Mix_Design!$J$4 -> 0.044853843 | I55: bag/sft | K55: =INDEX(Material_Master!$F$2:$F$1000,MATCH(C55,Material_Master!$A$2:$A$1000,0)) -> bag | L55: =INDEX(Material_Master!$Q$2:$Q$1000,MATCH(C55,Material_Master!$A$2:$A$1000,0)) -> 0.02
A56: WI-CN-13 | B56: =INDEX(Work_Items!$D$2:$D$300,MATCH(A56,Work_Items!$A$2:$A$300,0)) -> Plinth protection / apron PCC 1:2:4 3in | C56: CON-004 | D56: =INDEX(Material_Master!$D$2:$D$1000,MATCH(C56,Material_Master!$A$2:$A$1000,0)) -> Coarse sand for concrete (Lawrencepur) | E56: K_APRON_WET | F56: MX_RCC124 | G56: sand | H56: =Coefficients!$D$66*Mix_Design!$K$4 -> 0.11 | I56: cft/sft | K56: =INDEX(Material_Master!$F$2:$F$1000,MATCH(C56,Material_Master!$A$2:$A$1000,0)) -> cft | L56: =INDEX(Material_Master!$Q$2:$Q$1000,MATCH(C56,Material_Master!$A$2:$A$1000,0)) -> 0.1
A57: WI-CN-13 | B57: =INDEX(Work_Items!$D$2:$D$300,MATCH(A57,Work_Items!$A$2:$A$300,0)) -> Plinth protection / apron PCC 1:2:4 3in | C57: CON-007 | D57: =INDEX(Material_Master!$D$2:$D$1000,MATCH(C57,Material_Master!$A$2:$A$1000,0)) -> Crushed stone 1/2in / 3/8in down | E57: K_APRON_WET | F57: MX_RCC124 | G57: agg | H57: =Coefficients!$D$66*Mix_Design!$L$4 -> 0.22 | I57: cft/sft | K57: =INDEX(Material_Master!$F$2:$F$1000,MATCH(C57,Material_Master!$A$2:$A$1000,0)) -> cft | L57: =INDEX(Material_Master!$Q$2:$Q$1000,MATCH(C57,Material_Master!$A$2:$A$1000,0)) -> 0.075
A58: WI-RF-01 | B58: =INDEX(Work_Items!$D$2:$D$300,MATCH(A58,Work_Items!$A$2:$A$300,0)) -> Reinforcement in footings | C58: RBR-001 | D58: =INDEX(Material_Master!$D$2:$D$1000,MATCH(C58,Material_Master!$A$2:$A$1000,0)) -> Deformed bar #3 (10 mm / 3/8in) | E58: K_SPL_FTG_3 | H58: =Coefficients!$D$94 -> 0.3 | I58: kg/kg | J58: Bar-diameter split (replace with BBS) | K58: =INDEX(Material_Master!$F$2:$F$1000,MATCH(C58,Material_Master!$A$2:$A$1000,0)) -> kg | L58: =INDEX(Material_Master!$Q$2:$Q$1000,MATCH(C58,Material_Master!$A$2:$A$1000,0)) -> 0.03
A59: WI-RF-01 | B59: =INDEX(Work_Items!$D$2:$D$300,MATCH(A59,Work_Items!$A$2:$A$300,0)) -> Reinforcement in footings | C59: RBR-002 | D59: =INDEX(Material_Master!$D$2:$D$1000,MATCH(C59,Material_Master!$A$2:$A$1000,0)) -> Deformed bar #4 (12 mm / 1/2in) | E59: K_SPL_FTG_4 | H59: =Coefficients!$D$95 -> 0.7 | I59: kg/kg | J59: Bar-diameter split (replace with BBS) | K59: =INDEX(Material_Master!$F$2:$F$1000,MATCH(C59,Material_Master!$A$2:$A$1000,0)) -> kg | L59: =INDEX(Material_Master!$Q$2:$Q$1000,MATCH(C59,Material_Master!$A$2:$A$1000,0)) -> 0.03
A60: WI-RF-01 | B60: =INDEX(Work_Items!$D$2:$D$300,MATCH(A60,Work_Items!$A$2:$A$300,0)) -> Reinforcement in footings | C60: RBR-006 | D60: =INDEX(Material_Master!$D$2:$D$1000,MATCH(C60,Material_Master!$A$2:$A$1000,0)) -> Binding wire (black annealed) | E60: K_BIND_PER_KG | H60: =Coefficients!$D$98 -> 0.01 | I60: kg/kg | K60: =INDEX(Material_Master!$F$2:$F$1000,MATCH(C60,Material_Master!$A$2:$A$1000,0)) -> kg | L60: =INDEX(Material_Master!$Q$2:$Q$1000,MATCH(C60,Material_Master!$A$2:$A$1000,0)) -> 0
A61: WI-RF-02 | B61: =INDEX(Work_Items!$D$2:$D$300,MATCH(A61,Work_Items!$A$2:$A$300,0)) -> Reinforcement in columns | C61: RBR-001 | D61: =INDEX(Material_Master!$D$2:$D$1000,MATCH(C61,Material_Master!$A$2:$A$1000,0)) -> Deformed bar #3 (10 mm / 3/8in) | E61: K_SPL_COL_3 | H61: =Coefficients!$D$91 -> 0.25 | I61: kg/kg | J61: Bar-diameter split (replace with BBS) | K61: =INDEX(Material_Master!$F$2:$F$1000,MATCH(C61,Material_Master!$A$2:$A$1000,0)) -> kg | L61: =INDEX(Material_Master!$Q$2:$Q$1000,MATCH(C61,Material_Master!$A$2:$A$1000,0)) -> 0.03
A62: WI-RF-02 | B62: =INDEX(Work_Items!$D$2:$D$300,MATCH(A62,Work_Items!$A$2:$A$300,0)) -> Reinforcement in columns | C62: RBR-002 | D62: =INDEX(Material_Master!$D$2:$D$1000,MATCH(C62,Material_Master!$A$2:$A$1000,0)) -> Deformed bar #4 (12 mm / 1/2in) | E62: K_SPL_COL_4 | H62: =Coefficients!$D$92 -> 0.35 | I62: kg/kg | J62: Bar-diameter split (replace with BBS) | K62: =INDEX(Material_Master!$F$2:$F$1000,MATCH(C62,Material_Master!$A$2:$A$1000,0)) -> kg | L62: =INDEX(Material_Master!$Q$2:$Q$1000,MATCH(C62,Material_Master!$A$2:$A$1000,0)) -> 0.03
A63: WI-RF-02 | B63: =INDEX(Work_Items!$D$2:$D$300,MATCH(A63,Work_Items!$A$2:$A$300,0)) -> Reinforcement in columns | C63: RBR-003 | D63: =INDEX(Material_Master!$D$2:$D$1000,MATCH(C63,Material_Master!$A$2:$A$1000,0)) -> Deformed bar #5 (16 mm / 5/8in) | E63: K_SPL_COL_5 | H63: =Coefficients!$D$93 -> 0.4 | I63: kg/kg | J63: Bar-diameter split (replace with BBS) | K63: =INDEX(Material_Master!$F$2:$F$1000,MATCH(C63,Material_Master!$A$2:$A$1000,0)) -> kg | L63: =INDEX(Material_Master!$Q$2:$Q$1000,MATCH(C63,Material_Master!$A$2:$A$1000,0)) -> 0.03
A64: WI-RF-02 | B64: =INDEX(Work_Items!$D$2:$D$300,MATCH(A64,Work_Items!$A$2:$A$300,0)) -> Reinforcement in columns | C64: RBR-006 | D64: =INDEX(Material_Master!$D$2:$D$1000,MATCH(C64,Material_Master!$A$2:$A$1000,0)) -> Binding wire (black annealed) | E64: K_BIND_PER_KG | H64: =Coefficients!$D$98 -> 0.01 | I64: kg/kg | K64: =INDEX(Material_Master!$F$2:$F$1000,MATCH(C64,Material_Master!$A$2:$A$1000,0)) -> kg | L64: =INDEX(Material_Master!$Q$2:$Q$1000,MATCH(C64,Material_Master!$A$2:$A$1000,0)) -> 0
A65: WI-RF-03 | B65: =INDEX(Work_Items!$D$2:$D$300,MATCH(A65,Work_Items!$A$2:$A$300,0)) -> Reinforcement in beams & plinth beams | C65: RBR-001 | D65: =INDEX(Material_Master!$D$2:$D$1000,MATCH(C65,Material_Master!$A$2:$A$1000,0)) -> Deformed bar #3 (10 mm / 3/8in) | E65: K_SPL_BEAM_3 | H65: =Coefficients!$D$88 -> 0.25 | I65: kg/kg | J65: Bar-diameter split (replace with BBS) | K65: =INDEX(Material_Master!$F$2:$F$1000,MATCH(C65,Material_Master!$A$2:$A$1000,0)) -> kg | L65: =INDEX(Material_Master!$Q$2:$Q$1000,MATCH(C65,Material_Master!$A$2:$A$1000,0)) -> 0.03
A66: WI-RF-03 | B66: =INDEX(Work_Items!$D$2:$D$300,MATCH(A66,Work_Items!$A$2:$A$300,0)) -> Reinforcement in beams & plinth beams | C66: RBR-002 | D66: =INDEX(Material_Master!$D$2:$D$1000,MATCH(C66,Material_Master!$A$2:$A$1000,0)) -> Deformed bar #4 (12 mm / 1/2in) | E66: K_SPL_BEAM_4 | H66: =Coefficients!$D$89 -> 0.35 | I66: kg/kg | J66: Bar-diameter split (replace with BBS) | K66: =INDEX(Material_Master!$F$2:$F$1000,MATCH(C66,Material_Master!$A$2:$A$1000,0)) -> kg | L66: =INDEX(Material_Master!$Q$2:$Q$1000,MATCH(C66,Material_Master!$A$2:$A$1000,0)) -> 0.03
A67: WI-RF-03 | B67: =INDEX(Work_Items!$D$2:$D$300,MATCH(A67,Work_Items!$A$2:$A$300,0)) -> Reinforcement in beams & plinth beams | C67: RBR-003 | D67: =INDEX(Material_Master!$D$2:$D$1000,MATCH(C67,Material_Master!$A$2:$A$1000,0)) -> Deformed bar #5 (16 mm / 5/8in) | E67: K_SPL_BEAM_5 | H67: =Coefficients!$D$90 -> 0.4 | I67: kg/kg | J67: Bar-diameter split (replace with BBS) | K67: =INDEX(Material_Master!$F$2:$F$1000,MATCH(C67,Material_Master!$A$2:$A$1000,0)) -> kg | L67: =INDEX(Material_Master!$Q$2:$Q$1000,MATCH(C67,Material_Master!$A$2:$A$1000,0)) -> 0.03
A68: WI-RF-03 | B68: =INDEX(Work_Items!$D$2:$D$300,MATCH(A68,Work_Items!$A$2:$A$300,0)) -> Reinforcement in beams & plinth beams | C68: RBR-006 | D68: =INDEX(Material_Master!$D$2:$D$1000,MATCH(C68,Material_Master!$A$2:$A$1000,0)) -> Binding wire (black annealed) | E68: K_BIND_PER_KG | H68: =Coefficients!$D$98 -> 0.01 | I68: kg/kg | K68: =INDEX(Material_Master!$F$2:$F$1000,MATCH(C68,Material_Master!$A$2:$A$1000,0)) -> kg | L68: =INDEX(Material_Master!$Q$2:$Q$1000,MATCH(C68,Material_Master!$A$2:$A$1000,0)) -> 0
A69: WI-RF-04 | B69: =INDEX(Work_Items!$D$2:$D$300,MATCH(A69,Work_Items!$A$2:$A$300,0)) -> Reinforcement in slabs | C69: RBR-001 | D69: =INDEX(Material_Master!$D$2:$D$1000,MATCH(C69,Material_Master!$A$2:$A$1000,0)) -> Deformed bar #3 (10 mm / 3/8in) | E69: K_SPL_SLAB_3 | H69: =Coefficients!$D$86 -> 0.35 | I69: kg/kg | J69: Bar-diameter split (replace with BBS) | K69: =INDEX(Material_Master!$F$2:$F$1000,MATCH(C69,Material_Master!$A$2:$A$1000,0)) -> kg | L69: =INDEX(Material_Master!$Q$2:$Q$1000,MATCH(C69,Material_Master!$A$2:$A$1000,0)) -> 0.03
A70: WI-RF-04 | B70: =INDEX(Work_Items!$D$2:$D$300,MATCH(A70,Work_Items!$A$2:$A$300,0)) -> Reinforcement in slabs | C70: RBR-002 | D70: =INDEX(Material_Master!$D$2:$D$1000,MATCH(C70,Material_Master!$A$2:$A$1000,0)) -> Deformed bar #4 (12 mm / 1/2in) | E70: K_SPL_SLAB_4 | H70: =Coefficients!$D$87 -> 0.65 | I70: kg/kg | J70: Bar-diameter split (replace with BBS) | K70: =INDEX(Material_Master!$F$2:$F$1000,MATCH(C70,Material_Master!$A$2:$A$1000,0)) -> kg | L70: =INDEX(Material_Master!$Q$2:$Q$1000,MATCH(C70,Material_Master!$A$2:$A$1000,0)) -> 0.03
A71: WI-RF-04 | B71: =INDEX(Work_Items!$D$2:$D$300,MATCH(A71,Work_Items!$A$2:$A$300,0)) -> Reinforcement in slabs | C71: RBR-006 | D71: =INDEX(Material_Master!$D$2:$D$1000,MATCH(C71,Material_Master!$A$2:$A$1000,0)) -> Binding wire (black annealed) | E71: K_BIND_PER_KG | H71: =Coefficients!$D$98 -> 0.01 | I71: kg/kg | K71: =INDEX(Material_Master!$F$2:$F$1000,MATCH(C71,Material_Master!$A$2:$A$1000,0)) -> kg | L71: =INDEX(Material_Master!$Q$2:$Q$1000,MATCH(C71,Material_Master!$A$2:$A$1000,0)) -> 0
A72: WI-RF-05 | B72: =INDEX(Work_Items!$D$2:$D$300,MATCH(A72,Work_Items!$A$2:$A$300,0)) -> Reinforcement in stairs | C72: RBR-001 | D72: =INDEX(Material_Master!$D$2:$D$1000,MATCH(C72,Material_Master!$A$2:$A$1000,0)) -> Deformed bar #3 (10 mm / 3/8in) | E72: K_SPL_SLAB_3 | H72: =Coefficients!$D$86 -> 0.35 | I72: kg/kg | J72: Bar-diameter split (replace with BBS) | K72: =INDEX(Material_Master!$F$2:$F$1000,MATCH(C72,Material_Master!$A$2:$A$1000,0)) -> kg | L72: =INDEX(Material_Master!$Q$2:$Q$1000,MATCH(C72,Material_Master!$A$2:$A$1000,0)) -> 0.03
A73: WI-RF-05 | B73: =INDEX(Work_Items!$D$2:$D$300,MATCH(A73,Work_Items!$A$2:$A$300,0)) -> Reinforcement in stairs | C73: RBR-002 | D73: =INDEX(Material_Master!$D$2:$D$1000,MATCH(C73,Material_Master!$A$2:$A$1000,0)) -> Deformed bar #4 (12 mm / 1/2in) | E73: K_SPL_SLAB_4 | H73: =Coefficients!$D$87 -> 0.65 | I73: kg/kg | J73: Bar-diameter split (replace with BBS) | K73: =INDEX(Material_Master!$F$2:$F$1000,MATCH(C73,Material_Master!$A$2:$A$1000,0)) -> kg | L73: =INDEX(Material_Master!$Q$2:$Q$1000,MATCH(C73,Material_Master!$A$2:$A$1000,0)) -> 0.03
A74: WI-RF-05 | B74: =INDEX(Work_Items!$D$2:$D$300,MATCH(A74,Work_Items!$A$2:$A$300,0)) -> Reinforcement in stairs | C74: RBR-006 | D74: =INDEX(Material_Master!$D$2:$D$1000,MATCH(C74,Material_Master!$A$2:$A$1000,0)) -> Binding wire (black annealed) | E74: K_BIND_PER_KG | H74: =Coefficients!$D$98 -> 0.01 | I74: kg/kg | K74: =INDEX(Material_Master!$F$2:$F$1000,MATCH(C74,Material_Master!$A$2:$A$1000,0)) -> kg | L74: =INDEX(Material_Master!$Q$2:$Q$1000,MATCH(C74,Material_Master!$A$2:$A$1000,0)) -> 0
A75: WI-RF-06 | B75: =INDEX(Work_Items!$D$2:$D$300,MATCH(A75,Work_Items!$A$2:$A$300,0)) -> Reinforcement in lintels, bands, chajjas | C75: RBR-001 | D75: =INDEX(Material_Master!$D$2:$D$1000,MATCH(C75,Material_Master!$A$2:$A$1000,0)) -> Deformed bar #3 (10 mm / 3/8in) | E75: K_SPL_LIN_3 | H75: =Coefficients!$D$96 -> 0.4 | I75: kg/kg | J75: Bar-diameter split (replace with BBS) | K75: =INDEX(Material_Master!$F$2:$F$1000,MATCH(C75,Material_Master!$A$2:$A$1000,0)) -> kg | L75: =INDEX(Material_Master!$Q$2:$Q$1000,MATCH(C75,Material_Master!$A$2:$A$1000,0)) -> 0.03
A76: WI-RF-06 | B76: =INDEX(Work_Items!$D$2:$D$300,MATCH(A76,Work_Items!$A$2:$A$300,0)) -> Reinforcement in lintels, bands, chajjas | C76: RBR-002 | D76: =INDEX(Material_Master!$D$2:$D$1000,MATCH(C76,Material_Master!$A$2:$A$1000,0)) -> Deformed bar #4 (12 mm / 1/2in) | E76: K_SPL_LIN_4 | H76: =Coefficients!$D$97 -> 0.6 | I76: kg/kg | J76: Bar-diameter split (replace with BBS) | K76: =INDEX(Material_Master!$F$2:$F$1000,MATCH(C76,Material_Master!$A$2:$A$1000,0)) -> kg | L76: =INDEX(Material_Master!$Q$2:$Q$1000,MATCH(C76,Material_Master!$A$2:$A$1000,0)) -> 0.03
A77: WI-RF-06 | B77: =INDEX(Work_Items!$D$2:$D$300,MATCH(A77,Work_Items!$A$2:$A$300,0)) -> Reinforcement in lintels, bands, chajjas | C77: RBR-006 | D77: =INDEX(Material_Master!$D$2:$D$1000,MATCH(C77,Material_Master!$A$2:$A$1000,0)) -> Binding wire (black annealed) | E77: K_BIND_PER_KG | H77: =Coefficients!$D$98 -> 0.01 | I77: kg/kg | K77: =INDEX(Material_Master!$F$2:$F$1000,MATCH(C77,Material_Master!$A$2:$A$1000,0)) -> kg | L77: =INDEX(Material_Master!$Q$2:$Q$1000,MATCH(C77,Material_Master!$A$2:$A$1000,0)) -> 0
A78: WI-RF-07 | B78: =INDEX(Work_Items!$D$2:$D$300,MATCH(A78,Work_Items!$A$2:$A$300,0)) -> Reinforcement in tanks (3/8in @ 6-12in c/c both faces) | C78: RBR-001 | D78: =INDEX(Material_Master!$D$2:$D$1000,MATCH(C78,Material_Master!$A$2:$A$1000,0)) -> Deformed bar #3 (10 mm / 3/8in) | E78: K_ONE | H78: =Coefficients!$D$2 -> 1 | I78: kg/kg | J78: Bar-diameter split (replace with BBS) | K78: =INDEX(Material_Master!$F$2:$F$1000,MATCH(C78,Material_Master!$A$2:$A$1000,0)) -> kg | L78: =INDEX(Material_Master!$Q$2:$Q$1000,MATCH(C78,Material_Master!$A$2:$A$1000,0)) -> 0.03
A79: WI-RF-07 | B79: =INDEX(Work_Items!$D$2:$D$300,MATCH(A79,Work_Items!$A$2:$A$300,0)) -> Reinforcement in tanks (3/8in @ 6-12in c/c both faces) | C79: RBR-006 | D79: =INDEX(Material_Master!$D$2:$D$1000,MATCH(C79,Material_Master!$A$2:$A$1000,0)) -> Binding wire (black annealed) | E79: K_BIND_PER_KG | H79: =Coefficients!$D$98 -> 0.01 | I79: kg/kg | K79: =INDEX(Material_Master!$F$2:$F$1000,MATCH(C79,Material_Master!$A$2:$A$1000,0)) -> kg | L79: =INDEX(Material_Master!$Q$2:$Q$1000,MATCH(C79,Material_Master!$A$2:$A$1000,0)) -> 0
A80: WI-FW-01 | B80: =INDEX(Work_Items!$D$2:$D$300,MATCH(A80,Work_Items!$A$2:$A$300,0)) -> Formwork to slabs & beam soffits (steel shuttering, hired) | C80: FRM-001 | D80: =INDEX(Material_Master!$D$2:$D$1000,MATCH(C80,Material_Master!$A$2:$A$1000,0)) -> Steel shuttering plates (hire) | E80: K_ONE | H80: =Coefficients!$D$2 -> 1 | I80: sft/sft | J80: Hire | K80: =INDEX(Material_Master!$F$2:$F$1000,MATCH(C80,Material_Master!$A$2:$A$1000,0)) -> sft | L80: =INDEX(Material_Master!$Q$2:$Q$1000,MATCH(C80,Material_Master!$A$2:$A$1000,0)) -> 0
A81: WI-FW-01 | B81: =INDEX(Work_Items!$D$2:$D$300,MATCH(A81,Work_Items!$A$2:$A$300,0)) -> Formwork to slabs & beam soffits (steel shuttering, hired) | C81: FRM-003 | D81: =INDEX(Material_Master!$D$2:$D$1000,MATCH(C81,Material_Master!$A$2:$A$1000,0)) -> Steel props / bamboo ballies (hire) | E81: K_PROP_SFT | H81: =Coefficients!$D$100 -> 0.083 | I81: Nos/sft | J81: Hire | K81: =INDEX(Material_Master!$F$2:$F$1000,MATCH(C81,Material_Master!$A$2:$A$1000,0)) -> Nos | L81: =INDEX(Material_Master!$Q$2:$Q$1000,MATCH(C81,Material_Master!$A$2:$A$1000,0)) -> 0
A82: WI-FW-01 | B82: =INDEX(Work_Items!$D$2:$D$300,MATCH(A82,Work_Items!$A$2:$A$300,0)) -> Formwork to slabs & beam soffits (steel shuttering, hired) | C82: FRM-006 | D82: =INDEX(Material_Master!$D$2:$D$1000,MATCH(C82,Material_Master!$A$2:$A$1000,0)) -> Shuttering release oil | E82: K_OIL_L_SFT | H82: =Coefficients!$D$102 -> 0.008 | I82: L/sft | K82: =INDEX(Material_Master!$F$2:$F$1000,MATCH(C82,Material_Master!$A$2:$A$1000,0)) -> L | L82: =INDEX(Material_Master!$Q$2:$Q$1000,MATCH(C82,Material_Master!$A$2:$A$1000,0)) -> 0.05
A83: WI-FW-01 | B83: =INDEX(Work_Items!$D$2:$D$300,MATCH(A83,Work_Items!$A$2:$A$300,0)) -> Formwork to slabs & beam soffits (steel shuttering, hired) | C83: FRM-008 | D83: =INDEX(Material_Master!$D$2:$D$1000,MATCH(C83,Material_Master!$A$2:$A$1000,0)) -> Polythene sheet over shuttering | E83: K_RF_POLY | H83: =Coefficients!$D$54 -> 1.15 | I83: sft/sft | J83: Optional sheet over shuttering | K83: =INDEX(Material_Master!$F$2:$F$1000,MATCH(C83,Material_Master!$A$2:$A$1000,0)) -> sft | L83: =INDEX(Material_Master!$Q$2:$Q$1000,MATCH(C83,Material_Master!$A$2:$A$1000,0)) -> 0.05
A84: WI-FW-02 | B84: =INDEX(Work_Items!$D$2:$D$300,MATCH(A84,Work_Items!$A$2:$A$300,0)) -> Formwork to columns, footings, lintels, stairs, tanks (ply/timber) | C84: FRM-002 | D84: =INDEX(Material_Master!$D$2:$D$1000,MATCH(C84,Material_Master!$A$2:$A$1000,0)) -> Plywood (shuttering grade 12-18mm) / timber planks | E84: K_PLY_SFT | H84: =Coefficients!$D$104 -> 0.22 | I84: sft/sft | J84: after reuse | K84: =INDEX(Material_Master!$F$2:$F$1000,MATCH(C84,Material_Master!$A$2:$A$1000,0)) -> sft | L84: =INDEX(Material_Master!$Q$2:$Q$1000,MATCH(C84,Material_Master!$A$2:$A$1000,0)) -> 0.1
A85: WI-FW-02 | B85: =INDEX(Work_Items!$D$2:$D$300,MATCH(A85,Work_Items!$A$2:$A$300,0)) -> Formwork to columns, footings, lintels, stairs, tanks (ply/timber) | C85: FRM-004 | D85: =INDEX(Material_Master!$D$2:$D$1000,MATCH(C85,Material_Master!$A$2:$A$1000,0)) -> Timber battens / scantlings | E85: K_BATTEN_CFT_SFT | H85: =Coefficients!$D$105 -> 0.02 | I85: cft/sft | K85: =INDEX(Material_Master!$F$2:$F$1000,MATCH(C85,Material_Master!$A$2:$A$1000,0)) -> cft | L85: =INDEX(Material_Master!$Q$2:$Q$1000,MATCH(C85,Material_Master!$A$2:$A$1000,0)) -> 0.15
A86: WI-FW-02 | B86: =INDEX(Work_Items!$D$2:$D$300,MATCH(A86,Work_Items!$A$2:$A$300,0)) -> Formwork to columns, footings, lintels, stairs, tanks (ply/timber) | C86: FRM-005 | D86: =INDEX(Material_Master!$D$2:$D$1000,MATCH(C86,Material_Master!$A$2:$A$1000,0)) -> Nails (assorted) | E86: K_NAIL_KG_SFT | H86: =Coefficients!$D$101 -> 0.01 | I86: kg/sft | K86: =INDEX(Material_Master!$F$2:$F$1000,MATCH(C86,Material_Master!$A$2:$A$1000,0)) -> kg | L86: =INDEX(Material_Master!$Q$2:$Q$1000,MATCH(C86,Material_Master!$A$2:$A$1000,0)) -> 0.05
A87: WI-FW-02 | B87: =INDEX(Work_Items!$D$2:$D$300,MATCH(A87,Work_Items!$A$2:$A$300,0)) -> Formwork to columns, footings, lintels, stairs, tanks (ply/timber) | C87: FRM-006 | D87: =INDEX(Material_Master!$D$2:$D$1000,MATCH(C87,Material_Master!$A$2:$A$1000,0)) -> Shuttering release oil | E87: K_OIL_L_SFT | H87: =Coefficients!$D$102 -> 0.008 | I87: L/sft | K87: =INDEX(Material_Master!$F$2:$F$1000,MATCH(C87,Material_Master!$A$2:$A$1000,0)) -> L | L87: =INDEX(Material_Master!$Q$2:$Q$1000,MATCH(C87,Material_Master!$A$2:$A$1000,0)) -> 0.05
A88: WI-MS-01 | B88: =INDEX(Work_Items!$D$2:$D$300,MATCH(A88,Work_Items!$A$2:$A$300,0)) -> Brick masonry in stepped foundations 1:6 (below DPC) | C88: MAS-001 | D88: =INDEX(Material_Master!$D$2:$D$1000,MATCH(C88,Material_Master!$A$2:$A$1000,0)) -> Burnt clay brick Class A ('Awwal') 9x4.5x3in nominal | E88: K_BRK_PER_CFT | H88: =Coefficients!$D$17 -> 13.102347 | I88: Nos/cft | K88: =INDEX(Material_Master!$F$2:$F$1000,MATCH(C88,Material_Master!$A$2:$A$1000,0)) -> Nos | L88: =INDEX(Material_Master!$Q$2:$Q$1000,MATCH(C88,Material_Master!$A$2:$A$1000,0)) -> 0.05
A89: WI-MS-01 | B89: =INDEX(Work_Items!$D$2:$D$300,MATCH(A89,Work_Items!$A$2:$A$300,0)) -> Brick masonry in stepped foundations 1:6 (below DPC) | C89: CON-001 | D89: =INDEX(Material_Master!$D$2:$D$1000,MATCH(C89,Material_Master!$A$2:$A$1000,0)) -> Ordinary Portland Cement (OPC) - 50 kg bag | E89: K_MORT_WET_PER_CFT | F89: MX_MOR16 | G89: cement | H89: =Coefficients!$D$19*Mix_Design!$J$10 -> 0.03479913 | I89: bag/cft | K89: =INDEX(Material_Master!$F$2:$F$1000,MATCH(C89,Material_Master!$A$2:$A$1000,0)) -> bag | L89: =INDEX(Material_Master!$Q$2:$Q$1000,MATCH(C89,Material_Master!$A$2:$A$1000,0)) -> 0.02
A90: WI-MS-01 | B90: =INDEX(Work_Items!$D$2:$D$300,MATCH(A90,Work_Items!$A$2:$A$300,0)) -> Brick masonry in stepped foundations 1:6 (below DPC) | C90: CON-005 | D90: =INDEX(Material_Master!$D$2:$D$1000,MATCH(C90,Material_Master!$A$2:$A$1000,0)) -> Sand for masonry & plaster | E90: K_MORT_WET_PER_CFT | F90: MX_MOR16 | G90: sand | H90: =Coefficients!$D$19*Mix_Design!$K$10 -> 0.25602518 | I90: cft/cft | K90: =INDEX(Material_Master!$F$2:$F$1000,MATCH(C90,Material_Master!$A$2:$A$1000,0)) -> cft | L90: =INDEX(Material_Master!$Q$2:$Q$1000,MATCH(C90,Material_Master!$A$2:$A$1000,0)) -> 0.1
A91: WI-MS-02 | B91: =INDEX(Work_Items!$D$2:$D$300,MATCH(A91,Work_Items!$A$2:$A$300,0)) -> Brick masonry 9in in superstructure 1:6 | C91: MAS-001 | D91: =INDEX(Material_Master!$D$2:$D$1000,MATCH(C91,Material_Master!$A$2:$A$1000,0)) -> Burnt clay brick Class A ('Awwal') 9x4.5x3in nominal | E91: K_BRK_PER_CFT | H91: =Coefficients!$D$17 -> 13.102347 | I91: Nos/cft | K91: =INDEX(Material_Master!$F$2:$F$1000,MATCH(C91,Material_Master!$A$2:$A$1000,0)) -> Nos | L91: =INDEX(Material_Master!$Q$2:$Q$1000,MATCH(C91,Material_Master!$A$2:$A$1000,0)) -> 0.05
A92: WI-MS-02 | B92: =INDEX(Work_Items!$D$2:$D$300,MATCH(A92,Work_Items!$A$2:$A$300,0)) -> Brick masonry 9in in superstructure 1:6 | C92: CON-001 | D92: =INDEX(Material_Master!$D$2:$D$1000,MATCH(C92,Material_Master!$A$2:$A$1000,0)) -> Ordinary Portland Cement (OPC) - 50 kg bag | E92: K_MORT_WET_PER_CFT | F92: MX_MOR16 | G92: cement | H92: =Coefficients!$D$19*Mix_Design!$J$10 -> 0.03479913 | I92: bag/cft | K92: =INDEX(Material_Master!$F$2:$F$1000,MATCH(C92,Material_Master!$A$2:$A$1000,0)) -> bag | L92: =INDEX(Material_Master!$Q$2:$Q$1000,MATCH(C92,Material_Master!$A$2:$A$1000,0)) -> 0.02
A93: WI-MS-02 | B93: =INDEX(Work_Items!$D$2:$D$300,MATCH(A93,Work_Items!$A$2:$A$300,0)) -> Brick masonry 9in in superstructure 1:6 | C93: CON-005 | D93: =INDEX(Material_Master!$D$2:$D$1000,MATCH(C93,Material_Master!$A$2:$A$1000,0)) -> Sand for masonry & plaster | E93: K_MORT_WET_PER_CFT | F93: MX_MOR16 | G93: sand | H93: =Coefficients!$D$19*Mix_Design!$K$10 -> 0.25602518 | I93: cft/cft | K93: =INDEX(Material_Master!$F$2:$F$1000,MATCH(C93,Material_Master!$A$2:$A$1000,0)) -> cft | L93: =INDEX(Material_Master!$Q$2:$Q$1000,MATCH(C93,Material_Master!$A$2:$A$1000,0)) -> 0.1
A94: WI-MS-03 | B94: =INDEX(Work_Items!$D$2:$D$300,MATCH(A94,Work_Items!$A$2:$A$300,0)) -> Brick masonry 4.5in partitions 1:4 | C94: MAS-001 | D94: =INDEX(Material_Master!$D$2:$D$1000,MATCH(C94,Material_Master!$A$2:$A$1000,0)) -> Burnt clay brick Class A ('Awwal') 9x4.5x3in nominal | E94: K_BRK_PER_SFT_45 | H94: =Coefficients!$D$22 -> 4.9133802 | I94: Nos/sft | K94: =INDEX(Material_Master!$F$2:$F$1000,MATCH(C94,Material_Master!$A$2:$A$1000,0)) -> Nos | L94: =INDEX(Material_Master!$Q$2:$Q$1000,MATCH(C94,Material_Master!$A$2:$A$1000,0)) -> 0.05
A95: WI-MS-03 | B95: =INDEX(Work_Items!$D$2:$D$300,MATCH(A95,Work_Items!$A$2:$A$300,0)) -> Brick masonry 4.5in partitions 1:4 | C95: CON-001 | D95: =INDEX(Material_Master!$D$2:$D$1000,MATCH(C95,Material_Master!$A$2:$A$1000,0)) -> Ordinary Portland Cement (OPC) - 50 kg bag | E95: K_MORT_WET_PER_SFT_45 | F95: MX_MOR14 | G95: cement | H95: =Coefficients!$D$23*Mix_Design!$J$8 -> 0.018269543 | I95: bag/sft | K95: =INDEX(Material_Master!$F$2:$F$1000,MATCH(C95,Material_Master!$A$2:$A$1000,0)) -> bag | L95: =INDEX(Material_Master!$Q$2:$Q$1000,MATCH(C95,Material_Master!$A$2:$A$1000,0)) -> 0.02
A96: WI-MS-03 | B96: =INDEX(Work_Items!$D$2:$D$300,MATCH(A96,Work_Items!$A$2:$A$300,0)) -> Brick masonry 4.5in partitions 1:4 | C96: CON-005 | D96: =INDEX(Material_Master!$D$2:$D$1000,MATCH(C96,Material_Master!$A$2:$A$1000,0)) -> Sand for masonry & plaster | E96: K_MORT_WET_PER_SFT_45 | F96: MX_MOR14 | G96: sand | H96: =Coefficients!$D$23*Mix_Design!$K$8 -> 0.089608812 | I96: cft/sft | K96: =INDEX(Material_Master!$F$2:$F$1000,MATCH(C96,Material_Master!$A$2:$A$1000,0)) -> cft | L96: =INDEX(Material_Master!$Q$2:$Q$1000,MATCH(C96,Material_Master!$A$2:$A$1000,0)) -> 0.1
A97: WI-MS-04 | B97: =INDEX(Work_Items!$D$2:$D$300,MATCH(A97,Work_Items!$A$2:$A$300,0)) -> Parapet walls 9in / 4.5in | C97: MAS-001 | D97: =INDEX(Material_Master!$D$2:$D$1000,MATCH(C97,Material_Master!$A$2:$A$1000,0)) -> Burnt clay brick Class A ('Awwal') 9x4.5x3in nominal | E97: K_BRK_PER_CFT | H97: =Coefficients!$D$17 -> 13.102347 | I97: Nos/cft | K97: =INDEX(Material_Master!$F$2:$F$1000,MATCH(C97,Material_Master!$A$2:$A$1000,0)) -> Nos | L97: =INDEX(Material_Master!$Q$2:$Q$1000,MATCH(C97,Material_Master!$A$2:$A$1000,0)) -> 0.05
A98: WI-MS-04 | B98: =INDEX(Work_Items!$D$2:$D$300,MATCH(A98,Work_Items!$A$2:$A$300,0)) -> Parapet walls 9in / 4.5in | C98: CON-001 | D98: =INDEX(Material_Master!$D$2:$D$1000,MATCH(C98,Material_Master!$A$2:$A$1000,0)) -> Ordinary Portland Cement (OPC) - 50 kg bag | E98: K_MORT_WET_PER_CFT | F98: MX_MOR16 | G98: cement | H98: =Coefficients!$D$19*Mix_Design!$J$10 -> 0.03479913 | I98: bag/cft | K98: =INDEX(Material_Master!$F$2:$F$1000,MATCH(C98,Material_Master!$A$2:$A$1000,0)) -> bag | L98: =INDEX(Material_Master!$Q$2:$Q$1000,MATCH(C98,Material_Master!$A$2:$A$1000,0)) -> 0.02
A99: WI-MS-04 | B99: =INDEX(Work_Items!$D$2:$D$300,MATCH(A99,Work_Items!$A$2:$A$300,0)) -> Parapet walls 9in / 4.5in | C99: CON-005 | D99: =INDEX(Material_Master!$D$2:$D$1000,MATCH(C99,Material_Master!$A$2:$A$1000,0)) -> Sand for masonry & plaster | E99: K_MORT_WET_PER_CFT | F99: MX_MOR16 | G99: sand | H99: =Coefficients!$D$19*Mix_Design!$K$10 -> 0.25602518 | I99: cft/cft | K99: =INDEX(Material_Master!$F$2:$F$1000,MATCH(C99,Material_Master!$A$2:$A$1000,0)) -> cft | L99: =INDEX(Material_Master!$Q$2:$Q$1000,MATCH(C99,Material_Master!$A$2:$A$1000,0)) -> 0.1
A100: WI-MS-02 | B100: =INDEX(Work_Items!$D$2:$D$300,MATCH(A100,Work_Items!$A$2:$A$300,0)) -> Brick masonry 9in in superstructure 1:6 | C100: MAS-013 | D100: =INDEX(Material_Master!$D$2:$D$1000,MATCH(C100,Material_Master!$A$2:$A$1000,0)) -> Galvanised chicken wire mesh strip (6-9in) | E100: K_MESH_RFT_PER_SFT | H100: =Coefficients!$D$31 -> 0.1 | I100: rft/cft | J100: Allowance; better measured from junction length | K100: =INDEX(Material_Master!$F$2:$F$1000,MATCH(C100,Material_Master!$A$2:$A$1000,0)) -> rft | L100: =INDEX(Material_Master!$Q$2:$Q$1000,MATCH(C100,Material_Master!$A$2:$A$1000,0)) -> 0.05
...

Sheet Coefficients
A1: Coeff_ID | B1: Group | C1: Description | D1: Value | E1: Unit | F1: Basis / Formula | G1: Source
A2: K_ONE | B2: General | C2: Unity driver (1 unit of material per unit of work item) | D2: 1 | E2: - | F2: Used where material qty = work qty | G2: Definition
A3: K_CFT_M3 | B3: General | C3: Cubic feet per cubic metre | D3: 35.3147 | E3: cft/m3 | F3: Exact conversion | G3: SI definition
A4: K_SFT_M2 | B4: General | C4: Square feet per square metre | D4: 10.7639 | E4: sft/m2 | F4: Exact conversion | G4: SI definition
A5: K_FT_M | B5: General | C5: Feet per metre | D5: 3.28084 | E5: ft/m | F5: Exact conversion | G5: SI definition
A6: K_CEM_DENS | B6: General | C6: Bulk density of cement | D6: 1440 | E6: kg/m3 | F6: Loose bulk density used in PK/South-Asian estimating | G6: Standard estimating practice
A7: K_BAG_KG | B7: General | C7: Cement bag mass | D7: 50 | E7: kg/bag | F7: Standard PK bag | G7: PS 232 / market standard
A8: K_BAG_CFT | B8: General | C8: Volume of one 50 kg cement bag | D8: =$D$7/$D$6*$D$3 -> 1.2262049 | E8: cft/bag | F8: Rule: bag kg / density x cft per m3 (~1.226) | G8: Derived
A9: K_WC | B9: General | C9: Water-cement ratio (by mass) for mixing water | D9: 0.5 | E9: - | F9: Nominal-mix default; RMC/design mix overrides | G9: Engineering default - verify
A10: K_DF_CONC | B10: General | C10: Dry volume factor - concrete | D10: 1.54 | E10: - | F10: Wet-to-dry volume (voids + bulking + wastage in handling) | G10: Standard estimating practice (also used in current app rules.py)
A11: K_DF_MORT | B11: General | C11: Dry volume factor - mortar/plaster | D11: 1.33 | E11: - | F11: Wet-to-dry volume for cement-sand mortar | G11: Standard estimating practice
A12: K_GAL_L | B12: General | C12: Litres per Pakistani paint 'gallon' pack | D12: 3.64 | E12: L/gal | F12: Local paint packs are 3.64 L (verify brand pack size) | G12: Market practice - verify
A13: K_BRK_L | B13: Masonry | C13: Actual brick length (measure site sample) | D13: 8.75 | E13: in | F13: Class-A kiln bricks are usually smaller than nominal 9in | G13: Measure on site; nominal 9x4.5x3
A14: K_BRK_W | B14: Masonry | C14: Actual brick width | D14: 4.25 | E14: in | G14: Measure on site
A15: K_BRK_H | B15: Masonry | C15: Actual brick height | D15: 2.75 | E15: in | G15: Measure on site
A16: K_JOINT | B16: Masonry | C16: Mortar joint thickness | D16: 0.375 | E16: in | F16: 3/8 in standard | G16: Standard practice
A17: K_BRK_PER_CFT | B17: Masonry | C17: Bricks per cft of masonry (net, before wastage) | D17: =1728/(($D$13+$D$16)*($D$14+$D$16)*($D$15+$D$16)) -> 13.102347 | E17: Nos/cft | F17: Rule: 1728/((L+j)(W+j)(H+j)) | G17: Derived; cross-check with PK rule 1350/100 cft
A18: K_BRK_STD_PER_CFT | B18: Masonry | C18: PK conventional figure (reference only) | D18: 13.5 | E18: Nos/cft | F18: 1350 bricks per 100 cft (commonly quoted; includes some allowance) | G18: civilsir.com; civilengineerspk.com
A19: K_MORT_WET_PER_CFT | B19: Masonry | C19: Wet mortar per cft of brick masonry | D19: =1-$D$17*$D$13*$D$14*$D$15/1728 -> 0.22458349 | E19: cft/cft | F19: Rule: 1 - bricks x brick volume | G19: Derived (~0.22-0.25 wet; ~0.30 dry)
A20: K_T_WALL9 | B20: Masonry | C20: Thickness of 9in wall | D20: 0.75 | E20: ft | G20: Drawing: 9in walls
A21: K_T_WALL45 | B21: Masonry | C21: Thickness of 4.5in wall | D21: 0.375 | E21: ft | G21: Drawing: 4.5in partitions
A22: K_BRK_PER_SFT_45 | B22: Masonry | C22: Bricks per sft of 4.5in wall | D22: =$D$17*$D$21 -> 4.9133802 | E22: Nos/sft | G22: Derived
A23: K_MORT_WET_PER_SFT_45 | B23: Masonry | C23: Wet mortar per sft of 4.5in wall | D23: =$D$19*$D$21 -> 0.084218808 | E23: cft/sft | G23: Derived
A24: K_SOL_FLAT_PER_SFT | B24: Masonry | C24: Bricks per sft - flat soling | D24: =144/(($D$13+$D$16)*($D$14+$D$16)) -> 3.4120696 | E24: Nos/sft | G24: Derived
A25: K_SOL_SAND | B25: Masonry | C25: Sand for grouting joints of soling | D25: 0.03 | E25: cft/sft | F25: Allowance | G25: Estimating allowance - verify
A26: K_RTILE_L | B26: Masonry | C26: Roof brick tile length | D26: 9 | E26: in | F26: 9x4.5x1.5 burnt tiles | G26: Market practice
A27: K_RTILE_W | B27: Masonry | C27: Roof brick tile width | D27: 4.5 | E27: in | G27: Market practice
A28: K_RTILE_PER_SFT | B28: Masonry | C28: Roof tiles per sft | D28: =144/(($D$26+$D$16)*($D$27+$D$16)) -> 3.1507692 | E28: Nos/sft | G28: Derived
A29: K_BLK_PER_SFT | B29: Masonry | C29: Concrete blocks 8x8x16 per sft of wall face | D29: =144/((16+$D$16)*(8+$D$16)) -> 1.0500171 | E29: Nos/sft | G29: Derived
A30: K_BLK_MORT_WET_SFT | B30: Masonry | C30: Wet mortar per sft of 8in block wall | D30: 0.025 | E30: cft/sft | F30: Allowance (bed + perp joints) | G30: Estimating allowance - verify
A31: K_MESH_RFT_PER_SFT | B31: Masonry | C31: Chicken mesh strip at RCC/brick junction per sft of plaster | D31: 0.1 | E31: rft/sft | F31: Allowance; measure actual junction length when available | G31: Allowance
A32: K_PL_T_INT | B32: Plaster | C32: Internal plaster thickness | D32: 0.5 | E32: in | G32: Typical spec
A33: K_PL_T_EXT | B33: Plaster | C33: External plaster thickness | D33: 0.75 | E33: in | G33: Typical spec; drawing shows 3/4in on plinth
A34: K_PL_T_CEIL | B34: Plaster | C34: Ceiling plaster thickness | D34: 0.375 | E34: in | G34: Typical spec
A35: K_PL_EXTRA | B35: Plaster | C35: Extra for uneven surface / joint filling | D35: 0.2 | E35: - | G35: Estimating allowance
A36: K_PL_INT_WET | B36: Plaster | C36: Wet mortar per sft internal plaster | D36: =$D$32/12*(1+$D$35) -> 0.05 | E36: cft/sft | G36: Derived
A37: K_PL_EXT_WET | B37: Plaster | C37: Wet mortar per sft external plaster | D37: =$D$33/12*(1+$D$35) -> 0.075 | E37: cft/sft | G37: Derived
A38: K_PL_CEIL_WET | B38: Plaster | C38: Wet mortar per sft ceiling plaster | D38: =$D$34/12*(1+$D$35) -> 0.0375 | E38: cft/sft | G38: Derived
A39: K_CBEAD_RFT_SFT | B39: Plaster | C39: Corner bead per sft of plaster | D39: 0.05 | E39: rft/sft | F39: Allowance; measure external corners when available | G39: Allowance
A40: K_BED_T | B40: Flooring | C40: Tile/marble bedding mortar thickness | D40: 1 | E40: in | F40: Traditional mortar-bed method | G40: Typical practice
A41: K_BED_WET | B41: Flooring | C41: Wet bedding mortar per sft | D41: =$D$40/12 -> 0.083333333 | E41: cft/sft | G41: Derived
A42: K_DPC_T | B42: Waterproofing | C42: DPC thickness (drawing: 1.5in PCC 1:2:4) | D42: 1.5 | E42: in | G42: Drawing sheet 14/15
A43: K_DPC_WET | B43: Waterproofing | C43: DPC concrete per sft | D43: =$D$42/12 -> 0.125 | E43: cft/sft | G43: Derived
A44: K_BIT_KG_SFT_COAT | B44: Waterproofing | C44: Hot bitumen per sft per coat | D44: 0.14 | E44: kg/sft/coat | F44: ~1.5 kg/m2/coat | G44: Estimating allowance - verify
A45: K_DPC_BIT_COATS | B45: Waterproofing | C45: Bitumen coats on DPC | D45: 2 | E45: coats | G45: Drawing: two coats of bitumen
A46: K_DPC_BIT | B46: Waterproofing | C46: Bitumen per sft of DPC | D46: =$D$44*$D$45 -> 0.28 | E46: kg/sft | G46: Derived
A47: K_POLY_OVERLAP | B47: Waterproofing | C47: Polythene overlap allowance | D47: 0.15 | E47: - | G47: Allowance
A48: K_DPC_POLY_LAYERS | B48: Waterproofing | C48: Polythene layers on DPC | D48: 2 | E48: layers | G48: Drawing: double layer high-density plastic sheet
A49: K_DPC_POLY | B49: Waterproofing | C49: Polythene per sft DPC | D49: =$D$48*(1+$D$47) -> 2.3 | E49: sft/sft | G49: Derived
A50: K_WPADMIX_KG_BAG | B50: Waterproofing | C50: Integral waterproofing admixture per cement bag | D50: 1 | E50: kg/bag | F50: Per manufacturer (powder e.g. 'Puddlo'-type, or liquid equivalent) | G50: Manufacturer - verify
A51: K_DPC_WPADMIX | B51: Waterproofing | C51: WP admixture per sft DPC | D51: =$D$43*Mix_Design!$J$6*$D$50 -> 0.022426921 | E51: kg/sft | G51: Derived
A52: K_RF_BIT_COATS | B52: Waterproofing | C52: Bitumen coats on roof | D52: 2 | E52: coats | G52: Typical PK roof treatment
A53: K_RF_BIT | B53: Waterproofing | C53: Bitumen per sft roof | D53: =$D$44*$D$52 -> 0.28 | E53: kg/sft | G53: Derived
A54: K_RF_POLY | B54: Waterproofing | C54: Polythene per sft roof (1 layer) | D54: =1+$D$47 -> 1.15 | E54: sft/sft | G54: Derived
A55: K_RF_EARTH_T | B55: Waterproofing | C55: Roof earth/mud insulation avg thickness | D55: 4 | E55: in | F55: Traditional; laid to slope | G55: Typical practice
A56: K_RF_EARTH | B56: Waterproofing | C56: Earth per sft roof (incl. 20% compaction) | D56: =$D$55/12*1.2 -> 0.4 | E56: cft/sft | G56: Derived
A57: K_RF_MUD_T | B57: Waterproofing | C57: Mud plaster (leeping) thickness | D57: 1 | E57: in | G57: Typical practice
A58: K_RF_MUD | B58: Waterproofing | C58: Mud for plaster per sft | D58: =$D$57/12*1.2 -> 0.1 | E58: cft/sft | G58: Derived
A59: K_RF_STRAW | B59: Waterproofing | C59: Straw (bhoosa) in mud plaster | D59: 0.05 | E59: kg/sft | F59: Allowance | G59: Allowance - verify
A60: K_RF_BED_T | B60: Waterproofing | C60: Roof tile bedding mortar thickness | D60: 0.5 | E60: in | G60: Typical practice
A61: K_RF_BED_WET | B61: Waterproofing | C61: Roof tile bedding mortar per sft | D61: =$D$60/12*(1+$D$35) -> 0.05 | E61: cft/sft | G61: Derived
A62: K_SCREED_T | B62: Waterproofing | C62: Avg slope screed thickness (roof/terrace/bath) | D62: 2 | E62: in | F62: Slope 1:100 towards khuras | G62: Drawing: roof slope 0.01-0.02
A63: K_SCREED_WET | B63: Waterproofing | C63: Screed per sft | D63: =$D$62/12 -> 0.16666667 | E63: cft/sft | G63: Derived
A64: K_CEMWP_KG_SFT | B64: Waterproofing | C64: Cementitious WP coating (2 coats) | D64: 0.18 | E64: kg/sft | F64: ~2 kg/m2 total | G64: Manufacturer - verify
A65: K_APRON_T | B65: External | C65: Plinth protection / apron PCC thickness | D65: 3 | E65: in | G65: Typical practice
A66: K_APRON_WET | B66: External | C66: PCC per sft apron | D66: =$D$65/12 -> 0.25 | E66: cft/sft | G66: Derived
A67: K_FILL_COMPACT | B67: Earthwork | C67: Loose-to-compacted factor for earth fill | D67: 1.2 | E67: - | F67: Imported earth measured loose | G67: Estimating practice
A68: K_SAND_COMPACT | B68: Earthwork | C68: Loose-to-compacted factor for sand fill | D68: 1.15 | E68: - | G68: Estimating practice
A69: K_AT_L_SFT | B69: Earthwork | C69: Anti-termite concentrate per sft treated | D69: 0.025 | E69: L/sft | F69: Diluted per label; verify active ingredient | G69: Manufacturer label - verify
A70: K_ST_FTG_M3 | B70: Steel | C70: Steel ratio - footings | D70: 80 | E70: kg/m3 | F70: Use only if no BBS | G70: Current app rules.py (60-100)
A71: K_ST_COL_M3 | B71: Steel | C71: Steel ratio - columns | D71: 170 | E71: kg/m3 | G71: Current app rules.py (140-200)
A72: K_ST_BEAM_M3 | B72: Steel | C72: Steel ratio - beams | D72: 135 | E72: kg/m3 | G72: Current app rules.py (110-160)
A73: K_ST_SLAB_M3 | B73: Steel | C73: Steel ratio - slabs | D73: 85 | E73: kg/m3 | G73: Current app rules.py (70-100)
A74: K_ST_STAIR_M3 | B74: Steel | C74: Steel ratio - stairs | D74: 100 | E74: kg/m3 | G74: Current app rules.py
A75: K_ST_LINTEL_M3 | B75: Steel | C75: Steel ratio - lintels/bands/chajjas | D75: 80 | E75: kg/m3 | G75: Current app rules.py
A76: K_ST_PB_M3 | B76: Steel | C76: Steel ratio - plinth beams | D76: 120 | E76: kg/m3 | G76: Current app rules.py
A77: K_ST_TANK_M3 | B77: Steel | C77: Steel ratio - water/septic tanks | D77: 110 | E77: kg/m3 | F77: 3/8in @6in c/c both faces per drawing | G77: Estimated from sheet 16 details
A78: K_ST_FTG | B78: Steel | C78: Steel per cft - footings | D78: =$D$70/$D$3 -> 2.2653456 | E78: kg/cft | G78: Derived
A79: K_ST_COL | B79: Steel | C79: Steel per cft - columns | D79: =$D$71/$D$3 -> 4.8138594 | E79: kg/cft | G79: Derived
A80: K_ST_BEAM | B80: Steel | C80: Steel per cft - beams | D80: =$D$72/$D$3 -> 3.8227707 | E80: kg/cft | G80: Derived
A81: K_ST_SLAB | B81: Steel | C81: Steel per cft - slabs | D81: =$D$73/$D$3 -> 2.4069297 | E81: kg/cft | G81: Derived
A82: K_ST_STAIR | B82: Steel | C82: Steel per cft - stairs | D82: =$D$74/$D$3 -> 2.831682 | E82: kg/cft | G82: Derived
A83: K_ST_LINTEL | B83: Steel | C83: Steel per cft - lintels/bands | D83: =$D$75/$D$3 -> 2.2653456 | E83: kg/cft | G83: Derived
A84: K_ST_PB | B84: Steel | C84: Steel per cft - plinth beams | D84: =$D$76/$D$3 -> 3.3980184 | E84: kg/cft | G84: Derived
A85: K_ST_TANK | B85: Steel | C85: Steel per cft - tanks | D85: =$D$77/$D$3 -> 3.1148502 | E85: kg/cft | G85: Derived
A86: K_SPL_SLAB_3 | B86: Steel | C86: Bar split - slab #3 (10mm) | D86: 0.35 | E86: fraction | F86: Distribution/temperature bars | G86: Typical - replace with BBS
A87: K_SPL_SLAB_4 | B87: Steel | C87: Bar split - slab #4 (12mm) | D87: 0.65 | E87: fraction | F87: Main bars | G87: Typical - replace with BBS
A88: K_SPL_BEAM_3 | B88: Steel | C88: Bar split - beam #3 stirrups | D88: 0.25 | E88: fraction | G88: Typical
A89: K_SPL_BEAM_4 | B89: Steel | C89: Bar split - beam #4 | D89: 0.35 | E89: fraction | G89: Typical
A90: K_SPL_BEAM_5 | B90: Steel | C90: Bar split - beam #5 | D90: 0.4 | E90: fraction | G90: Typical
A91: K_SPL_COL_3 | B91: Steel | C91: Bar split - column #3 ties | D91: 0.25 | E91: fraction | G91: Typical
A92: K_SPL_COL_4 | B92: Steel | C92: Bar split - column #4 | D92: 0.35 | E92: fraction | F92: Drawing sec AA shows #4 | G92: Typical
A93: K_SPL_COL_5 | B93: Steel | C93: Bar split - column #5 | D93: 0.4 | E93: fraction | G93: Typical
A94: K_SPL_FTG_3 | B94: Steel | C94: Bar split - footing #3 | D94: 0.3 | E94: fraction | F94: Drawing: #3 @6in c/c mats | G94: Drawing sheet 14
A95: K_SPL_FTG_4 | B95: Steel | C95: Bar split - footing #4 | D95: 0.7 | E95: fraction | G95: Typical
A96: K_SPL_LIN_3 | B96: Steel | C96: Bar split - lintel/band #3 | D96: 0.4 | E96: fraction | G96: Typical
A97: K_SPL_LIN_4 | B97: Steel | C97: Bar split - lintel/band #4 | D97: 0.6 | E97: fraction | G97: Typical
A98: K_BIND_PER_KG | B98: Steel | C98: Binding wire per kg rebar | D98: 0.01 | E98: kg/kg | F98: ~10 kg per tonne | G98: Estimating practice (8-12 kg/t)
A99: K_COVERBLK_CFT | B99: Steel | C99: Cover blocks/spacers per cft RCC | D99: 1 | E99: Nos/cft | F99: Allowance | G99: Allowance
A100: K_PROP_SFT | B100: Formwork | C100: Props per sft of slab/beam soffit formwork | D100: 0.083 | E100: Nos/sft | F100: ~1 prop per 12 sft (3x4 ft grid) | G100: Typical practice
...

Sheet Mix_Design
A1: Mix_ID | B1: Description | C1: Typical Use | D1: Cement parts | E1: Sand parts | F1: Aggregate parts | G1: Dry Volume Factor | H1: Sum of parts | I1: Cement cft per cft wet | J1: Cement bags per cft | K1: Sand cft per cft | L1: Aggregate cft per cft | M1: Cement bags per m3 | N1: Sand m3 per m3 | O1: Aggregate m3 per m3 | P1: Water L per cft | Q1: Notes
A2: MX_PCC148 | B2: PCC 1:4:8 | C2: Foundation base, under-floor PCC (drawing) | D2: 1 | E2: 4 | F2: 8 | G2: =Coefficients!$D$10 -> 1.54 | H2: =D2+E2+F2 -> 13 | I2: =G2*D2/H2 -> 0.11846154 | J2: =I2/Coefficients!$D$8 -> 0.096608277 | K2: =G2*E2/H2 -> 0.47384615 | L2: =G2*F2/H2 -> 0.94769231 | M2: =J2*Coefficients!$D$3 -> 3.4116923 | N2: =K2 -> 0.47384615 | O2: =L2 -> 0.94769231 | P2: =J2*Coefficients!$D$7*Coefficients!$D$9 -> 2.4152069 | Q2: Drawing sheets 14/15/16
A3: MX_PCC136 | B3: PCC 1:3:6 | C3: Floor base / blinding alternative | D3: 1 | E3: 3 | F3: 6 | G3: =Coefficients!$D$10 -> 1.54 | H3: =D3+E3+F3 -> 10 | I3: =G3*D3/H3 -> 0.154 | J3: =I3/Coefficients!$D$8 -> 0.12559076 | K3: =G3*E3/H3 -> 0.462 | L3: =G3*F3/H3 -> 0.924 | M3: =J3*Coefficients!$D$3 -> 4.4352 | N3: =K3 -> 0.462 | O3: =L3 -> 0.924 | P3: =J3*Coefficients!$D$7*Coefficients!$D$9 -> 3.139769
A4: MX_RCC124 | B4: RCC 1:2:4 (~M15/2500 psi nominal) | C4: Footings, columns, beams, slabs, tanks (drawing spec) | D4: 1 | E4: 2 | F4: 4 | G4: =Coefficients!$D$10 -> 1.54 | H4: =D4+E4+F4 -> 7 | I4: =G4*D4/H4 -> 0.22 | J4: =I4/Coefficients!$D$8 -> 0.17941537 | K4: =G4*E4/H4 -> 0.44 | L4: =G4*F4/H4 -> 0.88 | M4: =J4*Coefficients!$D$3 -> 6.336 | N4: =K4 -> 0.44 | O4: =L4 -> 0.88 | P4: =J4*Coefficients!$D$7*Coefficients!$D$9 -> 4.4853843 | Q4: Drawing sheets 14/16/24
A5: MX_RCC1153 | B5: RCC 1:1.5:3 (~M20/3000 psi nominal) | C5: Recommended for slabs/columns in seismic zone 2B | D5: 1 | E5: 1.5 | F5: 3 | G5: =Coefficients!$D$10 -> 1.54 | H5: =D5+E5+F5 -> 5.5 | I5: =G5*D5/H5 -> 0.28 | J5: =I5/Coefficients!$D$8 -> 0.22834684 | K5: =G5*E5/H5 -> 0.42 | L5: =G5*F5/H5 -> 0.84 | M5: =J5*Coefficients!$D$3 -> 8.064 | N5: =K5 -> 0.42 | O5: =L5 -> 0.84 | P5: =J5*Coefficients!$D$7*Coefficients!$D$9 -> 5.7086709 | Q5: Engineer to confirm; BCP-2021
A6: MX_DPC124 | B6: DPC 1:2:4 with 3/8in aggregate | C6: Damp-proof course 1.5in | D6: 1 | E6: 2 | F6: 4 | G6: =Coefficients!$D$10 -> 1.54 | H6: =D6+E6+F6 -> 7 | I6: =G6*D6/H6 -> 0.22 | J6: =I6/Coefficients!$D$8 -> 0.17941537 | K6: =G6*E6/H6 -> 0.44 | L6: =G6*F6/H6 -> 0.88 | M6: =J6*Coefficients!$D$3 -> 6.336 | N6: =K6 -> 0.44 | O6: =L6 -> 0.88 | P6: =J6*Coefficients!$D$7*Coefficients!$D$9 -> 4.4853843 | Q6: Drawing sheet 14/15
A7: MX_MOR13 | B7: Mortar 1:3 | C7: Tank/manhole plaster, pointing | D7: 1 | E7: 3 | F7: 0 | G7: =Coefficients!$D$11 -> 1.33 | H7: =D7+E7+F7 -> 4 | I7: =G7*D7/H7 -> 0.3325 | J7: =I7/Coefficients!$D$8 -> 0.27116187 | K7: =G7*E7/H7 -> 0.9975 | L7: =G7*F7/H7 -> 0 | M7: =J7*Coefficients!$D$3 -> 9.576 | N7: =K7 -> 0.9975 | O7: =L7 -> 0 | P7: =J7*Coefficients!$D$7*Coefficients!$D$9 -> 6.7790467
A8: MX_MOR14 | B8: Mortar 1:4 | C8: External plaster, 4.5in walls, manholes, tile bedding | D8: 1 | E8: 4 | F8: 0 | G8: =Coefficients!$D$11 -> 1.33 | H8: =D8+E8+F8 -> 5 | I8: =G8*D8/H8 -> 0.266 | J8: =I8/Coefficients!$D$8 -> 0.21692949 | K8: =G8*E8/H8 -> 1.064 | L8: =G8*F8/H8 -> 0 | M8: =J8*Coefficients!$D$3 -> 7.6608 | N8: =K8 -> 1.064 | O8: =L8 -> 0 | P8: =J8*Coefficients!$D$7*Coefficients!$D$9 -> 5.4232373 | Q8: Drawing sheet 24 (brickwork 1:4)
A9: MX_MOR15 | B9: Mortar 1:5 | C9: Alternative plaster | D9: 1 | E9: 5 | F9: 0 | G9: =Coefficients!$D$11 -> 1.33 | H9: =D9+E9+F9 -> 6 | I9: =G9*D9/H9 -> 0.22166667 | J9: =I9/Coefficients!$D$8 -> 0.18077458 | K9: =G9*E9/H9 -> 1.1083333 | L9: =G9*F9/H9 -> 0 | M9: =J9*Coefficients!$D$3 -> 6.384 | N9: =K9 -> 1.1083333 | O9: =L9 -> 0 | P9: =J9*Coefficients!$D$7*Coefficients!$D$9 -> 4.5193645
A10: MX_MOR16 | B10: Mortar 1:6 | C10: 9in masonry, internal plaster | D10: 1 | E10: 6 | F10: 0 | G10: =Coefficients!$D$11 -> 1.33 | H10: =D10+E10+F10 -> 7 | I10: =G10*D10/H10 -> 0.19 | J10: =I10/Coefficients!$D$8 -> 0.15494964 | K10: =G10*E10/H10 -> 1.14 | L10: =G10*F10/H10 -> 0 | M10: =J10*Coefficients!$D$3 -> 5.472 | N10: =K10 -> 1.14 | O10: =L10 -> 0 | P10: =J10*Coefficients!$D$7*Coefficients!$D$9 -> 3.873741 | Q10: Current app (FDN-MAS-01 1:6)

Sheet Wastage_Factors
A1: Wastage_Key | B1: Default % | C1: Min % | D1: Max % | E1: Applies To | F1: Basis / Reason | G1: Materials Using Key
A2: W_CEM | B2: 0.02 | C2: 0.01 | D2: 0.03 | E2: Cement (bags) | F2: Handling, bag damage, setting in store | G2: =COUNTIF(Material_Master!$P$2:$P$1000,A2) -> 3
A3: W_SAND | B3: 0.1 | C3: 0.05 | D3: 0.15 | E3: Sand | F3: Loose delivery losses, bulking variation, spillage | G3: =COUNTIF(Material_Master!$P$2:$P$1000,A3) -> 5
A4: W_AGG | B4: 0.075 | C4: 0.05 | D4: 0.1 | E4: Crush/aggregate | F4: Spillage, over-excavated bases | G4: =COUNTIF(Material_Master!$P$2:$P$1000,A4) -> 6
A5: W_STEEL | B5: 0.03 | C5: 0.02 | D5: 0.05 | E5: Rebar (kg) | F5: Cut-offs; laps are measured separately in BBS | G5: =COUNTIF(Material_Master!$P$2:$P$1000,A5) -> 8
A6: W_BRICK | B6: 0.05 | C6: 0.03 | D6: 0.08 | E6: Bricks | F6: Breakage in transport & cutting (Class-A kiln bricks) | G6: =COUNTIF(Material_Master!$P$2:$P$1000,A6) -> 3
A7: W_BLOCK | B7: 0.03 | C7: 0.02 | D7: 0.05 | E7: Concrete blocks | F7: Breakage | G7: =COUNTIF(Material_Master!$P$2:$P$1000,A7) -> 2
A8: W_TILE_FLR | B8: 0.07 | C8: 0.05 | D8: 0.1 | E8: Floor tiles/pavers | F8: Cutting at edges; +3% for diagonal laying | G8: =COUNTIF(Material_Master!$P$2:$P$1000,A8) -> 7
A9: W_TILE_WALL | B9: 0.08 | C9: 0.05 | D9: 0.12 | E9: Wall tiles / cladding | F9: Cutting around openings & fixtures | G9: =COUNTIF(Material_Master!$P$2:$P$1000,A9) -> 3
A10: W_MARBLE | B10: 0.1 | C10: 0.08 | D10: 0.15 | E10: Marble/granite slabs | F10: Slab yield, edge cutting, veining selection | G10: =COUNTIF(Material_Master!$P$2:$P$1000,A10) -> 6
A11: W_PAINT | B11: 0.05 | C11: 0.03 | D11: 0.08 | E11: Paints/primers | F11: Can residues, roller absorption | G11: =COUNTIF(Material_Master!$P$2:$P$1000,A11) -> 13
A12: W_PUTTY | B12: 0.05 | C12: 0.03 | D12: 0.08 | E12: Wall putty | F12: Sanding loss | G12: =COUNTIF(Material_Master!$P$2:$P$1000,A12) -> 1
A13: W_WIRE | B13: 0.1 | C13: 0.05 | D13: 0.15 | E13: Building wires, LV cables | F13: Drops at boxes, DB terminations, route deviations | G13: =COUNTIF(Material_Master!$P$2:$P$1000,A13) -> 8
... A33: W_MISC | B33: 0.05 | C33: 0 | D33: 0.1 | E33: General consumables | F33: Default | G33: =COUNTIF(Material_Master!$P$2:$P$1000,A33) -> 44

Sheet Input_Dictionary
A1: Param_ID | B1: Group | C1: Description | D1: Unit | E1: Default | F1: Data Type | G1: Source in Drawing Set | H1: AI-Extractable? | I1: Validation / Typical Range | J1: Sample Project Value
A2: PROJECT_NAME | B2: Project | C2: Project name | D2: text | F2: text | G2: Title block | H2: High | I2: - | J2: 5 Marla - Mr. Sameer Shah
A3: MARLA_SFT | B3: Project | C3: Square feet per marla used by authority | D3: sft | E3: 272.25 | F3: number | G3: User / authority (CDA 272.25 vs 225 in some societies) | H3: No - user | I3: 225 or 272.25 | J3: 272.25
A4: PLOT_W | B4: Site | C4: Plot width | D4: ft | F4: number | G4: Site plan | H4: High | I4: 20-60 ft | J4: 33
A5: PLOT_D | B5: Site | C5: Plot depth | D5: ft | F5: number | G5: Site plan | H5: High | I5: 40-90 ft | J5: 41
A6: SITE_W | B6: Site | C6: Site working width (for prelims) | D6: ft | F6: number | G6: Site plan | H6: High | J6: 33
A7: SITE_D | B7: Site | C7: Site working depth | D7: ft | F7: number | G7: Site plan | H7: High | J7: 41
A8: N_FLOORS | B8: Building | C8: Number of floors (excl. mumty) | D8: Nos | E8: 2 | F8: integer | G8: Plans | H8: High | I8: 1-3 | J8: 2 + mumty
A9: H_PLINTH | B9: Levels | C9: Plinth height above road/NSL | D9: ft | E9: 1.5 | F9: number | G9: Elevations | H9: High | I9: 1-3 ft | J9: 1.5
A10: H_FLOOR | B10: Levels | C10: Floor-to-floor height | D10: ft | E10: 11.5 | F10: number | G10: Elevations/sections | H10: High | I10: 10-12.5 | J10: 11.5
A11: T_SLAB | B11: Structure | C11: Slab thickness | D11: in | E11: 6 | F11: number | G11: Elevations / structural | H11: Medium | I11: 5-7 | J11: 6
A12: H_PARAPET | B12: Levels | C12: Parapet height | D12: ft | E12: 3 | F12: number | G12: Elevations | H12: Medium | I12: 2-4 | J12: 2-3
A13: H_MUMTY | B13: Levels | C13: Mumty clear height | D13: ft | E13: 8.5 | F13: number | G13: Elevations | H13: High | I13: 7.5-9 | J13: 8.5
A14: WALL_CL_LEN | B14: Walls | C14: Centre-line length of walls by thickness (9in, 4.5in) per floor | D14: rft | F14: table | G14: Working plans | H14: Medium (vector PDF better) | I14: Check vs perimeter | J14: see Formula_Demo
A15: WALL_H | B15: Walls | C15: Wall height per floor (floor-to-soffit) | D15: ft | E15: formula: H_FLOOR-T_SLAB/12 | F15: number | G15: Derived | H15: Derived
A16: OPENINGS | B16: Openings | C16: Door/window/ventilator schedule: type, W, H, sill, count, location | D16: table | F16: table | G16: D&W sheets, chogath schedule | H16: Medium (widths often missing) | I16: W<=12 ft; H<=10 ft | J16: Doors 15 nos; window widths missing
A17: DOOR_SCHED | B17: Openings | C17: Door schedule (size, chogath width, leaf type, qty) | D17: table | F17: table | G17: Chogath sheet | H17: High | J17: sh.20
A18: ROOM | B18: Rooms | C18: Room list: name, type, floor, L, W, clear height, finish tier | D18: table | F18: table | G18: Furniture/working plans | H18: High (labels & dims printed) | I18: Area sum <= covered area | J18: see Sample_Project_Extract
A19: FDN_STRIP_LEN | B19: Foundation | C19: Strip foundation centre-line length per section type | D19: rft | F19: table | G19: Foundation plan | H19: Medium | I19: ~ wall CL length | J19: Sections 1.1-6.6
A20: FDN_SECTION | B20: Foundation | C20: Footing step widths/depths per section | D20: table | F20: table | G20: Foundation details | H20: High | J20: sh.14-15
A21: FDN_DEPTH | B21: Foundation | C21: Depth of foundation below NSL | D21: ft | E21: 3.5 | F21: number | G21: Foundation details | H21: High | I21: 2.5-5 | J21: 2.5 / 3.5
A22: FTG_ISO | B22: Foundation | C22: Isolated footings: mark, L, B, D, count | D22: table | F22: table | G22: Column/footing plan | H22: High | J22: C1 4x4; C2,C3 3x3
A23: COL | B23: Structure | C23: Columns: mark, b, d, height, count, bars | D23: table | F23: table | G23: Column schedule | H23: High | J23: C1 9x18, C2/C3 15x15
A24: BEAM | B24: Structure | C24: Beams: mark, b, d, length, bars | D24: table | F24: table | G24: Beam layout (missing) | H24: Low - missing | J24: Not provided
A25: PLINTH_BEAM | B25: Structure | C25: Plinth/tie beam length & section | D25: table | F25: table | G25: Foundation plan | H25: Low | J25: Not provided
A26: BAND_LEN | B26: Structure | C26: Seismic lintel/roof band length | D26: rft | E26: formula: WALL_CL_LEN (load-bearing) | F26: number | G26: Structural (missing) | H26: Derived | I26: Zone 2B: bands recommended | J26: Not provided
A27: SLAB | B27: Structure | C27: Slab panels: area, thickness, voids per floor | D27: table | F27: table | G27: Slab layout (missing) -> use covered area | H27: Medium | J27: Use covered area
A28: SLAB_AREA | B28: Structure | C28: Gross slab area per level | D28: sft | F28: number | G28: Area statement / plans | H28: High
A29: SLAB_VOID | B29: Structure | C29: Stair/shaft voids | D29: sft | F29: number | G29: Plans | H29: Medium
A30: STAIR | B30: Structure | C30: Stair: width, flights, risers, treads, waist, landing | D30: table | F30: table | G30: Plans/sections | H30: Medium | I30: R 6-7in; T 10-11in | J30: 12'-9 x 9' stair hall
A31: ROOF_AREA | B31: Roof | C31: Roof area requiring treatment (incl. mumty roof) | D31: sft | F31: number | G31: Mumty/roof plan | H31: High
A32: TERRACE_AREA | B32: Roof | C32: Open terraces/balconies requiring WP | D32: sft | F32: number | G32: FF plan | H32: Medium
A33: FACADE_AREA | B33: External | C33: External elevation area (net of openings) | D33: sft | F33: number | G33: Elevations | H33: Medium
A34: ELEVATIONS | B34: External | C34: Elevation cladding/feature areas by material | D34: table | F34: table | G34: Elevation working details | H34: Low (materials unlabelled)
A35: PB_FIXTURES | B35: Plumbing | C35: Fixture counts per room: WC, basin, shower, HF, sink, WM, FT | D35: table | F35: table | G35: Plumbing plans / symbols | H35: High (symbol count)
A36: PB_FT | B36: Plumbing | C36: Floor trap count | D36: Nos | F36: integer | G36: Plumbing plans | H36: High
A37: PB_GT | B37: Plumbing | C37: Gully trap count | D37: Nos | F37: integer | G37: Plumbing plans | H37: High
A38: PB_MH | B38: Plumbing | C38: Manholes: count, depth class, cover size | D38: table | F38: table | G38: Plumbing plans | H38: High
A39: MH_COUNT | B39: Plumbing | C39: Manhole count | D39: Nos | F39: integer | G39: Plumbing plans | H39: High
A40: SEWER_EXT_LEN | B40: Plumbing | C40: External sewer length (house to main) | D40: rft | F40: number | G40: Site/plumbing plan | H40: Medium
A41: RWP_COUNT | B41: Plumbing | C41: Rain-water pipes & khuras | D41: Nos | F41: integer | G41: Roof plan | H41: Medium | I41: 1 per 400-500 sft roof
A42: TANK | B42: Plumbing | C42: Tanks (UG, OH, septic): internal L,W,D, wall t, base t, slab t, bars | D42: table | F42: table | G42: Tank details | H42: High
A43: TANK_UG | B43: Plumbing | C43: UG water tank dims | D43: table | F43: table | G43: sh.16 | H43: High | J43: 3'-6 x 5'-0 / 8'-3 x 5'-6
A44: TANK_OH | B44: Plumbing | C44: OH tank type & capacity | D44: table | F44: table | G44: sh.16/23 | H44: High | J44: 600 gal FG vs RCC detail
A45: TANK_SEPTIC | B45: Plumbing | C45: Septic tank dims | D45: table | F45: table | G45: sh.16/21 | H45: High | J45: 6'-6x5' vs 8'x4'
A46: GAS_POINTS | B46: Gas | C46: Gas points (cooker, geyser, heaters) | D46: Nos | F46: integer | G46: Plumbing plans | H46: Medium
A47: EL_POINTS | B47: Electrical | C47: Point counts by symbol type per room | D47: table | F47: table | G47: Electrical plans + legend | H47: High (symbol detection)
A48: EL_DB_DIST | B48: Electrical | C48: DB locations & distances (for sub-mains) | D48: rft | F48: number | G48: Electrical plans | H48: Medium
A49: AC_UNITS | B49: HVAC | C49: Split AC count & tonnage | D49: table | F49: table | G49: Electrical symbols | H49: High | I49: 1 ton/120-150 sft
A50: EXH_FANS | B50: HVAC | C50: Exhaust fans | D50: Nos | F50: integer | G50: Electrical symbols | H50: High
A51: P_EARTH_PITS | B51: Electrical | C51: Earth pits | D51: Nos | E51: 2 | F51: integer | G51: Earthing detail | H51: Medium | I51: min 2
A52: BOUNDARY_LEN | B52: External | C52: Boundary wall length excluding shared walls | D52: rft | F52: number | G52: Site plan | H52: Medium
A53: GATE | B53: External | C53: Gate width & height | D53: ft | F53: number | G53: GF plan | H53: High | J53: ~11 ft
A54: PORCH | B54: External | C54: Porch/driveway paved area | D54: sft | F54: number | G54: GF plan | H54: High | J54: 12 x 16'-9
A55: PAVING_AREA | B55: External | C55: Other paved areas | D55: sft | F55: number | G55: Site plan | H55: Medium
A56: BALCONY | B56: Architecture | C56: Balcony areas & railing length | D56: table | F56: table | G56: FF plan | H56: Medium
A57: WARDROBE | B57: Joinery | C57: Wardrobes: W x H x D, count | D57: table | F57: table | G57: Furniture plans | H57: High (label)
A58: RWH | B58: External | C58: Recharge well required? depth | D58: Y/N + ft | E58: Y / 100 | F58: text | G58: Authority rule (not in drawings) | H58: No - user | I58: CDA by-law
A59: NGL | B59: Levels | C59: Natural ground level vs road | D59: ft | E59: 0 | F59: number | G59: Survey (missing) | H59: No
A60: P_WORKSPACE | B60: Assumption | C60: Working space each side in excavation | D60: ft | E60: 0.5 | F60: number | G60: Assumption | H60: - | I60: 0.5-1
A61: P_BEARING | B61: Assumption | C61: Bearing of lintels beyond opening each side | D61: in | E61: 6 | F61: number | G61: Assumption | H61: - | I61: 6-9
A62: P_BULKING | B62: Assumption | C62: Sand bulking allowance (if volume batching) | D62: % | E62: 0 | F62: number | G62: Assumption | H62: - | I62: 0-25% (included in dry factor)
A63: P_SAND_FILL_T | B63: Assumption | C63: Sand fill under GF floor | D63: in | E63: 3 | F63: number | G63: Assumption | H63: - | I63: 3-4
A64: P_FLOOR_PCC_T | B64: Assumption | C64: GF floor PCC thickness | D64: in | E64: 3 | F64: number | G64: Assumption | H64: - | I64: 3-4
A65: T_FLOOR_BUILDUP | B65: Assumption | C65: Floor build-up above fill (soling+PCC+screed+finish) | D65: in | E65: 9 | F65: number | G65: Derived | H65: -
A66: P_APRON_W | B66: Assumption | C66: Plinth protection apron width | D66: ft | E66: 2.5 | F66: number | G66: Assumption | H66: - | I66: 2-3
A67: FINISH_TIER | B67: Project | C67: Finish tier: Economy / Standard / Premium | D67: text | E67: Standard | F67: enum | G67: User | H67: No
A68: CONC_MODE | B68: Project | C68: Concrete: site-mix nominal or RMC design mix | D68: text | E68: Site-mix | F68: enum | G68: User | H68: No
A69: STRUCT_SYSTEM | B69: Project | C69: Load-bearing masonry / RCC frame / confined masonry | D69: text | E69: Load-bearing + RCC slabs | F69: enum | G69: Drawings + user | H69: Medium
A70: GAS_SOURCE | B70: Project | C70: SNGPL / LPG / none | D70: text | E70: LPG | F70: enum | G70: User | H70: No

Sheet Element_Library
A1: Element_ID | B1: Element | C1: Scope | D1: Detected From | E1: Key Attributes to Extract | F1: Drives Work Items | G1: AI Detection Method | H1: Default Confidence | I1: Notes
A2: E-SITE | B2: Plot / site boundary | C2: Complete | D2: Site plan | E2: W, D, road side, shared walls | F2: WI-PRE-01, WI-EX-01 | G2: OCR dims on site plan | H2: High
A3: E-ROOM | B3: Room / space | C3: Architecture | D3: Furniture & working plans | E3: name, type, L, W, floor, height | F3: WI-FL-*, WI-PL-*, WI-PT-*, WI-CL-01 | G3: OCR room label 'NAME LxW' + keyword map to Room_Finish_Defaults | H3: High | I3: Sample labels follow 'NAME 12'-0''x13'-0''' pattern
A4: E-WALL9 | B4: External/load-bearing wall 9in | C4: Structure | D4: Working plans | E4: CL length, height, floor, openings | F4: WI-MS-01, WI-PL-01/02, WI-PT-01/03 | G4: Vector line pairs at 9in spacing; or thickness dims | H4: Medium
A5: E-WALL45 | B5: Partition wall 4.5in | C5: Architecture | D5: Working plans | E5: CL length, height | F5: WI-MS-02, WI-PL-01 | G5: Line pairs at 4.5in | H5: Medium
A6: E-PARAPET | B6: Parapet wall | C6: Structure | D6: Elevations/roof | E6: length=roof perimeter, height | F6: WI-MS-01/02, WI-PL-02 | G6: Roof perimeter x H_PARAPET | H6: High
A7: E-FDN-STRIP | B7: Stepped brick strip footing | C7: Structure | D7: Foundation details | E7: section id, steps (w,h), PCC w/t, length | F7: WI-EW-01, WI-CN-01, WI-MS-03 | G7: Section table OCR + wall CL mapping | H7: Medium | I7: Sections 1.1-6.6 in sample
A8: E-FTG-ISO | B8: Isolated column footing | C8: Structure | D8: Foundation details | E8: L, B, D, bars, count | F8: WI-EW-02, WI-CN-03, WI-RF-*, WI-FW-* | G8: Column plan OCR | H8: High | I8: C1 4'x4', C2/C3 3'x3'
A9: E-COL | B9: RCC column | C9: Structure | D9: Foundation/column details | E9: b, d, H, bars, ties | F9: WI-CN-04, WI-RF-02, WI-FW-01 | G9: Schedule OCR | H9: High
A10: E-BEAM | B10: RCC beam / plinth beam | C10: Structure | D10: Structural layout (missing in sample) | E10: b, d, L, bars | F10: WI-CN-05, WI-RF-03 | G10: Structural sheet or rule-based default | H10: Low | I10: Missing in sample -> engineer input
A11: E-BAND | B11: Seismic lintel/roof band | C11: Structure | D11: Structural (missing) | E11: b, d, L | F11: WI-CN-08, WI-RF-06 | G11: Rule: wall CL of load-bearing walls | H11: Derived | I11: BCP zone 2B
A12: E-LINTEL | B12: Lintel over opening | C12: Structure | D12: D&W sheets | E12: opening W + 2 bearings, wall t | F12: WI-CN-08, WI-RF-06 | G12: From each opening | H12: Derived
A13: E-SLAB | B13: RCC slab | C13: Structure | D13: Plans / area statement | E13: area, t, voids | F13: WI-CN-06, WI-RF-04, WI-FW-01 | G13: Covered area minus voids | H13: Medium
A14: E-STAIR | B14: RCC stair | C14: Structure | D14: Plans | E14: width, flights, R, T, waist | F14: WI-CN-07, WI-RF-05, WI-FL-* | G14: Stair symbol + 'UP/DN' + hall dims | H14: Medium
A15: E-DPC | B15: Damp proof course | C15: Structure | D15: Foundation details | E15: wall CL length at plinth, width | F15: WI-WP-01 | G15: All walls at plinth | H15: High | I15: 1.5-2in PCC 1:2:4 + bitumen + polythene
A16: E-ROOF | B16: Roof / terrace | C16: Architecture | D16: Mumty / roof plan | E16: area, slopes, outlets | F16: WI-WP-02/03, WI-PB-09/10 | G16: Roof outline area | H16: High
A17: E-DOOR | B17: Door | C17: Architecture | D17: D&W + chogath schedule | E17: W, H, chogath width, leaf type, count | F17: WI-DW-01..03, WI-PT-04 | G17: Schedule OCR + plan swing symbols | H17: High
A18: E-WINDOW | B18: Window / ventilator | C18: Architecture | D18: D&W sheets | E18: W, H, sill, type, glass | F18: WI-DW-04..06 | G18: Sill/height tags + measured widths | H18: Medium | I18: Sample lacks widths
A19: E-WARDROBE | B19: Wardrobe / built-in | C19: Architecture | D19: Furniture plan | E19: W, H, D | F19: WI-JN-01 | G19: Label 'WARDROBE' + measured length | H19: Medium
A20: E-KITCHEN | B20: Kitchen cabinets & counter | C20: Kitchen | D20: Furniture plan | E20: counter rft, upper rft, appliances | F20: WI-KT-01..03 | G20: Room type = kitchen + counter polyline | H20: Medium
A21: E-BATH | B21: Bathroom group | C21: Plumbing | D21: Plumbing plans | E21: WC, basin, shower, FT, HF | F21: WI-PB-01..06 | G21: Symbol detection in bath room polygon | H21: High
A22: E-FT | B22: Floor trap | C22: Plumbing | D22: Plumbing plans | E22: count | F22: WI-PB-05 | G22: Text 'F.T' | H22: High
A23: E-MH | B23: Manhole | C23: Plumbing | D23: Plumbing plans | E23: count, depth, cover | F23: WI-PB-12 | G23: Text 'M.H' | H23: High
A24: E-GT | B24: Gully trap | C24: Plumbing | D24: Plumbing plans | E24: count | F24: WI-PB-13 | G24: Text 'G.T' | H24: High
A25: E-SEWER | B25: External sewer line | C25: Plumbing | D25: Site/plumbing plan | E25: length, dia, depth | F25: WI-PB-11, WI-EW-03 | G25: Polyline length | H25: Medium
A26: E-RWP | B26: Rainwater pipe & khura | C26: Plumbing | D26: Roof plan / details | E26: count, height | F26: WI-PB-09/10 | G26: Roof outlets / 'SLOPE' arrows | H26: Medium
A27: E-TANK-UG | B27: Underground water tank | C27: Plumbing | D27: Tank details | E27: dims, t, bars | F27: WI-EW-03, WI-CN-10, WI-RF-07 | G27: Detail OCR | H27: High
A28: E-TANK-OH | B28: Overhead tank | C28: Plumbing | D28: Mumty plumbing / tank detail | E28: type, capacity | F28: WI-PB-14 / WI-CN-10 | G28: Label '600 GAL' | H28: High
A29: E-SEPTIC | B29: Septic tank | C29: Plumbing | D29: Tank details | E29: dims | F29: WI-CN-10 | G29: Detail OCR | H29: High
A30: E-RISER | B30: Water/gas risers | C30: Plumbing | D30: Plumbing details | E30: sizes, heights | F30: WI-PB-14, WI-GS-01 | G30: Riser legend OCR | H30: Medium
... A45: E-RAILING | B45: Railings | C45: Architecture | D45: Plans/elevations | E45: length | F45: EXT-011 | G45: Balcony/stair edges | H45: Medium
A46: E-FACADE | B46: Elevation feature / cladding | C46: Architecture | D46: Elevations | E46: areas by material | F46: EXT-010, WI-PT-03 | G46: Elevation regions | H46: Low | I46: Materials not labelled
A47: E-RWH | B47: Recharge well | C47: External | D47: Not in drawings | E47: count, depth | F47: WI-EX-02 | G47: Authority rule | H47: Rule-based

Sheet Room_Finish_Defaults
A1: Room Type | B1: Label Keywords (AI matching) | C1: Floor Finish | D1: Skirting | E1: Wall Finish | F1: Wall Tile Height (ft) | G1: Ceiling Finish | H1: False Ceiling % of Area | I1: Light Pts | J1: Fan Pts | K1: 13A Sockets | L1: 15A/Power Pts | M1: AC Pts | N1: TV Pts | O1: Data Pts | P1: Exhaust Fans | Q1: WC | R1: Basin | S1: Shower | T1: Health Faucet | U1: Sink | V1: Floor Traps | W1: Notes
A2: Bedroom | B2: BED, BEDROOM, MASTER BED, KIDS, GUEST | C2: Porcelain/ceramic tile 24x24 (or wood-look) | D2: Tile 4in | E2: Putty + emulsion | F2: 0 | G2: Emulsion; gypsum bulkhead optional | H2: 0.3 | I2: 4 | J2: 1 | K2: 4 | L2: 0 | M2: 1 | N2: 1 | O2: 1 | P2: 0 | Q2: 0 | R2: 0 | S2: 0 | T2: 0 | U2: 0 | V2: 0 | W2: Wardrobe per plan
A3: Drawing room | B3: DRAWING, SITTING, GUEST ROOM | C3: Marble/porcelain 24x48 | D3: Marble/tile 4in | E3: Putty + emulsion / feature wall | F3: 0 | G3: Gypsum false ceiling + cornice | H3: 0.6 | I3: 6 | J3: 1 | K3: 4 | L3: 0 | M3: 1 | N3: 1 | O3: 1 | P3: 0 | Q3: 0 | R3: 0 | S3: 0 | T3: 0 | U3: 0 | V3: 0 | W3: Chandelier point typical
A4: Lounge / TV lounge | B4: LOUNGE, TV LOUNGE, FAMILY, LIVING | C4: Porcelain 24x24/24x48 | D4: Tile 4in | E4: Putty + emulsion | F4: 0 | G4: Gypsum partial | H4: 0.4 | I4: 6 | J4: 1 | K4: 5 | L4: 0 | M4: 1 | N4: 1 | O4: 1 | P4: 0 | Q4: 0 | R4: 0 | S4: 0 | T4: 0 | U4: 0 | V4: 0 | W4: Intercom indoor unit
A5: Kitchen | B5: KITCHEN | C5: Porcelain anti-skid 24x24 | D5: Tile 4in | E5: Wall tile behind counter to 2 ft above counter; rest emulsion | F5: 2 | G5: PVC/gypsum MR or emulsion | H5: 0.5 | I5: 3 | J5: 0 | K5: 4 | L5: 2 | M5: 0 | N5: 0 | O5: 0 | P5: 1 | Q5: 0 | R5: 0 | S5: 0 | T5: 0 | U5: 1 | V5: 1 | W5: Cooker & fridge sockets; gas point; hood duct
A6: Bathroom | B6: BATH, TOILET, WASHROOM, WC | C6: Anti-skid ceramic/porcelain | D6: Nil (full-height wall tile) | E6: Wall tiles full height (7-8 ft) | F6: 8 | G6: PVC/aluminium or MR gypsum | H6: 1 | I6: 2 | J6: 0 | K6: 0 | L6: 1 | M6: 0 | N6: 0 | O6: 0 | P6: 1 | Q6: 1 | R6: 1 | S6: 1 | T6: 1 | U6: 0 | V6: 2 | W6: Geyser point; waterproofing floor + 12in up walls
A7: Laundry | B7: LAUNDRY, WASH AREA | C7: Anti-skid tile | D7: Tile 4in | E7: Tile dado 4 ft | F7: 4 | G7: Emulsion | H7: 0 | I7: 1 | J7: 0 | K7: 1 | L7: 1 | M7: 0 | N7: 0 | O7: 0 | P7: 1 | Q7: 0 | R7: 0 | S7: 0 | T7: 0 | U7: 0 | V7: 1 | W7: Washing machine point
A8: Staircase | B8: STAIR, STAIRCASE | C8: Marble/granite treads & risers | D8: Marble skirting (stepped) | E8: Putty + emulsion | F8: 0 | G8: Emulsion | H8: 0 | I8: 3 | J8: 0 | K8: 1 | L8: 0 | M8: 0 | N8: 0 | O8: 0 | P8: 0 | Q8: 0 | R8: 0 | S8: 0 | T8: 0 | U8: 0 | V8: 0 | W8: 2-way switching; step lights; railing
A9: Porch / car porch | B9: PORCH, CAR PORCH, GARAGE | C9: Pavers / anti-skid outdoor tile | D9: - | E9: Exterior finish | F9: 0 | G9: Exterior emulsion | H9: 0 | I9: 2 | J9: 0 | K9: 1 | L9: 1 | M9: 0 | N9: 0 | O9: 0 | P9: 0 | Q9: 0 | R9: 0 | S9: 0 | T9: 0 | U9: 0 | V9: 1 | W9: WP lights; garden tap; gate
A10: Terrace / balcony | B10: TERRACE, BALCONY | C10: Outdoor tile on WP membrane | D10: Tile 4in | E10: Exterior finish | F10: 0 | G10: - | H10: 0 | I10: 1 | J10: 0 | K10: 1 | L10: 0 | M10: 0 | N10: 0 | O10: 0 | P10: 0 | Q10: 0 | R10: 0 | S10: 0 | T10: 0 | U10: 0 | V10: 1 | W10: Railing; WP; floor trap
A11: Mumty | B11: MUMTY, STAIR ROOM | C11: Tile / cement finish | D11: Tile 4in | E11: Emulsion | F11: 0 | G11: Emulsion | H11: 0 | I11: 1 | J11: 0 | K11: 1 | L11: 0 | M11: 0 | N11: 0 | O11: 0 | P11: 0 | Q11: 0 | R11: 0 | S11: 0 | T11: 0 | U11: 0 | V11: 0 | W11: Door to roof; OH tank nearby
A12: Store / utility | B12: STORE, UTILITY | C12: Tile | D12: Tile 4in | E12: Emulsion | F12: 0 | G12: Emulsion | H12: 0 | I12: 1 | J12: 0 | K12: 1 | L12: 0 | M12: 0 | N12: 0 | O12: 0 | P12: 0 | Q12: 0 | R12: 0 | S12: 0 | T12: 0 | U12: 0 | V12: 0
A13: Servant quarter | B13: SERVANT, SQ | C13: Tile | D13: Tile 4in | E13: Emulsion | F13: 0 | G13: Emulsion | H13: 0 | I13: 2 | J13: 1 | K13: 2 | L13: 0 | M13: 0 | N13: 0 | O13: 0 | P13: 0 | Q13: 0 | R13: 0 | S13: 0 | T13: 0 | U13: 0 | V13: 0 | W13: Often with attached bath
A14: Planter / lawn | B14: PLANTER, LAWN, GARDEN | C14: Soil + grass | D14: - | E14: - | F14: 0 | G14: - | H14: 0 | I14: 1 | J14: 0 | K14: 0 | L14: 0 | M14: 0 | N14: 0 | O14: 0 | P14: 0 | Q14: 0 | R14: 0 | S14: 0 | T14: 0 | U14: 0 | V14: 0 | W14: Garden tap; drain D-1

Sheet Scope_Map
A1: Category | B1: Architecture | C1: Structure | D1: Electrical | E1: Plumbing | F1: HVAC | G1: External Works | H1: Complete Project | I1: Grey Structure (PK) | J1: Finishing (PK) | K1: No. of Materials
A2: Preliminaries & Site | B2: Y | C2: Y | D2: - | E2: - | F2: - | G2: - | H2: Y | I2: Y | J2: - | K2: =COUNTIF(Material_Master!$B$2:$B$1000,A2) -> 7
A3: Earthwork & Site Prep | B3: - | C3: Y | D3: - | E3: P | F3: - | G3: P | H3: Y | I3: Y | J3: - | K3: =COUNTIF(Material_Master!$B$2:$B$1000,A3) -> 7
A4: Concrete & Aggregates | B4: - | C4: Y | D4: - | E4: P | F4: - | G4: P | H4: Y | I4: Y | J4: - | K4: =COUNTIF(Material_Master!$B$2:$B$1000,A4) -> 14
A5: Reinforcement & Steel | B5: - | C5: Y | D5: - | E5: P | F5: - | G5: P | H5: Y | I5: Y | J5: - | K5: =COUNTIF(Material_Master!$B$2:$B$1000,A5) -> 9
A6: Formwork & Temporary Works | B6: - | C6: Y | D6: - | E6: - | F6: - | G6: - | H6: Y | I6: Y | J6: - | K6: =COUNTIF(Material_Master!$B$2:$B$1000,A6) -> 8
A7: Masonry | B7: P | C7: Y | D7: - | E7: P | F7: - | G7: P | H7: Y | I7: Y | J7: - | K7: =COUNTIF(Material_Master!$B$2:$B$1000,A7) -> 12
A8: Plaster & Screeds | B8: Y | C8: - | D8: - | E8: - | F8: - | G8: P | H8: Y | I8: Y | J8: - | K8: =COUNTIF(Material_Master!$B$2:$B$1000,A8) -> 6
A9: Waterproofing, DPC & Insulation | B9: Y | C9: Y | D9: - | E9: P | F9: - | G9: - | H9: Y | I9: Y | J9: P | K9: =COUNTIF(Material_Master!$B$2:$B$1000,A9) -> 14
A10: Flooring & Tiling | B10: Y | C10: - | D10: - | E10: - | F10: - | G10: P | H10: Y | I10: - | J10: Y | K10: =COUNTIF(Material_Master!$B$2:$B$1000,A10) -> 16
A11: Doors, Windows & Glazing | B11: Y | C11: - | D11: - | E11: - | F11: - | G11: - | H11: Y | I11: P | J11: Y | K11: =COUNTIF(Material_Master!$B$2:$B$1000,A11) -> 18
A12: Ceilings & Partitions | B12: Y | C12: - | D12: - | E12: - | F12: - | G12: - | H12: Y | I12: - | J12: Y | K12: =COUNTIF(Material_Master!$B$2:$B$1000,A12) -> 6
A13: Paints & Coatings | B13: Y | C13: - | D13: - | E13: - | F13: - | G13: P | H13: Y | I13: - | J13: Y | K13: =COUNTIF(Material_Master!$B$2:$B$1000,A13) -> 13
... A26: Miscellaneous & Consumables | B26: Y | C26: Y | D26: Y | E26: Y | F26: Y | G26: Y | H26: Y | I26: Y | J26: Y | K26: =COUNTIF(Material_Master!$B$2:$B$1000,A26) -> 9
A27: TOTAL | K27: =SUM(K2:K26) -> 309
A29: Legend: Y = included; P = partial (only items tagged with that Scope in Material_Master col K); - = excluded. 'Grey Structure' and 'Finishing' are the two standard Pakistani contract packages.

Sheet Stages
A1: Stage | B1: Name | C1: Typical Activities / Procurement Triggers | D1: Materials in Stage
A2: S0 | B2: Pre-construction / preliminaries | C2: Approvals, site setup, surveys, soil test | D2: =COUNTIF(Material_Master!$R$2:$R$1000,"*"&A2&"*") -> 9
A3: S1 | B3: Substructure | C3: Excavation, anti-termite, PCC, foundations, DPC, earthing pits, UG/septic tanks | D3: =COUNTIF(Material_Master!$R$2:$R$1000,"*"&A3&"*") -> 33
A4: S2 | B4: MEP rough-in (below slab / in-wall first fix) | C4: Soil/waste under floor, concealed cisterns, mixer bodies, gas pipes, sleeves | D4: =COUNTIF(Material_Master!$R$2:$R$1000,"*"&A4&"*") -> 45
A5: S3 | B5: Superstructure masonry | C5: Brickwork, lintels, sills, AC sleeves, window frames if built-in | D5: =COUNTIF(Material_Master!$R$2:$R$1000,"*"&A5&"*") -> 16
A6: S4 | B6: RCC frame & slabs | C6: Columns, beams, slabs, stairs, slab conduits, fan hooks, sleeves | D6: =COUNTIF(Material_Master!$R$2:$R$1000,"*"&A6&"*") -> 21
A7: S5 | B7: Second-fix MEP in walls | C7: Wall chasing, conduits, PPR, AC pre-piping | D7: =COUNTIF(Material_Master!$R$2:$R$1000,"*"&A7&"*") -> 15
A8: S6 | B8: Finishes (wet trades) | C8: Plaster, screeds, waterproofing, tiling, marble, ceilings, paint, wiring pull | D8: =COUNTIF(Material_Master!$R$2:$R$1000,"*"&A8&"*") -> 83
A9: S7 | B9: Roof & external envelope | C9: Roof treatment, parapets, RWP, OH tank, elevation cladding, railings | D9: =COUNTIF(Material_Master!$R$2:$R$1000,"*"&A9&"*") -> 25
A10: S8 | B10: External works & services | C10: Sewer, manholes, boundary wall, paving, RWH, meter, gate | D10: =COUNTIF(Material_Master!$R$2:$R$1000,"*"&A10&"*") -> 44
A11: S9 | B11: Fixtures & handover | C11: Sanitaryware, CP, switches, lights, doors hardware, cleaning, testing | D11: =COUNTIF(Material_Master!$R$2:$R$1000,"*"&A11&"*") -> 46

Sheet Calc_Methods
A1: Formula_Key | B1: Meaning | C1: When Used | D1: Example | E1: Engine Notes
A2: RECIPE | B2: Material qty = Σ over linked work items (WI qty × coefficient) × (1 + wastage) | C2: Default when Formula_Key blank. Coefficients in Recipes sheet (live formulas). | D2: CON-001 cement = Σ(WI-CN-xx cft × bags/cft) × 1.02 | E2: Engine: join Work_Items → Recipes → Material_Master
A3: AREA(x) | B3: Area measured from drawing object x (sft) | C3: Rooms, roofs, paved areas, elevation panels | D3: AREA(room|wet) = Σ L×W of rooms where wet=TRUE | E3: Filter expression after '|'
A4: LEN(x) | B4: Length measured (rft) | C4: Walls CL, sewer, boundary, railing, skirting | D4: LEN(boundary) = plot perimeter − shared − front | E4: Use centre-line for masonry, clear length for finishes
A5: VOL(x) | B5: Volume (cft) | C5: Tanks, footings, concrete elements | D5: VOL(tank) = walls + base + cover slab | E5: Deductions per Measurement rule in Work_Items
A6: COUNT(x) | B6: Count of symbols/labels/schedule rows | C6: Doors, fixtures, electrical points | D6: COUNT(F.T) on plumbing plans | E6: AI symbol detection must be verified by user
A7: BBS(x) | B7: Bar bending schedule (kg) from bar dia, spacing, cover, laps, hooks | C7: Tanks, slabs, footings when detailed | D7: kg = Σ n × cut_len × d²/162 (d in mm, kg/m) ×3.281 | E7: Fallback = steel ratio kg/cft (K_ST_*)
A8: PCT(scope,p) | B8: Percentage of another group | C8: Consumables, small fittings | D8: PCT(EL,2%) | E8: Only for low-value items
A9: LS | B9: Lump sum / provisional | C9: Approvals, testing, cleaning | D9: LS | E9: Not quantity-driven; carried as PC/provisional sum
A10: INPUT | B10: User-provided quantity | C10: Solar kW, CCTV cameras | D10: INPUT(solar_kW) | E10: Collected in Select-Scope step
A11: K*COUNT | B11: Coefficient × count | C11: Boring depth × wells | D11: K_RWH_DEPTH × COUNT(well)
A12: Measurement rules | B12: Deductions | C12: Openings > 4 sft deducted from masonry & plaster (PK practice / PWD); openings ≤ 4 sft not deducted; plaster reveals added; paint = plaster area; tile skirting = room perimeter − door widths | E12: Store as parameters so the rule can be switched (e.g., PEC/PWD vs SMM7/NRM)

Sheet Units
A1: Unit | B1: Name | C1: SI Unit | D1: Factor to SI | E1: Used For
A2: cft | B2: cubic foot | C2: m3 | D2: 0.0283168 | E2: Concrete, earthwork, sand, crush
A3: sft | B3: square foot | C3: m2 | D3: 0.092903 | E3: Areas
A4: rft | B4: running foot | C4: m | D4: 0.3048 | E4: Lengths
A5: m | B5: metre | C5: m | D5: 1 | E5: Wires/cables
A6: kg | B6: kilogram | C6: kg | D6: 1 | E6: Steel, putty, adhesive
A7: ton | B7: metric tonne | C7: kg | D7: 1000 | E7: Steel procurement
A8: bag | B8: cement bag 50 kg | C8: kg | D8: 50 | E8: Cement
A9: Nos | B9: number | C9: - | D9: 1 | E9: Counted items
A10: set | B10: set | C10: - | D10: 1 | E10: Assemblies
A11: gal | B11: PK paint gallon ~3.64 L / Imperial gal 4.546 L (water) | C11: L | D11: 3.64 | E11: Paint (check pack); water uses 4.546
A12: L | B12: litre | C12: L | D12: 1 | E12: Liquids
A13: coil | B13: wire coil ~90 m | C13: m | D13: 90 | E13: Wire procurement
... A22: psi | B22: pound per sq inch | C22: MPa | D22: 0.006895 | E22: Concrete strength

Sheet Drawing_Checklist
A1: Required Drawing / Information | B1: Sheet Type | C1: Needed For | D1: Present in Sample Set? | E1: Fallback if Missing
A2: Site plan with plot dims, setbacks, road side, shared walls | B2: Site plan | C2: Boundary wall, paving, sewer route, RWH | D2: Partial (dims only) | E2: User input
A3: Area statement (covered area per floor) | B3: Site plan | C3: Slab area checks, benchmarks | D3: Yes (inconsistent) | E3: Compute from plans
A4: Furniture plans with room names & sizes | B4: Arch plans | C4: Room finishes, MEP defaults | D4: Yes | E4: -
A5: Working plans with all wall dimensions & thickness | B5: Arch plans | C5: Masonry, plaster, DPC | D5: Yes | E5: -
A6: Building sections (levels, slab/beam depths, stair) | B6: Sections | C6: Heights, stairs, parapets | D6: No | E6: Use elevations + defaults
A7: Elevations with material callouts | B7: Elevations | C7: External finishes, cladding | D7: Partial (no materials) | E7: Tier defaults
A8: Door & window schedule with W x H x type x glass x hardware | B8: Schedules | C8: Doors/windows/glazing | D8: Partial (door sizes; windows sill/height only) | E8: Measure widths from plan
A9: Finishes schedule (floor/wall/ceiling per room) | B9: Schedules | C9: Finishes | D9: No | E9: Room_Finish_Defaults
A10: Reflected ceiling plans | B10: Ceilings | C10: False ceiling, lights | D10: No | E10: FC % defaults
A11: Foundation plan + sections | B11: Structure | C11: Excavation, PCC, footings | D11: Yes (sections) | E11: -
A12: Structural framing: beams, slabs, lintels, bands, stair reinforcement | B12: Structure | C12: Concrete & steel | D12: No | E12: Steel ratios; engineer review
... A25: Specifications / material notes | B25: Specs | C25: Grades & brands | D25: Partial (plumbing notes) | E25: Tier defaults

Sheet Sample_Project_Extract
A1: Floor | B1: Room (as labelled) | C1: Room Type | D1: L ft | E1: L in | F1: W ft | G1: W in | H1: Length (ft) | I1: Width (ft) | J1: Area (sft) | K1: Perimeter (rft) | L1: Source Sheet | M1: Confidence
A2: GF | B2: DRAWING | C2: Drawing room | D2: 13 | E2: 4 | F2: 8 | G2: 9 | H2: =D2+E2/12 -> 13.333333 | I2: =F2+G2/12 -> 8.75 | J2: =H2*I2 -> 116.66667 | K2: =2*(H2+I2) -> 44.166667 | L2: sh.2-3 / 8-9 | M2: High
A3: GF | B3: LOUNGE | C3: Lounge / TV lounge | D3: 18 | E3: 10 | F3: 9 | G3: 5 | H3: =D3+E3/12 -> 18.833333 | I3: =F3+G3/12 -> 9.4166667 | J3: =H3*I3 -> 177.34722 | K3: =2*(H3+I3) -> 56.5 | L3: sh.2-3 / 8-9 | M3: High
A4: GF | B4: KIDS ROOM | C4: Bedroom | D4: 10 | E4: 3 | F4: 12 | G4: 6 | H4: =D4+E4/12 -> 10.25 | I4: =F4+G4/12 -> 12.5 | J4: =H4*I4 -> 128.125 | K4: =2*(H4+I4) -> 45.5 | L4: sh.2-3 / 8-9 | M4: High
A5: GF | B5: BED ROOM | C5: Bedroom | D5: 12 | E5: 0 | F5: 13 | G5: 0 | H5: =D5+E5/12 -> 12 | I5: =F5+G5/12 -> 13 | J5: =H5*I5 -> 156 | K5: =2*(H5+I5) -> 50 | L5: sh.2-3 / 8-9 | M5: High
A6: GF | B6: BATH (1) | C6: Bathroom | D6: 9 | E6: 10 | F6: 4 | G6: 6 | H6: =D6+E6/12 -> 9.8333333 | I6: =F6+G6/12 -> 4.5 | J6: =H6*I6 -> 44.25 | K6: =2*(H6+I6) -> 28.666667 | L6: sh.2-3 / 8-9 | M6: High
